Workbook

Sheet IIRUP
A1: PAR Number | B1: Series Number | C1: Article | D1: Property Number | E1: Type of Properties | F1: Brand | G1: Model | H1: Serial Number | I1: Processor | J1: RAM | K1: Storage | L1: Color | M1: Other Description | N1: Unit of Measure | O1: Unit Value | P1: Total Value | Q1: Value Category | R1: Qty | PCard | S1: Qty | PCount | T1: S|O Qty | U1: S|O Value | V1: Date of Acquisition | W1: Location | X1: Accountable Person | Y1: Position | Z1: Source of Fund | AA1: Full Specifications | AB1: Issued ICS
B2: 1 | C2: Furniture and Fixture | D2: =CONCATENATE(TEXT(Table164[[#This Row],[Date of Acquisition]],"yyyy")," - ", VLOOKUP(Table164[[#This Row],[Article]],'Data Validation'!$A$2:$B$16,2,FALSE)," - ",TEXT(Table164[[#This Row],[Series Number]],"0000")," - ",TEXT(VLOOKUP(Table164[[#This Row],[Location]],'Data Validation'!$A$20:$B$47,2,FALSE),"00")) -> 2010 - 07 - 01 - 0001 - 01A | E2: Frame Chalk & Eraser Holder Kiln Dried Size | F2: n|a | G2: n|a | H2: n|a | I2: n|a | J2: n|a | K2: n|a | L2: n|a | M2: Frame Chalk & Eraser Holder Kiln Dried Size | N2: unit | O2: 50000 | P2: =Table164[[#This Row],[Unit Value]]*Table164[[#This Row],[Qty | PCount]] -> 50000 | Q2: =IF(Table164[[#This Row],[Unit Value]]<=4999,"Low-Value Asset","High-Value Asset") -> High-Value Asset | R2: 1 | S2: 1 | T2: 0 | U2: 0 | V2: 40513 | W2: 001A - Office of the School Division Superintendent | X2: - | Y2: - | Z2: Unserviceable | AA2: =CONCATENATE(Table164[[#This Row],[Other Description]]," - ",IF(Table164[[#This Row],[Brand]]="n|a","",CONCATENATE("Brand: ",Table164[[#This Row],[Brand]]," - ")),IF(Table164[[#This Row],[Model]]="n|a","",CONCATENATE("Model: ",Table164[[#This Row],[Model]]," - ")),IF(Table164[[#This Row],[Serial Number]]="n|a","",CONCATENATE("SN: ",Table164[[#This Row],[Serial Number]]," - ")),IF(Table164[[#This Row],[Processor]]="n|a","",CONCATENATE("Processor: ",Table164[[#This Row],[Processor]]," - ")),IF(Table164[[#This Row],[RAM]]="n|a","",CONCATENATE("RAM: ",Table164[[#This Row],[RAM]]," - ")),IF(Table164[[#This Row],[Storage]]="n|a","",CONCATENATE("Storage: ",Table164[[#This Row],[Storage]]," - ")),IF(Table164[[#This Row],[Color]]="n|a","",CONCATENATE("Color: ",Table164[[#This Row],[Color]]))) -> Frame Chalk & Eraser Holder Kiln Dried Size -
B3: 1 | C3: Furniture and Fixture | D3: =CONCATENATE(TEXT(Table164[[#This Row],[Date of Acquisition]],"yyyy")," - ", VLOOKUP(Table164[[#This Row],[Article]],'Data Validation'!$A$2:$B$16,2,FALSE)," - ",TEXT(Table164[[#This Row],[Series Number]],"0000")," - ",TEXT(VLOOKUP(Table164[[#This Row],[Location]],'Data Validation'!$A$20:$B$47,2,FALSE),"00")) -> 2017 - 07 - 01 - 0001 - 01A | E3: Electronic Magnifying Glass (SPED) | F3: n|a | G3: n|a | H3: n|a | I3: n|a | J3: n|a | K3: n|a | L3: n|a | M3: Electronic Magnifying Glass (SPED) | N3: unit | O3: 56817 | P3: =Table164[[#This Row],[Unit Value]]*Table164[[#This Row],[Qty | PCount]] -> 56817 | Q3: =IF(Table164[[#This Row],[Unit Value]]<=4999,"Low-Value Asset","High-Value Asset") -> High-Value Asset | R3: 1 | S3: 1 | T3: 0 | U3: 0 | V3: 43070 | W3: 001A - Office of the School Division Superintendent | X3: - | Y3: - | Z3: Unserviceable | AA3: =CONCATENATE(Table164[[#This Row],[Other Description]]," - ",IF(Table164[[#This Row],[Brand]]="n|a","",CONCATENATE("Brand: ",Table164[[#This Row],[Brand]]," - ")),IF(Table164[[#This Row],[Model]]="n|a","",CONCATENATE("Model: ",Table164[[#This Row],[Model]]," - ")),IF(Table164[[#This Row],[Serial Number]]="n|a","",CONCATENATE("SN: ",Table164[[#This Row],[Serial Number]]," - ")),IF(Table164[[#This Row],[Processor]]="n|a","",CONCATENATE("Processor: ",Table164[[#This Row],[Processor]]," - ")),IF(Table164[[#This Row],[RAM]]="n|a","",CONCATENATE("RAM: ",Table164[[#This Row],[RAM]]," - ")),IF(Table164[[#This Row],[Storage]]="n|a","",CONCATENATE("Storage: ",Table164[[#This Row],[Storage]]," - ")),IF(Table164[[#This Row],[Color]]="n|a","",CONCATENATE("Color: ",Table164[[#This Row],[Color]]))) -> Electronic Magnifying Glass (SPED) -
B4: 1 | C4: ICT Equipment | D4: =CONCATENATE(TEXT(Table164[[#This Row],[Date of Acquisition]],"yyyy")," - ", VLOOKUP(Table164[[#This Row],[Article]],'Data Validation'!$A$2:$B$16,2,FALSE)," - ",TEXT(Table164[[#This Row],[Series Number]],"0000")," - ",TEXT(VLOOKUP(Table164[[#This Row],[Location]],'Data Validation'!$A$20:$B$47,2,FALSE),"00")) -> 2005 - 05 - 03 - 0001 - 01A | E4: Desktop Computer | F4: n|a | G4: n|a | H4: n|a | I4: Pentium 4 | J4: n|a | K4: n|a | L4: Black | M4: Desktop Computer with Printer | N4: unit | O4: 65500 | P4: =Table164[[#This Row],[Unit Value]]*Table164[[#This Row],[Qty | PCount]] -> 65500 | Q4: =IF(Table164[[#This Row],[Unit Value]]<=4999,"Low-Value Asset","High-Value Asset") -> High-Value Asset | R4: 1 | S4: 1 | T4: 0 | U4: 0 | V4: 38498 | W4: 001A - Office of the School Division Superintendent | Z4: Unserviceable | AA4: =CONCATENATE(Table164[[#This Row],[Other Description]]," - ",IF(Table164[[#This Row],[Brand]]="n|a","",CONCATENATE("Brand: ",Table164[[#This Row],[Brand]]," - ")),IF(Table164[[#This Row],[Model]]="n|a","",CONCATENATE("Model: ",Table164[[#This Row],[Model]]," - ")),IF(Table164[[#This Row],[Serial Number]]="n|a","",CONCATENATE("SN: ",Table164[[#This Row],[Serial Number]]," - ")),IF(Table164[[#This Row],[Processor]]="n|a","",CONCATENATE("Processor: ",Table164[[#This Row],[Processor]]," - ")),IF(Table164[[#This Row],[RAM]]="n|a","",CONCATENATE("RAM: ",Table164[[#This Row],[RAM]]," - ")),IF(Table164[[#This Row],[Storage]]="n|a","",CONCATENATE("Storage: ",Table164[[#This Row],[Storage]]," - ")),IF(Table164[[#This Row],[Color]]="n|a","",CONCATENATE("Color: ",Table164[[#This Row],[Color]]))) -> Desktop Computer with Printer - Processor: Pentium 4 - Color: Black
B5: 2 | C5: ICT Equipment | D5: =CONCATENATE(TEXT(Table164[[#This Row],[Date of Acquisition]],"yyyy")," - ", VLOOKUP(Table164[[#This Row],[Article]],'Data Validation'!$A$2:$B$16,2,FALSE)," - ",TEXT(Table164[[#This Row],[Series Number]],"0000")," - ",TEXT(VLOOKUP(Table164[[#This Row],[Location]],'Data Validation'!$A$20:$B$47,2,FALSE),"00")) -> 2005 - 05 - 03 - 0002 - 01A | E5: Desktop Computer | F5: Compaq | G5: n|a | H5: n|a | I5: n|a | J5: n|a | K5: n|a | L5: Black | M5: Desktop Computer | N5: unit | O5: 125000 | P5: =Table164[[#This Row],[Unit Value]]*Table164[[#This Row],[Qty | PCount]] -> 125000 | Q5: =IF(Table164[[#This Row],[Unit Value]]<=4999,"Low-Value Asset","High-Value Asset") -> High-Value Asset | R5: 1 | S5: 1 | T5: 0 | U5: 0 | V5: 38580 | W5: 001A - Office of the School Division Superintendent | Z5: Unserviceable | AA5: =CONCATENATE(Table164[[#This Row],[Other Description]]," - ",IF(Table164[[#This Row],[Brand]]="n|a","",CONCATENATE("Brand: ",Table164[[#This Row],[Brand]]," - ")),IF(Table164[[#This Row],[Model]]="n|a","",CONCATENATE("Model: ",Table164[[#This Row],[Model]]," - ")),IF(Table164[[#This Row],[Serial Number]]="n|a","",CONCATENATE("SN: ",Table164[[#This Row],[Serial Number]]," - ")),IF(Table164[[#This Row],[Processor]]="n|a","",CONCATENATE("Processor: ",Table164[[#This Row],[Processor]]," - ")),IF(Table164[[#This Row],[RAM]]="n|a","",CONCATENATE("RAM: ",Table164[[#This Row],[RAM]]," - ")),IF(Table164[[#This Row],[Storage]]="n|a","",CONCATENATE("Storage: ",Table164[[#This Row],[Storage]]," - ")),IF(Table164[[#This Row],[Color]]="n|a","",CONCATENATE("Color: ",Table164[[#This Row],[Color]]))) -> Desktop Computer - Brand: Compaq - Color: Black
B6: 3 | C6: ICT Equipment | D6: =CONCATENATE(TEXT(Table164[[#This Row],[Date of Acquisition]],"yyyy")," - ", VLOOKUP(Table164[[#This Row],[Article]],'Data Validation'!$A$2:$B$16,2,FALSE)," - ",TEXT(Table164[[#This Row],[Series Number]],"0000")," - ",TEXT(VLOOKUP(Table164[[#This Row],[Location]],'Data Validation'!$A$20:$B$47,2,FALSE),"00")) -> 2005 - 05 - 03 - 0003 - 01A | E6: Desktop Computer | F6: n|a | G6: n|a | H6: n|a | I6: Pentium 4 | J6: n|a | K6: n|a | L6: Black | M6: Desktop Computer with Printer and Computer Table | N6: unit | O6: 66500 | P6: =Table164[[#This Row],[Unit Value]]*Table164[[#This Row],[Qty | PCount]] -> 66500 | Q6: =IF(Table164[[#This Row],[Unit Value]]<=4999,"Low-Value Asset","High-Value Asset") -> High-Value Asset | R6: 1 | S6: 1 | T6: 0 | U6: 0 | V6: 38580 | W6: 001A - Office of the School Division Superintendent | Z6: Unserviceable | AA6: =CONCATENATE(Table164[[#This Row],[Other Description]]," - ",IF(Table164[[#This Row],[Brand]]="n|a","",CONCATENATE("Brand: ",Table164[[#This Row],[Brand]]," - ")),IF(Table164[[#This Row],[Model]]="n|a","",CONCATENATE("Model: ",Table164[[#This Row],[Model]]," - ")),IF(Table164[[#This Row],[Serial Number]]="n|a","",CONCATENATE("SN: ",Table164[[#This Row],[Serial Number]]," - ")),IF(Table164[[#This Row],[Processor]]="n|a","",CONCATENATE("Processor: ",Table164[[#This Row],[Processor]]," - ")),IF(Table164[[#This Row],[RAM]]="n|a","",CONCATENATE("RAM: ",Table164[[#This Row],[RAM]]," - ")),IF(Table164[[#This Row],[Storage]]="n|a","",CONCATENATE("Storage: ",Table164[[#This Row],[Storage]]," - ")),IF(Table164[[#This Row],[Color]]="n|a","",CONCATENATE("Color: ",Table164[[#This Row],[Color]]))) -> Desktop Computer with Printer and Computer Table - Processor: Pentium 4 - Color: Black
B7: 4 | C7: ICT Equipment | D7: =CONCATENATE(TEXT(Table164[[#This Row],[Date of Acquisition]],"yyyy")," - ", VLOOKUP(Table164[[#This Row],[Article]],'Data Validation'!$A$2:$B$16,2,FALSE)," - ",TEXT(Table164[[#This Row],[Series Number]],"0000")," - ",TEXT(VLOOKUP(Table164[[#This Row],[Location]],'Data Validation'!$A$20:$B$47,2,FALSE),"00")) -> 2005 - 05 - 03 - 0004 - 01A | E7: Printing Machine | F7: Epson | G7: 2175 | H7: n|a | I7: n|a | J7: n|a | K7: n|a | L7: n|a | M7: Printing Machine | N7: unit | O7: 58500 | P7: =Table164[[#This Row],[Unit Value]]*Table164[[#This Row],[Qty | PCount]] -> 58500 | Q7: =IF(Table164[[#This Row],[Unit Value]]<=4999,"Low-Value Asset","High-Value Asset") -> High-Value Asset | R7: 1 | S7: 1 | T7: 0 | U7: 0 | V7: 38687 | W7: 001A - Office of the School Division Superintendent | X7: - | Y7: - | Z7: Unserviceable | AA7: =CONCATENATE(Table164[[#This Row],[Other Description]]," - ",IF(Table164[[#This Row],[Brand]]="n|a","",CONCATENATE("Brand: ",Table164[[#This Row],[Brand]]," - ")),IF(Table164[[#This Row],[Model]]="n|a","",CONCATENATE("Model: ",Table164[[#This Row],[Model]]," - ")),IF(Table164[[#This Row],[Serial Number]]="n|a","",CONCATENATE("SN: ",Table164[[#This Row],[Serial Number]]," - ")),IF(Table164[[#This Row],[Processor]]="n|a","",CONCATENATE("Processor: ",Table164[[#This Row],[Processor]]," - ")),IF(Table164[[#This Row],[RAM]]="n|a","",CONCATENATE("RAM: ",Table164[[#This Row],[RAM]]," - ")),IF(Table164[[#This Row],[Storage]]="n|a","",CONCATENATE("Storage: ",Table164[[#This Row],[Storage]]," - ")),IF(Table164[[#This Row],[Color]]="n|a","",CONCATENATE("Color: ",Table164[[#This Row],[Color]]))) -> Printing Machine - Brand: Epson - Model: 2175 -
B8: 1 | C8: ICT Equipment | D8: =CONCATENATE(TEXT(Table164[[#This Row],[Date of Acquisition]],"yyyy")," - ", VLOOKUP(Table164[[#This Row],[Article]],'Data Validation'!$A$2:$B$16,2,FALSE)," - ",TEXT(Table164[[#This Row],[Series Number]],"0000")," - ",TEXT(VLOOKUP(Table164[[#This Row],[Location]],'Data Validation'!$A$20:$B$47,2,FALSE),"00")) -> 2006 - 05 - 03 - 0001 - 01A | E8: Desktop Computer | F8: IBM | G8: n|a | H8: n|a | I8: n|a | J8: n|a | K8: n|a | L8: Black | M8: Compatible Computer System with Cog Manipulatives | N8: unit | O8: 250000 | P8: =Table164[[#This Row],[Unit Value]]*Table164[[#This Row],[Qty | PCount]] -> 250000 | Q8: =IF(Table164[[#This Row],[Unit Value]]<=4999,"Low-Value Asset","High-Value Asset") -> High-Value Asset | R8: 1 | S8: 1 | T8: 0 | U8: 0 | V8: 39046 | W8: 001A - Office of the School Division Superintendent | Z8: Unserviceable | AA8: =CONCATENATE(Table164[[#This Row],[Other Description]]," - ",IF(Table164[[#This Row],[Brand]]="n|a","",CONCATENATE("Brand: ",Table164[[#This Row],[Brand]]," - ")),IF(Table164[[#This Row],[Model]]="n|a","",CONCATENATE("Model: ",Table164[[#This Row],[Model]]," - ")),IF(Table164[[#This Row],[Serial Number]]="n|a","",CONCATENATE("SN: ",Table164[[#This Row],[Serial Number]]," - ")),IF(Table164[[#This Row],[Processor]]="n|a","",CONCATENATE("Processor: ",Table164[[#This Row],[Processor]]," - ")),IF(Table164[[#This Row],[RAM]]="n|a","",CONCATENATE("RAM: ",Table164[[#This Row],[RAM]]," - ")),IF(Table164[[#This Row],[Storage]]="n|a","",CONCATENATE("Storage: ",Table164[[#This Row],[Storage]]," - ")),IF(Table164[[#This Row],[Color]]="n|a","",CONCATENATE("Color: ",Table164[[#This Row],[Color]]))) -> Compatible Computer System with Cog Manipulatives - Brand: IBM - Color: Black
B9: 1 | C9: ICT Equipment | D9: =CONCATENATE(TEXT(Table164[[#This Row],[Date of Acquisition]],"yyyy")," - ", VLOOKUP(Table164[[#This Row],[Article]],'Data Validation'!$A$2:$B$16,2,FALSE)," - ",TEXT(Table164[[#This Row],[Series Number]],"0000")," - ",TEXT(VLOOKUP(Table164[[#This Row],[Location]],'Data Validation'!$A$20:$B$47,2,FALSE),"00")) -> 2008 - 05 - 03 - 0001 - 01A | E9: Laptop | F9: n|a | G9: n|a | H9: n|a | I9: n|a | J9: n|a | K9: n|a | L9: n|a | M9: Laptop Computer | N9: unit | O9: 116800 | P9: =Table164[[#This Row],[Unit Value]]*Table164[[#This Row],[Qty | PCount]] -> 116800 | Q9: =IF(Table164[[#This Row],[Unit Value]]<=4999,"Low-Value Asset","High-Value Asset") -> High-Value Asset | R9: 1 | S9: 1 | T9: 0 | U9: 0 | V9: 39448 | W9: 001A - Office of the School Division Superintendent | Z9: Unserviceable | AA9: =CONCATENATE(Table164[[#This Row],[Other Description]]," - ",IF(Table164[[#This Row],[Brand]]="n|a","",CONCATENATE("Brand: ",Table164[[#This Row],[Brand]]," - ")),IF(Table164[[#This Row],[Model]]="n|a","",CONCATENATE("Model: ",Table164[[#This Row],[Model]]," - ")),IF(Table164[[#This Row],[Serial Number]]="n|a","",CONCATENATE("SN: ",Table164[[#This Row],[Serial Number]]," - ")),IF(Table164[[#This Row],[Processor]]="n|a","",CONCATENATE("Processor: ",Table164[[#This Row],[Processor]]," - ")),IF(Table164[[#This Row],[RAM]]="n|a","",CONCATENATE("RAM: ",Table164[[#This Row],[RAM]]," - ")),IF(Table164[[#This Row],[Storage]]="n|a","",CONCATENATE("Storage: ",Table164[[#This Row],[Storage]]," - ")),IF(Table164[[#This Row],[Color]]="n|a","",CONCATENATE("Color: ",Table164[[#This Row],[Color]]))) -> Laptop Computer -
B10: 1 | C10: ICT Equipment | D10: =CONCATENATE(TEXT(Table164[[#This Row],[Date of Acquisition]],"yyyy")," - ", VLOOKUP(Table164[[#This Row],[Article]],'Data Validation'!$A$2:$B$16,2,FALSE)," - ",TEXT(Table164[[#This Row],[Series Number]],"0000")," - ",TEXT(VLOOKUP(Table164[[#This Row],[Location]],'Data Validation'!$A$20:$B$47,2,FALSE),"00")) -> 2009 - 05 - 03 - 0001 - 01A | E10: Desktop Computer | F10: Lenovo | G10: ThinkCentre M58E | H10: n|a | I10: n|a | J10: n|a | K10: n|a | L10: Black | M10: Desktop Computer | N10: unit | O10: 74800 | P10: =Table164[[#This Row],[Unit Value]]*Table164[[#This Row],[Qty | PCount]] -> 74800 | Q10: =IF(Table164[[#This Row],[Unit Value]]<=4999,"Low-Value Asset","High-Value Asset") -> High-Value Asset | R10: 1 | S10: 1 | T10: 0 | U10: 0 | V10: 40058 | W10: 001A - Office of the School Division Superintendent | Z10: Unserviceable | AA10: =CONCATENATE(Table164[[#This Row],[Other Description]]," - ",IF(Table164[[#This Row],[Brand]]="n|a","",CONCATENATE("Brand: ",Table164[[#This Row],[Brand]]," - ")),IF(Table164[[#This Row],[Model]]="n|a","",CONCATENATE("Model: ",Table164[[#This Row],[Model]]," - ")),IF(Table164[[#This Row],[Serial Number]]="n|a","",CONCATENATE("SN: ",Table164[[#This Row],[Serial Number]]," - ")),IF(Table164[[#This Row],[Processor]]="n|a","",CONCATENATE("Processor: ",Table164[[#This Row],[Processor]]," - ")),IF(Table164[[#This Row],[RAM]]="n|a","",CONCATENATE("RAM: ",Table164[[#This Row],[RAM]]," - ")),IF(Table164[[#This Row],[Storage]]="n|a","",CONCATENATE("Storage: ",Table164[[#This Row],[Storage]]," - ")),IF(Table164[[#This Row],[Color]]="n|a","",CONCATENATE("Color: ",Table164[[#This Row],[Color]]))) -> Desktop Computer - Brand: Lenovo - Model: ThinkCentre M58E - Color: Black
B11: 1 | C11: ICT Equipment | D11: =CONCATENATE(TEXT(Table164[[#This Row],[Date of Acquisition]],"yyyy")," - ", VLOOKUP(Table164[[#This Row],[Article]],'Data Validation'!$A$2:$B$16,2,FALSE)," - ",TEXT(Table164[[#This Row],[Series Number]],"0000")," - ",TEXT(VLOOKUP(Table164[[#This Row],[Location]],'Data Validation'!$A$20:$B$47,2,FALSE),"00")) -> 2017 - 05 - 03 - 0001 - 01A | E11: Laptop | F11: Acer | G11: Switch Alpha 12 | H11: n|a | I11: n|a | J11: n|a | K11: n|a | L11: Black | M11: Laptop | N11: unit | O11: 104444 | P11: =Table164[[#This Row],[Unit Value]]*Table164[[#This Row],[Qty | PCount]] -> 104444 | Q11: =IF(Table164[[#This Row],[Unit Value]]<=4999,"Low-Value Asset","High-Value Asset") -> High-Value Asset | R11: 1 | S11: 1 | T11: 0 | U11: 0 | V11: 42919 | W11: 001A - Office of the School Division Superintendent | Z11: Unserviceable | AA11: =CONCATENATE(Table164[[#This Row],[Other Description]]," - ",IF(Table164[[#This Row],[Brand]]="n|a","",CONCATENATE("Brand: ",Table164[[#This Row],[Brand]]," - ")),IF(Table164[[#This Row],[Model]]="n|a","",CONCATENATE("Model: ",Table164[[#This Row],[Model]]," - ")),IF(Table164[[#This Row],[Serial Number]]="n|a","",CONCATENATE("SN: ",Table164[[#This Row],[Serial Number]]," - ")),IF(Table164[[#This Row],[Processor]]="n|a","",CONCATENATE("Processor: ",Table164[[#This Row],[Processor]]," - ")),IF(Table164[[#This Row],[RAM]]="n|a","",CONCATENATE("RAM: ",Table164[[#This Row],[RAM]]," - ")),IF(Table164[[#This Row],[Storage]]="n|a","",CONCATENATE("Storage: ",Table164[[#This Row],[Storage]]," - ")),IF(Table164[[#This Row],[Color]]="n|a","",CONCATENATE("Color: ",Table164[[#This Row],[Color]]))) -> Laptop - Brand: Acer - Model: Switch Alpha 12 - Color: Black
B12: 2 | C12: ICT Equipment | D12: =CONCATENATE(TEXT(Table164[[#This Row],[Date of Acquisition]],"yyyy")," - ", VLOOKUP(Table164[[#This Row],[Article]],'Data Validation'!$A$2:$B$16,2,FALSE)," - ",TEXT(Table164[[#This Row],[Series Number]],"0000")," - ",TEXT(VLOOKUP(Table164[[#This Row],[Location]],'Data Validation'!$A$20:$B$47,2,FALSE),"00")) -> 2019 - 05 - 03 - 0002 - 01A | E12: Laptop | F12: Asus | G12: S530 | H12: n|a | I12: n|a | J12: n|a | K12: n|a | L12: n|a | M12: Laptop | N12: unit | O12: 63000 | P12: =Table164[[#This Row],[Unit Value]]*Table164[[#This Row],[Qty | PCount]] -> 63000 | Q12: =IF(Table164[[#This Row],[Unit Value]]<=4999,"Low-Value Asset","High-Value Asset") -> High-Value Asset | R12: 1 | S12: 1 | T12: 0 | U12: 0 | V12: 43700 | W12: 001A - Office of the School Division Superintendent | Z12: Unserviceable | AA12: =CONCATENATE(Table164[[#This Row],[Other Description]]," - ",IF(Table164[[#This Row],[Brand]]="n|a","",CONCATENATE("Brand: ",Table164[[#This Row],[Brand]]," - ")),IF(Table164[[#This Row],[Model]]="n|a","",CONCATENATE("Model: ",Table164[[#This Row],[Model]]," - ")),IF(Table164[[#This Row],[Serial Number]]="n|a","",CONCATENATE("SN: ",Table164[[#This Row],[Serial Number]]," - ")),IF(Table164[[#This Row],[Processor]]="n|a","",CONCATENATE("Processor: ",Table164[[#This Row],[Processor]]," - ")),IF(Table164[[#This Row],[RAM]]="n|a","",CONCATENATE("RAM: ",Table164[[#This Row],[RAM]]," - ")),IF(Table164[[#This Row],[Storage]]="n|a","",CONCATENATE("Storage: ",Table164[[#This Row],[Storage]]," - ")),IF(Table164[[#This Row],[Color]]="n|a","",CONCATENATE("Color: ",Table164[[#This Row],[Color]]))) -> Laptop - Brand: Asus - Model: S530 -
B13: 1 | C13: Medical Equipment | D13: =CONCATENATE(TEXT(Table164[[#This Row],[Date of Acquisition]],"yyyy")," - ", VLOOKUP(Table164[[#This Row],[Article]],'Data Validation'!$A$2:$B$16,2,FALSE)," - ",TEXT(Table164[[#This Row],[Series Number]],"0000")," - ",TEXT(VLOOKUP(Table164[[#This Row],[Location]],'Data Validation'!$A$20:$B$47,2,FALSE),"00")) -> 2005 - 05 - 11 - 0001 - 01A | E13: Dental Chair | F13: n|a | G13: n|a | H13: n|a | I13: n|a | J13: n|a | K13: n|a | L13: Red | M13: Dental Chair | N13: unit | O13: 221760.75 | P13: =Table164[[#This Row],[Unit Value]]*Table164[[#This Row],[Qty | PCount]] -> 221760.75 | Q13: =IF(Table164[[#This Row],[Unit Value]]<=4999,"Low-Value Asset","High-Value Asset") -> High-Value Asset | R13: 1 | S13: 1 | T13: 0 | U13: 0 | V13: 38580 | W13: 001A - Office of the School Division Superintendent | X13: - | Y13: - | Z13: Unserviceable | AA13: =CONCATENATE(Table164[[#This Row],[Other Description]]," - ",IF(Table164[[#This Row],[Brand]]="n|a","",CONCATENATE("Brand: ",Table164[[#This Row],[Brand]]," - ")),IF(Table164[[#This Row],[Model]]="n|a","",CONCATENATE("Model: ",Table164[[#This Row],[Model]]," - ")),IF(Table164[[#This Row],[Serial Number]]="n|a","",CONCATENATE("SN: ",Table164[[#This Row],[Serial Number]]," - ")),IF(Table164[[#This Row],[Processor]]="n|a","",CONCATENATE("Processor: ",Table164[[#This Row],[Processor]]," - ")),IF(Table164[[#This Row],[RAM]]="n|a","",CONCATENATE("RAM: ",Table164[[#This Row],[RAM]]," - ")),IF(Table164[[#This Row],[Storage]]="n|a","",CONCATENATE("Storage: ",Table164[[#This Row],[Storage]]," - ")),IF(Table164[[#This Row],[Color]]="n|a","",CONCATENATE("Color: ",Table164[[#This Row],[Color]]))) -> Dental Chair - Color: Red
B14: 2 | C14: Medical Equipment | D14: =CONCATENATE(TEXT(Table164[[#This Row],[Date of Acquisition]],"yyyy")," - ", VLOOKUP(Table164[[#This Row],[Article]],'Data Validation'!$A$2:$B$16,2,FALSE)," - ",TEXT(Table164[[#This Row],[Series Number]],"0000")," - ",TEXT(VLOOKUP(Table164[[#This Row],[Location]],'Data Validation'!$A$20:$B$47,2,FALSE),"00")) -> 2005 - 05 - 11 - 0002 - 01A | E14: Dental Chair Accessories | F14: n|a | G14: n|a | H14: n|a | I14: n|a | J14: n|a | K14: n|a | L14: n|a | M14: Compressor with Attaching Parts | N14: unit | O14: 72650 | P14: =Table164[[#This Row],[Unit Value]]*Table164[[#This Row],[Qty | PCount]] -> 72650 | Q14: =IF(Table164[[#This Row],[Unit Value]]<=4999,"Low-Value Asset","High-Value Asset") -> High-Value Asset | R14: 1 | S14: 1 | T14: 0 | U14: 0 | V14: 38687 | W14: 001A - Office of the School Division Superintendent | X14: - | Y14: - | Z14: Unserviceable | AA14: =CONCATENATE(Table164[[#This Row],[Other Description]]," - ",IF(Table164[[#This Row],[Brand]]="n|a","",CONCATENATE("Brand: ",Table164[[#This Row],[Brand]]," - ")),IF(Table164[[#This Row],[Model]]="n|a","",CONCATENATE("Model: ",Table164[[#This Row],[Model]]," - ")),IF(Table164[[#This Row],[Serial Number]]="n|a","",CONCATENATE("SN: ",Table164[[#This Row],[Serial Number]]," - ")),IF(Table164[[#This Row],[Processor]]="n|a","",CONCATENATE("Processor: ",Table164[[#This Row],[Processor]]," - ")),IF(Table164[[#This Row],[RAM]]="n|a","",CONCATENATE("RAM: ",Table164[[#This Row],[RAM]]," - ")),IF(Table164[[#This Row],[Storage]]="n|a","",CONCATENATE("Storage: ",Table164[[#This Row],[Storage]]," - ")),IF(Table164[[#This Row],[Color]]="n|a","",CONCATENATE("Color: ",Table164[[#This Row],[Color]]))) -> Compressor with Attaching Parts -
B15: 1 | C15: Motor Vehicle | D15: =CONCATENATE(TEXT(Table164[[#This Row],[Date of Acquisition]],"yyyy")," - ", VLOOKUP(Table164[[#This Row],[Article]],'Data Validation'!$A$2:$B$16,2,FALSE)," - ",TEXT(Table164[[#This Row],[Series Number]],"0000")," - ",TEXT(VLOOKUP(Table164[[#This Row],[Location]],'Data Validation'!$A$20:$B$47,2,FALSE),"00")) -> 2007 - 06 - 01 - 0001 - 01A | E15: Revo | F15: Toyota | G15: Revo Wagon 1999 | H15: n|a | I15: n|a | J15: n|a | K15: n|a | L15: Red | M15: Manual Transmission - Gas Fueled - Plate Number: SGB-883 | N15: unit | O15: 335000 | P15: =Table164[[#This Row],[Unit Value]]*Table164[[#This Row],[Qty | PCount]] -> 335000 | Q15: =IF(Table164[[#This Row],[Unit Value]]<=4999,"Low-Value Asset","High-Value Asset") -> High-Value Asset | R15: 1 | S15: 1 | T15: 0 | U15: 0 | V15: 39083 | W15: 001A - Office of the School Division Superintendent | X15: - | Y15: - | Z15: Unserviceable | AA15: =CONCATENATE(Table164[[#This Row],[Other Description]]," - ",IF(Table164[[#This Row],[Brand]]="n|a","",CONCATENATE("Brand: ",Table164[[#This Row],[Brand]]," - ")),IF(Table164[[#This Row],[Model]]="n|a","",CONCATENATE("Model: ",Table164[[#This Row],[Model]]," - ")),IF(Table164[[#This Row],[Serial Number]]="n|a","",CONCATENATE("SN: ",Table164[[#This Row],[Serial Number]]," - ")),IF(Table164[[#This Row],[Processor]]="n|a","",CONCATENATE("Processor: ",Table164[[#This Row],[Processor]]," - ")),IF(Table164[[#This Row],[RAM]]="n|a","",CONCATENATE("RAM: ",Table164[[#This Row],[RAM]]," - ")),IF(Table164[[#This Row],[Storage]]="n|a","",CONCATENATE("Storage: ",Table164[[#This Row],[Storage]]," - ")),IF(Table164[[#This Row],[Color]]="n|a","",CONCATENATE("Color: ",Table164[[#This Row],[Color]]))) -> Manual Transmission - Gas Fueled - Plate Number: SGB-883 - Brand: Toyota - Model: Revo Wagon 1999 - Color: Red
B16: 1 | C16: Office Equipment | D16: =CONCATENATE(TEXT(Table164[[#This Row],[Date of Acquisition]],"yyyy")," - ", VLOOKUP(Table164[[#This Row],[Article]],'Data Validation'!$A$2:$B$16,2,FALSE)," - ",TEXT(Table164[[#This Row],[Series Number]],"0000")," - ",TEXT(VLOOKUP(Table164[[#This Row],[Location]],'Data Validation'!$A$20:$B$47,2,FALSE),"00")) -> 2005 - 05 - 02 - 0001 - 01A | E16: Printing Machine | F16: RISO | G16: KS800 | H16: n|a | I16: n|a | J16: n|a | K16: n|a | L16: White | M16: Risograph Machine | N16: unit | O16: 222000 | P16: =Table164[[#This Row],[Unit Value]]*Table164[[#This Row],[Qty | PCount]] -> 222000 | Q16: =IF(Table164[[#This Row],[Unit Value]]<=4999,"Low-Value Asset","High-Value Asset") -> High-Value Asset | R16: 1 | S16: 1 | T16: 0 | U16: 0 | V16: 38353 | W16: 001A - Office of the School Division Superintendent | X16: - | Y16: - | Z16: Unserviceable | AA16: =CONCATENATE(Table164[[#This Row],[Other Description]]," - ",IF(Table164[[#This Row],[Brand]]="n|a","",CONCATENATE("Brand: ",Table164[[#This Row],[Brand]]," - ")),IF(Table164[[#This Row],[Model]]="n|a","",CONCATENATE("Model: ",Table164[[#This Row],[Model]]," - ")),IF(Table164[[#This Row],[Serial Number]]="n|a","",CONCATENATE("SN: ",Table164[[#This Row],[Serial Number]]," - ")),IF(Table164[[#This Row],[Processor]]="n|a","",CONCATENATE("Processor: ",Table164[[#This Row],[Processor]]," - ")),IF(Table164[[#This Row],[RAM]]="n|a","",CONCATENATE("RAM: ",Table164[[#This Row],[RAM]]," - ")),IF(Table164[[#This Row],[Storage]]="n|a","",CONCATENATE("Storage: ",Table164[[#This Row],[Storage]]," - ")),IF(Table164[[#This Row],[Color]]="n|a","",CONCATENATE("Color: ",Table164[[#This Row],[Color]]))) -> Risograph Machine - Brand: RISO - Model: KS800 - Color: White
B17: 1 | C17: Office Equipment | D17: =CONCATENATE(TEXT(Table164[[#This Row],[Date of Acquisition]],"yyyy")," - ", VLOOKUP(Table164[[#This Row],[Article]],'Data Validation'!$A$2:$B$16,2,FALSE)," - ",TEXT(Table164[[#This Row],[Series Number]],"0000")," - ",TEXT(VLOOKUP(Table164[[#This Row],[Location]],'Data Validation'!$A$20:$B$47,2,FALSE),"00")) -> 2010 - 05 - 02 - 0001 - 01A | E17: Printing Machine | F17: Canon | G17: DQT-04749 | H17: n|a | I17: n|a | J17: n|a | K17: n|a | L17: n|a | M17: Canon Copier | N17: unit | O17: 76000 | P17: =Table164[[#This Row],[Unit Value]]*Table164[[#This Row],[Qty | PCount]] -> 76000 | Q17: =IF(Table164[[#This Row],[Unit Value]]<=4999,"Low-Value Asset","High-Value Asset") -> High-Value Asset | R17: 1 | S17: 1 | T17: 0 | U17: 0 | V17: 40466 | W17: 001A - Office of the School Division Superintendent | X17: - | Y17: - | Z17: Unserviceable | AA17: =CONCATENATE(Table164[[#This Row],[Other Description]]," - ",IF(Table164[[#This Row],[Brand]]="n|a","",CONCATENATE("Brand: ",Table164[[#This Row],[Brand]]," - ")),IF(Table164[[#This Row],[Model]]="n|a","",CONCATENATE("Model: ",Table164[[#This Row],[Model]]," - ")),IF(Table164[[#This Row],[Serial Number]]="n|a","",CONCATENATE("SN: ",Table164[[#This Row],[Serial Number]]," - ")),IF(Table164[[#This Row],[Processor]]="n|a","",CONCATENATE("Processor: ",Table164[[#This Row],[Processor]]," - ")),IF(Table164[[#This Row],[RAM]]="n|a","",CONCATENATE("RAM: ",Table164[[#This Row],[RAM]]," - ")),IF(Table164[[#This Row],[Storage]]="n|a","",CONCATENATE("Storage: ",Table164[[#This Row],[Storage]]," - ")),IF(Table164[[#This Row],[Color]]="n|a","",CONCATENATE("Color: ",Table164[[#This Row],[Color]]))) -> Canon Copier - Brand: Canon - Model: DQT-04749 -
B18: 1 | C18: Office Equipment | D18: =CONCATENATE(TEXT(Table164[[#This Row],[Date of Acquisition]],"yyyy")," - ", VLOOKUP(Table164[[#This Row],[Article]],'Data Validation'!$A$2:$B$16,2,FALSE)," - ",TEXT(Table164[[#This Row],[Series Number]],"0000")," - ",TEXT(VLOOKUP(Table164[[#This Row],[Location]],'Data Validation'!$A$20:$B$47,2,FALSE),"00")) -> 2016 - 05 - 02 - 0001 - 01A | E18: Intercom | F18: n|a | G18: n|a | H18: n|a | I18: n|a | J18: n|a | K18: n|a | L18: n|a | M18: Intercom | N18: unit | O18: 56330 | P18: =Table164[[#This Row],[Unit Value]]*Table164[[#This Row],[Qty | PCount]] -> 56330 | Q18: =IF(Table164[[#This Row],[Unit Value]]<=4999,"Low-Value Asset","High-Value Asset") -> High-Value Asset | R18: 1 | S18: 1 | T18: 0 | U18: 0 | V18: 42725 | W18: 001A - Office of the School Division Superintendent | X18: - | Y18: - | Z18: Unserviceable | AA18: =CONCATENATE(Table164[[#This Row],[Other Description]]," - ",IF(Table164[[#This Row],[Brand]]="n|a","",CONCATENATE("Brand: ",Table164[[#This Row],[Brand]]," - ")),IF(Table164[[#This Row],[Model]]="n|a","",CONCATENATE("Model: ",Table164[[#This Row],[Model]]," - ")),IF(Table164[[#This Row],[Serial Number]]="n|a","",CONCATENATE("SN: ",Table164[[#This Row],[Serial Number]]," - ")),IF(Table164[[#This Row],[Processor]]="n|a","",CONCATENATE("Processor: ",Table164[[#This Row],[Processor]]," - ")),IF(Table164[[#This Row],[RAM]]="n|a","",CONCATENATE("RAM: ",Table164[[#This Row],[RAM]]," - ")),IF(Table164[[#This Row],[Storage]]="n|a","",CONCATENATE("Storage: ",Table164[[#This Row],[Storage]]," - ")),IF(Table164[[#This Row],[Color]]="n|a","",CONCATENATE("Color: ",Table164[[#This Row],[Color]]))) -> Intercom -
B19: 1 | C19: Other PPE | D19: =CONCATENATE(TEXT(Table164[[#This Row],[Date of Acquisition]],"yyyy")," - ", VLOOKUP(Table164[[#This Row],[Article]],'Data Validation'!$A$2:$B$16,2,FALSE)," - ",TEXT(Table164[[#This Row],[Series Number]],"0000")," - ",TEXT(VLOOKUP(Table164[[#This Row],[Location]],'Data Validation'!$A$20:$B$47,2,FALSE),"00")) -> 1997 - 00 - 00 - 0001 - 01A | E19: Pumping Stations,& Conduits | F19: n|a | G19: n|a | H19: n|a | I19: n|a | J19: n|a | K19: n|a | L19: n|a | M19: 'Pumping Stations,& Conduits | N19: unit | O19: 156353.35 | P19: =Table164[[#This Row],[Unit Value]]*Table164[[#This Row],[Qty | PCount]] -> 156353.35 | Q19: =IF(Table164[[#This Row],[Unit Value]]<=4999,"Low-Value Asset","High-Value Asset") -> High-Value Asset | R19: 1 | S19: 1 | T19: 0 | U19: 0 | V19: 35582 | W19: 001A - Office of the School Division Superintendent | X19: - | Y19: - | Z19: Unserviceable | AA19: =CONCATENATE(Table164[[#This Row],[Other Description]]," - ",IF(Table164[[#This Row],[Brand]]="n|a","",CONCATENATE("Brand: ",Table164[[#This Row],[Brand]]," - ")),IF(Table164[[#This Row],[Model]]="n|a","",CONCATENATE("Model: ",Table164[[#This Row],[Model]]," - ")),IF(Table164[[#This Row],[Serial Number]]="n|a","",CONCATENATE("SN: ",Table164[[#This Row],[Serial Number]]," - ")),IF(Table164[[#This Row],[Processor]]="n|a","",CONCATENATE("Processor: ",Table164[[#This Row],[Processor]]," - ")),IF(Table164[[#This Row],[RAM]]="n|a","",CONCATENATE("RAM: ",Table164[[#This Row],[RAM]]," - ")),IF(Table164[[#This Row],[Storage]]="n|a","",CONCATENATE("Storage: ",Table164[[#This Row],[Storage]]," - ")),IF(Table164[[#This Row],[Color]]="n|a","",CONCATENATE("Color: ",Table164[[#This Row],[Color]]))) -> 'Pumping Stations,& Conduits -
D20: =CONCATENATE(TEXT(Table164[[#This Row],[Date of Acquisition]],"yyyy")," - ", VLOOKUP(Table164[[#This Row],[Article]],'Data Validation'!$A$2:$B$16,2,FALSE)," - ",TEXT(Table164[[#This Row],[Series Number]],"0000")," - ",TEXT(VLOOKUP(Table164[[#This Row],[Location]],'Data Validation'!$A$20:$B$47,2,FALSE),"00")) -> #N/A | P20: =Table164[[#This Row],[Unit Value]]*Table164[[#This Row],[Qty | PCount]] -> 0 | Q20: =IF(Table164[[#This Row],[Unit Value]]<=4999,"Low-Value Asset","High-Value Asset") -> Low-Value Asset | Z20: Unserviceable | AA20: =CONCATENATE(Table164[[#This Row],[Other Description]]," - ",IF(Table164[[#This Row],[Brand]]="n|a","",CONCATENATE("Brand: ",Table164[[#This Row],[Brand]]," - ")),IF(Table164[[#This Row],[Model]]="n|a","",CONCATENATE("Model: ",Table164[[#This Row],[Model]]," - ")),IF(Table164[[#This Row],[Serial Number]]="n|a","",CONCATENATE("SN: ",Table164[[#This Row],[Serial Number]]," - ")),IF(Table164[[#This Row],[Processor]]="n|a","",CONCATENATE("Processor: ",Table164[[#This Row],[Processor]]," - ")),IF(Table164[[#This Row],[RAM]]="n|a","",CONCATENATE("RAM: ",Table164[[#This Row],[RAM]]," - ")),IF(Table164[[#This Row],[Storage]]="n|a","",CONCATENATE("Storage: ",Table164[[#This Row],[Storage]]," - ")),IF(Table164[[#This Row],[Color]]="n|a","",CONCATENATE("Color: ",Table164[[#This Row],[Color]]))) -> - Brand: - Model: - SN: - Processor: - RAM: - Storage: - Color:
D21: =CONCATENATE(TEXT(Table164[[#This Row],[Date of Acquisition]],"yyyy")," - ", VLOOKUP(Table164[[#This Row],[Article]],'Data Validation'!$A$2:$B$16,2,FALSE)," - ",TEXT(Table164[[#This Row],[Series Number]],"0000")," - ",TEXT(VLOOKUP(Table164[[#This Row],[Location]],'Data Validation'!$A$20:$B$47,2,FALSE),"00")) -> #N/A | P21: =Table164[[#This Row],[Unit Value]]*Table164[[#This Row],[Qty | PCount]] -> 0 | Q21: =IF(Table164[[#This Row],[Unit Value]]<=4999,"Low-Value Asset","High-Value Asset") -> Low-Value Asset | Z21: Unserviceable | AA21: =CONCATENATE(Table164[[#This Row],[Other Description]]," - ",IF(Table164[[#This Row],[Brand]]="n|a","",CONCATENATE("Brand: ",Table164[[#This Row],[Brand]]," - ")),IF(Table164[[#This Row],[Model]]="n|a","",CONCATENATE("Model: ",Table164[[#This Row],[Model]]," - ")),IF(Table164[[#This Row],[Serial Number]]="n|a","",CONCATENATE("SN: ",Table164[[#This Row],[Serial Number]]," - ")),IF(Table164[[#This Row],[Processor]]="n|a","",CONCATENATE("Processor: ",Table164[[#This Row],[Processor]]," - ")),IF(Table164[[#This Row],[RAM]]="n|a","",CONCATENATE("RAM: ",Table164[[#This Row],[RAM]]," - ")),IF(Table164[[#This Row],[Storage]]="n|a","",CONCATENATE("Storage: ",Table164[[#This Row],[Storage]]," - ")),IF(Table164[[#This Row],[Color]]="n|a","",CONCATENATE("Color: ",Table164[[#This Row],[Color]]))) -> - Brand: - Model: - SN: - Processor: - RAM: - Storage: - Color:
D22: =CONCATENATE(TEXT(Table164[[#This Row],[Date of Acquisition]],"yyyy")," - ", VLOOKUP(Table164[[#This Row],[Article]],'Data Validation'!$A$2:$B$16,2,FALSE)," - ",TEXT(Table164[[#This Row],[Series Number]],"0000")," - ",TEXT(VLOOKUP(Table164[[#This Row],[Location]],'Data Validation'!$A$20:$B$47,2,FALSE),"00")) -> #N/A | P22: =Table164[[#This Row],[Unit Value]]*Table164[[#This Row],[Qty | PCount]] -> 0 | Q22: =IF(Table164[[#This Row],[Unit Value]]<=4999,"Low-Value Asset","High-Value Asset") -> Low-Value Asset | Z22: Unserviceable | AA22: =CONCATENATE(Table164[[#This Row],[Other Description]]," - ",IF(Table164[[#This Row],[Brand]]="n|a","",CONCATENATE("Brand: ",Table164[[#This Row],[Brand]]," - ")),IF(Table164[[#This Row],[Model]]="n|a","",CONCATENATE("Model: ",Table164[[#This Row],[Model]]," - ")),IF(Table164[[#This Row],[Serial Number]]="n|a","",CONCATENATE("SN: ",Table164[[#This Row],[Serial Number]]," - ")),IF(Table164[[#This Row],[Processor]]="n|a","",CONCATENATE("Processor: ",Table164[[#This Row],[Processor]]," - ")),IF(Table164[[#This Row],[RAM]]="n|a","",CONCATENATE("RAM: ",Table164[[#This Row],[RAM]]," - ")),IF(Table164[[#This Row],[Storage]]="n|a","",CONCATENATE("Storage: ",Table164[[#This Row],[Storage]]," - ")),IF(Table164[[#This Row],[Color]]="n|a","",CONCATENATE("Color: ",Table164[[#This Row],[Color]]))) -> - Brand: - Model: - SN: - Processor: - RAM: - Storage: - Color:
D23: =CONCATENATE(TEXT(Table164[[#This Row],[Date of Acquisition]],"yyyy")," - ", VLOOKUP(Table164[[#This Row],[Article]],'Data Validation'!$A$2:$B$16,2,FALSE)," - ",TEXT(Table164[[#This Row],[Series Number]],"0000")," - ",TEXT(VLOOKUP(Table164[[#This Row],[Location]],'Data Validation'!$A$20:$B$47,2,FALSE),"00")) -> #N/A | P23: =Table164[[#This Row],[Unit Value]]*Table164[[#This Row],[Qty | PCount]] -> 0 | Q23: =IF(Table164[[#This Row],[Unit Value]]<=4999,"Low-Value Asset","High-Value Asset") -> Low-Value Asset | Z23: Unserviceable | AA23: =CONCATENATE(Table164[[#This Row],[Other Description]]," - ",IF(Table164[[#This Row],[Brand]]="n|a","",CONCATENATE("Brand: ",Table164[[#This Row],[Brand]]," - ")),IF(Table164[[#This Row],[Model]]="n|a","",CONCATENATE("Model: ",Table164[[#This Row],[Model]]," - ")),IF(Table164[[#This Row],[Serial Number]]="n|a","",CONCATENATE("SN: ",Table164[[#This Row],[Serial Number]]," - ")),IF(Table164[[#This Row],[Processor]]="n|a","",CONCATENATE("Processor: ",Table164[[#This Row],[Processor]]," - ")),IF(Table164[[#This Row],[RAM]]="n|a","",CONCATENATE("RAM: ",Table164[[#This Row],[RAM]]," - ")),IF(Table164[[#This Row],[Storage]]="n|a","",CONCATENATE("Storage: ",Table164[[#This Row],[Storage]]," - ")),IF(Table164[[#This Row],[Color]]="n|a","",CONCATENATE("Color: ",Table164[[#This Row],[Color]]))) -> - Brand: - Model: - SN: - Processor: - RAM: - Storage: - Color:
D24: =CONCATENATE(TEXT(Table164[[#This Row],[Date of Acquisition]],"yyyy")," - ", VLOOKUP(Table164[[#This Row],[Article]],'Data Validation'!$A$2:$B$16,2,FALSE)," - ",TEXT(Table164[[#This Row],[Series Number]],"0000")," - ",TEXT(VLOOKUP(Table164[[#This Row],[Location]],'Data Validation'!$A$20:$B$47,2,FALSE),"00")) -> #N/A | P24: =Table164[[#This Row],[Unit Value]]*Table164[[#This Row],[Qty | PCount]] -> 0 | Q24: =IF(Table164[[#This Row],[Unit Value]]<=4999,"Low-Value Asset","High-Value Asset") -> Low-Value Asset | Z24: Unserviceable | AA24: =CONCATENATE(Table164[[#This Row],[Other Description]]," - ",IF(Table164[[#This Row],[Brand]]="n|a","",CONCATENATE("Brand: ",Table164[[#This Row],[Brand]]," - ")),IF(Table164[[#This Row],[Model]]="n|a","",CONCATENATE("Model: ",Table164[[#This Row],[Model]]," - ")),IF(Table164[[#This Row],[Serial Number]]="n|a","",CONCATENATE("SN: ",Table164[[#This Row],[Serial Number]]," - ")),IF(Table164[[#This Row],[Processor]]="n|a","",CONCATENATE("Processor: ",Table164[[#This Row],[Processor]]," - ")),IF(Table164[[#This Row],[RAM]]="n|a","",CONCATENATE("RAM: ",Table164[[#This Row],[RAM]]," - ")),IF(Table164[[#This Row],[Storage]]="n|a","",CONCATENATE("Storage: ",Table164[[#This Row],[Storage]]," - ")),IF(Table164[[#This Row],[Color]]="n|a","",CONCATENATE("Color: ",Table164[[#This Row],[Color]]))) -> - Brand: - Model: - SN: - Processor: - RAM: - Storage: - Color:
D25: =CONCATENATE(TEXT(Table164[[#This Row],[Date of Acquisition]],"yyyy")," - ", VLOOKUP(Table164[[#This Row],[Article]],'Data Validation'!$A$2:$B$16,2,FALSE)," - ",TEXT(Table164[[#This Row],[Series Number]],"0000")," - ",TEXT(VLOOKUP(Table164[[#This Row],[Location]],'Data Validation'!$A$20:$B$47,2,FALSE),"00")) -> #N/A | P25: =Table164[[#This Row],[Unit Value]]*Table164[[#This Row],[Qty | PCount]] -> 0 | Q25: =IF(Table164[[#This Row],[Unit Value]]<=4999,"Low-Value Asset","High-Value Asset") -> Low-Value Asset | Z25: Unserviceable | AA25: =CONCATENATE(Table164[[#This Row],[Other Description]]," - ",IF(Table164[[#This Row],[Brand]]="n|a","",CONCATENATE("Brand: ",Table164[[#This Row],[Brand]]," - ")),IF(Table164[[#This Row],[Model]]="n|a","",CONCATENATE("Model: ",Table164[[#This Row],[Model]]," - ")),IF(Table164[[#This Row],[Serial Number]]="n|a","",CONCATENATE("SN: ",Table164[[#This Row],[Serial Number]]," - ")),IF(Table164[[#This Row],[Processor]]="n|a","",CONCATENATE("Processor: ",Table164[[#This Row],[Processor]]," - ")),IF(Table164[[#This Row],[RAM]]="n|a","",CONCATENATE("RAM: ",Table164[[#This Row],[RAM]]," - ")),IF(Table164[[#This Row],[Storage]]="n|a","",CONCATENATE("Storage: ",Table164[[#This Row],[Storage]]," - ")),IF(Table164[[#This Row],[Color]]="n|a","",CONCATENATE("Color: ",Table164[[#This Row],[Color]]))) -> - Brand: - Model: - SN: - Processor: - RAM: - Storage: - Color:
D26: =CONCATENATE(TEXT(Table164[[#This Row],[Date of Acquisition]],"yyyy")," - ", VLOOKUP(Table164[[#This Row],[Article]],'Data Validation'!$A$2:$B$16,2,FALSE)," - ",TEXT(Table164[[#This Row],[Series Number]],"0000")," - ",TEXT(VLOOKUP(Table164[[#This Row],[Location]],'Data Validation'!$A$20:$B$47,2,FALSE),"00")) -> #N/A | P26: =Table164[[#This Row],[Unit Value]]*Table164[[#This Row],[Qty | PCount]] -> 0 | Q26: =IF(Table164[[#This Row],[Unit Value]]<=4999,"Low-Value Asset","High-Value Asset") -> Low-Value Asset | Z26: Unserviceable | AA26: =CONCATENATE(Table164[[#This Row],[Other Description]]," - ",IF(Table164[[#This Row],[Brand]]="n|a","",CONCATENATE("Brand: ",Table164[[#This Row],[Brand]]," - ")),IF(Table164[[#This Row],[Model]]="n|a","",CONCATENATE("Model: ",Table164[[#This Row],[Model]]," - ")),IF(Table164[[#This Row],[Serial Number]]="n|a","",CONCATENATE("SN: ",Table164[[#This Row],[Serial Number]]," - ")),IF(Table164[[#This Row],[Processor]]="n|a","",CONCATENATE("Processor: ",Table164[[#This Row],[Processor]]," - ")),IF(Table164[[#This Row],[RAM]]="n|a","",CONCATENATE("RAM: ",Table164[[#This Row],[RAM]]," - ")),IF(Table164[[#This Row],[Storage]]="n|a","",CONCATENATE("Storage: ",Table164[[#This Row],[Storage]]," - ")),IF(Table164[[#This Row],[Color]]="n|a","",CONCATENATE("Color: ",Table164[[#This Row],[Color]]))) -> - Brand: - Model: - SN: - Processor: - RAM: - Storage: - Color:
D27: =CONCATENATE(TEXT(Table164[[#This Row],[Date of Acquisition]],"yyyy")," - ", VLOOKUP(Table164[[#This Row],[Article]],'Data Validation'!$A$2:$B$16,2,FALSE)," - ",TEXT(Table164[[#This Row],[Series Number]],"0000")," - ",TEXT(VLOOKUP(Table164[[#This Row],[Location]],'Data Validation'!$A$20:$B$47,2,FALSE),"00")) -> #N/A | P27: =Table164[[#This Row],[Unit Value]]*Table164[[#This Row],[Qty | PCount]] -> 0 | Q27: =IF(Table164[[#This Row],[Unit Value]]<=4999,"Low-Value Asset","High-Value Asset") -> Low-Value Asset | Z27: Unserviceable | AA27: =CONCATENATE(Table164[[#This Row],[Other Description]]," - ",IF(Table164[[#This Row],[Brand]]="n|a","",CONCATENATE("Brand: ",Table164[[#This Row],[Brand]]," - ")),IF(Table164[[#This Row],[Model]]="n|a","",CONCATENATE("Model: ",Table164[[#This Row],[Model]]," - ")),IF(Table164[[#This Row],[Serial Number]]="n|a","",CONCATENATE("SN: ",Table164[[#This Row],[Serial Number]]," - ")),IF(Table164[[#This Row],[Processor]]="n|a","",CONCATENATE("Processor: ",Table164[[#This Row],[Processor]]," - ")),IF(Table164[[#This Row],[RAM]]="n|a","",CONCATENATE("RAM: ",Table164[[#This Row],[RAM]]," - ")),IF(Table164[[#This Row],[Storage]]="n|a","",CONCATENATE("Storage: ",Table164[[#This Row],[Storage]]," - ")),IF(Table164[[#This Row],[Color]]="n|a","",CONCATENATE("Color: ",Table164[[#This Row],[Color]]))) -> - Brand: - Model: - SN: - Processor: - RAM: - Storage: - Color:
D28: =CONCATENATE(TEXT(Table164[[#This Row],[Date of Acquisition]],"yyyy")," - ", VLOOKUP(Table164[[#This Row],[Article]],'Data Validation'!$A$2:$B$16,2,FALSE)," - ",TEXT(Table164[[#This Row],[Series Number]],"0000")," - ",TEXT(VLOOKUP(Table164[[#This Row],[Location]],'Data Validation'!$A$20:$B$47,2,FALSE),"00")) -> #N/A | P28: =Table164[[#This Row],[Unit Value]]*Table164[[#This Row],[Qty | PCount]] -> 0 | Q28: =IF(Table164[[#This Row],[Unit Value]]<=4999,"Low-Value Asset","High-Value Asset") -> Low-Value Asset | Z28: Unserviceable | AA28: =CONCATENATE(Table164[[#This Row],[Other Description]]," - ",IF(Table164[[#This Row],[Brand]]="n|a","",CONCATENATE("Brand: ",Table164[[#This Row],[Brand]]," - ")),IF(Table164[[#This Row],[Model]]="n|a","",CONCATENATE("Model: ",Table164[[#This Row],[Model]]," - ")),IF(Table164[[#This Row],[Serial Number]]="n|a","",CONCATENATE("SN: ",Table164[[#This Row],[Serial Number]]," - ")),IF(Table164[[#This Row],[Processor]]="n|a","",CONCATENATE("Processor: ",Table164[[#This Row],[Processor]]," - ")),IF(Table164[[#This Row],[RAM]]="n|a","",CONCATENATE("RAM: ",Table164[[#This Row],[RAM]]," - ")),IF(Table164[[#This Row],[Storage]]="n|a","",CONCATENATE("Storage: ",Table164[[#This Row],[Storage]]," - ")),IF(Table164[[#This Row],[Color]]="n|a","",CONCATENATE("Color: ",Table164[[#This Row],[Color]]))) -> - Brand: - Model: - SN: - Processor: - RAM: - Storage: - Color:
D29: =CONCATENATE(TEXT(Table164[[#This Row],[Date of Acquisition]],"yyyy")," - ", VLOOKUP(Table164[[#This Row],[Article]],'Data Validation'!$A$2:$B$16,2,FALSE)," - ",TEXT(Table164[[#This Row],[Series Number]],"0000")," - ",TEXT(VLOOKUP(Table164[[#This Row],[Location]],'Data Validation'!$A$20:$B$47,2,FALSE),"00")) -> #N/A | P29: =Table164[[#This Row],[Unit Value]]*Table164[[#This Row],[Qty | PCount]] -> 0 | Q29: =IF(Table164[[#This Row],[Unit Value]]<=4999,"Low-Value Asset","High-Value Asset") -> Low-Value Asset | Z29: Unserviceable | AA29: =CONCATENATE(Table164[[#This Row],[Other Description]]," - ",IF(Table164[[#This Row],[Brand]]="n|a","",CONCATENATE("Brand: ",Table164[[#This Row],[Brand]]," - ")),IF(Table164[[#This Row],[Model]]="n|a","",CONCATENATE("Model: ",Table164[[#This Row],[Model]]," - ")),IF(Table164[[#This Row],[Serial Number]]="n|a","",CONCATENATE("SN: ",Table164[[#This Row],[Serial Number]]," - ")),IF(Table164[[#This Row],[Processor]]="n|a","",CONCATENATE("Processor: ",Table164[[#This Row],[Processor]]," - ")),IF(Table164[[#This Row],[RAM]]="n|a","",CONCATENATE("RAM: ",Table164[[#This Row],[RAM]]," - ")),IF(Table164[[#This Row],[Storage]]="n|a","",CONCATENATE("Storage: ",Table164[[#This Row],[Storage]]," - ")),IF(Table164[[#This Row],[Color]]="n|a","",CONCATENATE("Color: ",Table164[[#This Row],[Color]]))) -> - Brand: - Model: - SN: - Processor: - RAM: - Storage: - Color:
D30: =CONCATENATE(TEXT(Table164[[#This Row],[Date of Acquisition]],"yyyy")," - ", VLOOKUP(Table164[[#This Row],[Article]],'Data Validation'!$A$2:$B$16,2,FALSE)," - ",TEXT(Table164[[#This Row],[Series Number]],"0000")," - ",TEXT(VLOOKUP(Table164[[#This Row],[Location]],'Data Validation'!$A$20:$B$47,2,FALSE),"00")) -> #N/A | P30: =Table164[[#This Row],[Unit Value]]*Table164[[#This Row],[Qty | PCount]] -> 0 | Q30: =IF(Table164[[#This Row],[Unit Value]]<=4999,"Low-Value Asset","High-Value Asset") -> Low-Value Asset | Z30: Unserviceable | AA30: =CONCATENATE(Table164[[#This Row],[Other Description]]," - ",IF(Table164[[#This Row],[Brand]]="n|a","",CONCATENATE("Brand: ",Table164[[#This Row],[Brand]]," - ")),IF(Table164[[#This Row],[Model]]="n|a","",CONCATENATE("Model: ",Table164[[#This Row],[Model]]," - ")),IF(Table164[[#This Row],[Serial Number]]="n|a","",CONCATENATE("SN: ",Table164[[#This Row],[Serial Number]]," - ")),IF(Table164[[#This Row],[Processor]]="n|a","",CONCATENATE("Processor: ",Table164[[#This Row],[Processor]]," - ")),IF(Table164[[#This Row],[RAM]]="n|a","",CONCATENATE("RAM: ",Table164[[#This Row],[RAM]]," - ")),IF(Table164[[#This Row],[Storage]]="n|a","",CONCATENATE("Storage: ",Table164[[#This Row],[Storage]]," - ")),IF(Table164[[#This Row],[Color]]="n|a","",CONCATENATE("Color: ",Table164[[#This Row],[Color]]))) -> - Brand: - Model: - SN: - Processor: - RAM: - Storage: - Color:
D31: =CONCATENATE(TEXT(Table164[[#This Row],[Date of Acquisition]],"yyyy")," - ", VLOOKUP(Table164[[#This Row],[Article]],'Data Validation'!$A$2:$B$16,2,FALSE)," - ",TEXT(Table164[[#This Row],[Series Number]],"0000")," - ",TEXT(VLOOKUP(Table164[[#This Row],[Location]],'Data Validation'!$A$20:$B$47,2,FALSE),"00")) -> #N/A | P31: =Table164[[#This Row],[Unit Value]]*Table164[[#This Row],[Qty | PCount]] -> 0 | Q31: =IF(Table164[[#This Row],[Unit Value]]<=4999,"Low-Value Asset","High-Value Asset") -> Low-Value Asset | Z31: Unserviceable | AA31: =CONCATENATE(Table164[[#This Row],[Other Description]]," - ",IF(Table164[[#This Row],[Brand]]="n|a","",CONCATENATE("Brand: ",Table164[[#This Row],[Brand]]," - ")),IF(Table164[[#This Row],[Model]]="n|a","",CONCATENATE("Model: ",Table164[[#This Row],[Model]]," - ")),IF(Table164[[#This Row],[Serial Number]]="n|a","",CONCATENATE("SN: ",Table164[[#This Row],[Serial Number]]," - ")),IF(Table164[[#This Row],[Processor]]="n|a","",CONCATENATE("Processor: ",Table164[[#This Row],[Processor]]," - ")),IF(Table164[[#This Row],[RAM]]="n|a","",CONCATENATE("RAM: ",Table164[[#This Row],[RAM]]," - ")),IF(Table164[[#This Row],[Storage]]="n|a","",CONCATENATE("Storage: ",Table164[[#This Row],[Storage]]," - ")),IF(Table164[[#This Row],[Color]]="n|a","",CONCATENATE("Color: ",Table164[[#This Row],[Color]]))) -> - Brand: - Model: - SN: - Processor: - RAM: - Storage: - Color:
... D33: =CONCATENATE(TEXT(Table164[[#This Row],[Date of Acquisition]],"yyyy")," - ", VLOOKUP(Table164[[#This Row],[Article]],'Data Validation'!$A$2:$B$16,2,FALSE)," - ",TEXT(Table164[[#This Row],[Series Number]],"0000")," - ",TEXT(VLOOKUP(Table164[[#This Row],[Location]],'Data Validation'!$A$20:$B$47,2,FALSE),"00")) -> #N/A | P33: =Table164[[#This Row],[Unit Value]]*Table164[[#This Row],[Qty | PCount]] -> 0 | Q33: =IF(Table164[[#This Row],[Unit Value]]<=4999,"Low-Value Asset","High-Value Asset") -> Low-Value Asset | Z33: Unserviceable | AA33: =CONCATENATE(Table164[[#This Row],[Other Description]]," - ",IF(Table164[[#This Row],[Brand]]="n|a","",CONCATENATE("Brand: ",Table164[[#This Row],[Brand]]," - ")),IF(Table164[[#This Row],[Model]]="n|a","",CONCATENATE("Model: ",Table164[[#This Row],[Model]]," - ")),IF(Table164[[#This Row],[Serial Number]]="n|a","",CONCATENATE("SN: ",Table164[[#This Row],[Serial Number]]," - ")),IF(Table164[[#This Row],[Processor]]="n|a","",CONCATENATE("Processor: ",Table164[[#This Row],[Processor]]," - ")),IF(Table164[[#This Row],[RAM]]="n|a","",CONCATENATE("RAM: ",Table164[[#This Row],[RAM]]," - ")),IF(Table164[[#This Row],[Storage]]="n|a","",CONCATENATE("Storage: ",Table164[[#This Row],[Storage]]," - ")),IF(Table164[[#This Row],[Color]]="n|a","",CONCATENATE("Color: ",Table164[[#This Row],[Color]]))) -> - Brand: - Model: - SN: - Processor: - RAM: - Storage: - Color:
D34: =CONCATENATE(TEXT(Table164[[#This Row],[Date of Acquisition]],"yyyy")," - ", VLOOKUP(Table164[[#This Row],[Article]],'Data Validation'!$A$2:$B$16,2,FALSE)," - ",TEXT(Table164[[#This Row],[Series Number]],"0000")," - ",TEXT(VLOOKUP(Table164[[#This Row],[Location]],'Data Validation'!$A$20:$B$47,2,FALSE),"00")) -> #N/A | P34: =Table164[[#This Row],[Unit Value]]*Table164[[#This Row],[Qty | PCount]] -> 0 | Q34: =IF(Table164[[#This Row],[Unit Value]]<=4999,"Low-Value Asset","High-Value Asset") -> Low-Value Asset | AA34: =CONCATENATE(Table164[[#This Row],[Other Description]]," - ",IF(Table164[[#This Row],[Brand]]="n|a","",CONCATENATE("Brand: ",Table164[[#This Row],[Brand]]," - ")),IF(Table164[[#This Row],[Model]]="n|a","",CONCATENATE("Model: ",Table164[[#This Row],[Model]]," - ")),IF(Table164[[#This Row],[Serial Number]]="n|a","",CONCATENATE("SN: ",Table164[[#This Row],[Serial Number]]," - ")),IF(Table164[[#This Row],[Processor]]="n|a","",CONCATENATE("Processor: ",Table164[[#This Row],[Processor]]," - ")),IF(Table164[[#This Row],[RAM]]="n|a","",CONCATENATE("RAM: ",Table164[[#This Row],[RAM]]," - ")),IF(Table164[[#This Row],[Storage]]="n|a","",CONCATENATE("Storage: ",Table164[[#This Row],[Storage]]," - ")),IF(Table164[[#This Row],[Color]]="n|a","",CONCATENATE("Color: ",Table164[[#This Row],[Color]]))) -> - Brand: - Model: - SN: - Processor: - RAM: - Storage: - Color:
D35: =CONCATENATE(TEXT(Table164[[#This Row],[Date of Acquisition]],"yyyy")," - ", VLOOKUP(Table164[[#This Row],[Article]],'Data Validation'!$A$2:$B$16,2,FALSE)," - ",TEXT(Table164[[#This Row],[Series Number]],"0000")," - ",TEXT(VLOOKUP(Table164[[#This Row],[Location]],'Data Validation'!$A$20:$B$47,2,FALSE),"00")) -> #N/A | P35: =Table164[[#This Row],[Unit Value]]*Table164[[#This Row],[Qty | PCount]] -> 0 | Q35: =IF(Table164[[#This Row],[Unit Value]]<=4999,"Low-Value Asset","High-Value Asset") -> Low-Value Asset | AA35: =CONCATENATE(Table164[[#This Row],[Other Description]]," - ",IF(Table164[[#This Row],[Brand]]="n|a","",CONCATENATE("Brand: ",Table164[[#This Row],[Brand]]," - ")),IF(Table164[[#This Row],[Model]]="n|a","",CONCATENATE("Model: ",Table164[[#This Row],[Model]]," - ")),IF(Table164[[#This Row],[Serial Number]]="n|a","",CONCATENATE("SN: ",Table164[[#This Row],[Serial Number]]," - ")),IF(Table164[[#This Row],[Processor]]="n|a","",CONCATENATE("Processor: ",Table164[[#This Row],[Processor]]," - ")),IF(Table164[[#This Row],[RAM]]="n|a","",CONCATENATE("RAM: ",Table164[[#This Row],[RAM]]," - ")),IF(Table164[[#This Row],[Storage]]="n|a","",CONCATENATE("Storage: ",Table164[[#This Row],[Storage]]," - ")),IF(Table164[[#This Row],[Color]]="n|a","",CONCATENATE("Color: ",Table164[[#This Row],[Color]]))) -> - Brand: - Model: - SN: - Processor: - RAM: - Storage: - Color:
D36: =CONCATENATE(TEXT(Table164[[#This Row],[Date of Acquisition]],"yyyy")," - ", VLOOKUP(Table164[[#This Row],[Article]],'Data Validation'!$A$2:$B$16,2,FALSE)," - ",TEXT(Table164[[#This Row],[Series Number]],"0000")," - ",TEXT(VLOOKUP(Table164[[#This Row],[Location]],'Data Validation'!$A$20:$B$47,2,FALSE),"00")) -> #N/A | P36: =Table164[[#This Row],[Unit Value]]*Table164[[#This Row],[Qty | PCount]] -> 0 | Q36: =IF(Table164[[#This Row],[Unit Value]]<=4999,"Low-Value Asset","High-Value Asset") -> Low-Value Asset | AA36: =CONCATENATE(Table164[[#This Row],[Other Description]]," - ",IF(Table164[[#This Row],[Brand]]="n|a","",CONCATENATE("Brand: ",Table164[[#This Row],[Brand]]," - ")),IF(Table164[[#This Row],[Model]]="n|a","",CONCATENATE("Model: ",Table164[[#This Row],[Model]]," - ")),IF(Table164[[#This Row],[Serial Number]]="n|a","",CONCATENATE("SN: ",Table164[[#This Row],[Serial Number]]," - ")),IF(Table164[[#This Row],[Processor]]="n|a","",CONCATENATE("Processor: ",Table164[[#This Row],[Processor]]," - ")),IF(Table164[[#This Row],[RAM]]="n|a","",CONCATENATE("RAM: ",Table164[[#This Row],[RAM]]," - ")),IF(Table164[[#This Row],[Storage]]="n|a","",CONCATENATE("Storage: ",Table164[[#This Row],[Storage]]," - ")),IF(Table164[[#This Row],[Color]]="n|a","",CONCATENATE("Color: ",Table164[[#This Row],[Color]]))) -> - Brand: - Model: - SN: - Processor: - RAM: - Storage: - Color:
D37: =CONCATENATE(TEXT(Table164[[#This Row],[Date of Acquisition]],"yyyy")," - ", VLOOKUP(Table164[[#This Row],[Article]],'Data Validation'!$A$2:$B$16,2,FALSE)," - ",TEXT(Table164[[#This Row],[Series Number]],"0000")," - ",TEXT(VLOOKUP(Table164[[#This Row],[Location]],'Data Validation'!$A$20:$B$47,2,FALSE),"00")) -> #N/A | P37: =Table164[[#This Row],[Unit Value]]*Table164[[#This Row],[Qty | PCount]] -> 0 | Q37: =IF(Table164[[#This Row],[Unit Value]]<=4999,"Low-Value Asset","High-Value Asset") -> Low-Value Asset | AA37: =CONCATENATE(Table164[[#This Row],[Other Description]]," - ",IF(Table164[[#This Row],[Brand]]="n|a","",CONCATENATE("Brand: ",Table164[[#This Row],[Brand]]," - ")),IF(Table164[[#This Row],[Model]]="n|a","",CONCATENATE("Model: ",Table164[[#This Row],[Model]]," - ")),IF(Table164[[#This Row],[Serial Number]]="n|a","",CONCATENATE("SN: ",Table164[[#This Row],[Serial Number]]," - ")),IF(Table164[[#This Row],[Processor]]="n|a","",CONCATENATE("Processor: ",Table164[[#This Row],[Processor]]," - ")),IF(Table164[[#This Row],[RAM]]="n|a","",CONCATENATE("RAM: ",Table164[[#This Row],[RAM]]," - ")),IF(Table164[[#This Row],[Storage]]="n|a","",CONCATENATE("Storage: ",Table164[[#This Row],[Storage]]," - ")),IF(Table164[[#This Row],[Color]]="n|a","",CONCATENATE("Color: ",Table164[[#This Row],[Color]]))) -> - Brand: - Model: - SN: - Processor: - RAM: - Storage: - Color:
D38: =CONCATENATE(TEXT(Table164[[#This Row],[Date of Acquisition]],"yyyy")," - ", VLOOKUP(Table164[[#This Row],[Article]],'Data Validation'!$A$2:$B$16,2,FALSE)," - ",TEXT(Table164[[#This Row],[Series Number]],"0000")," - ",TEXT(VLOOKUP(Table164[[#This Row],[Location]],'Data Validation'!$A$20:$B$47,2,FALSE),"00")) -> #N/A | P38: =Table164[[#This Row],[Unit Value]]*Table164[[#This Row],[Qty | PCount]] -> 0 | Q38: =IF(Table164[[#This Row],[Unit Value]]<=4999,"Low-Value Asset","High-Value Asset") -> Low-Value Asset | AA38: =CONCATENATE(Table164[[#This Row],[Other Description]]," - ",IF(Table164[[#This Row],[Brand]]="n|a","",CONCATENATE("Brand: ",Table164[[#This Row],[Brand]]," - ")),IF(Table164[[#This Row],[Model]]="n|a","",CONCATENATE("Model: ",Table164[[#This Row],[Model]]," - ")),IF(Table164[[#This Row],[Serial Number]]="n|a","",CONCATENATE("SN: ",Table164[[#This Row],[Serial Number]]," - ")),IF(Table164[[#This Row],[Processor]]="n|a","",CONCATENATE("Processor: ",Table164[[#This Row],[Processor]]," - ")),IF(Table164[[#This Row],[RAM]]="n|a","",CONCATENATE("RAM: ",Table164[[#This Row],[RAM]]," - ")),IF(Table164[[#This Row],[Storage]]="n|a","",CONCATENATE("Storage: ",Table164[[#This Row],[Storage]]," - ")),IF(Table164[[#This Row],[Color]]="n|a","",CONCATENATE("Color: ",Table164[[#This Row],[Color]]))) -> - Brand: - Model: - SN: - Processor: - RAM: - Storage: - Color:
D39: =CONCATENATE(TEXT(Table164[[#This Row],[Date of Acquisition]],"yyyy")," - ", VLOOKUP(Table164[[#This Row],[Article]],'Data Validation'!$A$2:$B$16,2,FALSE)," - ",TEXT(Table164[[#This Row],[Series Number]],"0000")," - ",TEXT(VLOOKUP(Table164[[#This Row],[Location]],'Data Validation'!$A$20:$B$47,2,FALSE),"00")) -> #N/A | P39: =Table164[[#This Row],[Unit Value]]*Table164[[#This Row],[Qty | PCount]] -> 0 | Q39: =IF(Table164[[#This Row],[Unit Value]]<=4999,"Low-Value Asset","High-Value Asset") -> Low-Value Asset | AA39: =CONCATENATE(Table164[[#This Row],[Other Description]]," - ",IF(Table164[[#This Row],[Brand]]="n|a","",CONCATENATE("Brand: ",Table164[[#This Row],[Brand]]," - ")),IF(Table164[[#This Row],[Model]]="n|a","",CONCATENATE("Model: ",Table164[[#This Row],[Model]]," - ")),IF(Table164[[#This Row],[Serial Number]]="n|a","",CONCATENATE("SN: ",Table164[[#This Row],[Serial Number]]," - ")),IF(Table164[[#This Row],[Processor]]="n|a","",CONCATENATE("Processor: ",Table164[[#This Row],[Processor]]," - ")),IF(Table164[[#This Row],[RAM]]="n|a","",CONCATENATE("RAM: ",Table164[[#This Row],[RAM]]," - ")),IF(Table164[[#This Row],[Storage]]="n|a","",CONCATENATE("Storage: ",Table164[[#This Row],[Storage]]," - ")),IF(Table164[[#This Row],[Color]]="n|a","",CONCATENATE("Color: ",Table164[[#This Row],[Color]]))) -> - Brand: - Model: - SN: - Processor: - RAM: - Storage: - Color:
D40: =CONCATENATE(TEXT(Table164[[#This Row],[Date of Acquisition]],"yyyy")," - ", VLOOKUP(Table164[[#This Row],[Article]],'Data Validation'!$A$2:$B$16,2,FALSE)," - ",TEXT(Table164[[#This Row],[Series Number]],"0000")," - ",TEXT(VLOOKUP(Table164[[#This Row],[Location]],'Data Validation'!$A$20:$B$47,2,FALSE),"00")) -> #N/A | P40: =Table164[[#This Row],[Unit Value]]*Table164[[#This Row],[Qty | PCount]] -> 0 | Q40: =IF(Table164[[#This Row],[Unit Value]]<=4999,"Low-Value Asset","High-Value Asset") -> Low-Value Asset | AA40: =CONCATENATE(Table164[[#This Row],[Other Description]]," - ",IF(Table164[[#This Row],[Brand]]="n|a","",CONCATENATE("Brand: ",Table164[[#This Row],[Brand]]," - ")),IF(Table164[[#This Row],[Model]]="n|a","",CONCATENATE("Model: ",Table164[[#This Row],[Model]]," - ")),IF(Table164[[#This Row],[Serial Number]]="n|a","",CONCATENATE("SN: ",Table164[[#This Row],[Serial Number]]," - ")),IF(Table164[[#This Row],[Processor]]="n|a","",CONCATENATE("Processor: ",Table164[[#This Row],[Processor]]," - ")),IF(Table164[[#This Row],[RAM]]="n|a","",CONCATENATE("RAM: ",Table164[[#This Row],[RAM]]," - ")),IF(Table164[[#This Row],[Storage]]="n|a","",CONCATENATE("Storage: ",Table164[[#This Row],[Storage]]," - ")),IF(Table164[[#This Row],[Color]]="n|a","",CONCATENATE("Color: ",Table164[[#This Row],[Color]]))) -> - Brand: - Model: - SN: - Processor: - RAM: - Storage: - Color:
D41: =CONCATENATE(TEXT(Table164[[#This Row],[Date of Acquisition]],"yyyy")," - ", VLOOKUP(Table164[[#This Row],[Article]],'Data Validation'!$A$2:$B$16,2,FALSE)," - ",TEXT(Table164[[#This Row],[Series Number]],"0000")," - ",TEXT(VLOOKUP(Table164[[#This Row],[Location]],'Data Validation'!$A$20:$B$47,2,FALSE),"00")) -> #N/A | P41: =Table164[[#This Row],[Unit Value]]*Table164[[#This Row],[Qty | PCount]] -> 0 | Q41: =IF(Table164[[#This Row],[Unit Value]]<=4999,"Low-Value Asset","High-Value Asset") -> Low-Value Asset | AA41: =CONCATENATE(Table164[[#This Row],[Other Description]]," - ",IF(Table164[[#This Row],[Brand]]="n|a","",CONCATENATE("Brand: ",Table164[[#This Row],[Brand]]," - ")),IF(Table164[[#This Row],[Model]]="n|a","",CONCATENATE("Model: ",Table164[[#This Row],[Model]]," - ")),IF(Table164[[#This Row],[Serial Number]]="n|a","",CONCATENATE("SN: ",Table164[[#This Row],[Serial Number]]," - ")),IF(Table164[[#This Row],[Processor]]="n|a","",CONCATENATE("Processor: ",Table164[[#This Row],[Processor]]," - ")),IF(Table164[[#This Row],[RAM]]="n|a","",CONCATENATE("RAM: ",Table164[[#This Row],[RAM]]," - ")),IF(Table164[[#This Row],[Storage]]="n|a","",CONCATENATE("Storage: ",Table164[[#This Row],[Storage]]," - ")),IF(Table164[[#This Row],[Color]]="n|a","",CONCATENATE("Color: ",Table164[[#This Row],[Color]]))) -> - Brand: - Model: - SN: - Processor: - RAM: - Storage: - Color:
D42: =CONCATENATE(TEXT(Table164[[#This Row],[Date of Acquisition]],"yyyy")," - ", VLOOKUP(Table164[[#This Row],[Article]],'Data Validation'!$A$2:$B$16,2,FALSE)," - ",TEXT(Table164[[#This Row],[Series Number]],"0000")," - ",TEXT(VLOOKUP(Table164[[#This Row],[Location]],'Data Validation'!$A$20:$B$47,2,FALSE),"00")) -> #N/A | P42: =Table164[[#This Row],[Unit Value]]*Table164[[#This Row],[Qty | PCount]] -> 0 | Q42: =IF(Table164[[#This Row],[Unit Value]]<=4999,"Low-Value Asset","High-Value Asset") -> Low-Value Asset | AA42: =CONCATENATE(Table164[[#This Row],[Other Description]]," - ",IF(Table164[[#This Row],[Brand]]="n|a","",CONCATENATE("Brand: ",Table164[[#This Row],[Brand]]," - ")),IF(Table164[[#This Row],[Model]]="n|a","",CONCATENATE("Model: ",Table164[[#This Row],[Model]]," - ")),IF(Table164[[#This Row],[Serial Number]]="n|a","",CONCATENATE("SN: ",Table164[[#This Row],[Serial Number]]," - ")),IF(Table164[[#This Row],[Processor]]="n|a","",CONCATENATE("Processor: ",Table164[[#This Row],[Processor]]," - ")),IF(Table164[[#This Row],[RAM]]="n|a","",CONCATENATE("RAM: ",Table164[[#This Row],[RAM]]," - ")),IF(Table164[[#This Row],[Storage]]="n|a","",CONCATENATE("Storage: ",Table164[[#This Row],[Storage]]," - ")),IF(Table164[[#This Row],[Color]]="n|a","",CONCATENATE("Color: ",Table164[[#This Row],[Color]]))) -> - Brand: - Model: - SN: - Processor: - RAM: - Storage: - Color:
D43: =CONCATENATE(TEXT(Table164[[#This Row],[Date of Acquisition]],"yyyy")," - ", VLOOKUP(Table164[[#This Row],[Article]],'Data Validation'!$A$2:$B$16,2,FALSE)," - ",TEXT(Table164[[#This Row],[Series Number]],"0000")," - ",TEXT(VLOOKUP(Table164[[#This Row],[Location]],'Data Validation'!$A$20:$B$47,2,FALSE),"00")) -> #N/A | P43: =Table164[[#This Row],[Unit Value]]*Table164[[#This Row],[Qty | PCount]] -> 0 | Q43: =IF(Table164[[#This Row],[Unit Value]]<=4999,"Low-Value Asset","High-Value Asset") -> Low-Value Asset | AA43: =CONCATENATE(Table164[[#This Row],[Other Description]]," - ",IF(Table164[[#This Row],[Brand]]="n|a","",CONCATENATE("Brand: ",Table164[[#This Row],[Brand]]," - ")),IF(Table164[[#This Row],[Model]]="n|a","",CONCATENATE("Model: ",Table164[[#This Row],[Model]]," - ")),IF(Table164[[#This Row],[Serial Number]]="n|a","",CONCATENATE("SN: ",Table164[[#This Row],[Serial Number]]," - ")),IF(Table164[[#This Row],[Processor]]="n|a","",CONCATENATE("Processor: ",Table164[[#This Row],[Processor]]," - ")),IF(Table164[[#This Row],[RAM]]="n|a","",CONCATENATE("RAM: ",Table164[[#This Row],[RAM]]," - ")),IF(Table164[[#This Row],[Storage]]="n|a","",CONCATENATE("Storage: ",Table164[[#This Row],[Storage]]," - ")),IF(Table164[[#This Row],[Color]]="n|a","",CONCATENATE("Color: ",Table164[[#This Row],[Color]]))) -> - Brand: - Model: - SN: - Processor: - RAM: - Storage: - Color:
D44: =CONCATENATE(TEXT(Table164[[#This Row],[Date of Acquisition]],"yyyy")," - ", VLOOKUP(Table164[[#This Row],[Article]],'Data Validation'!$A$2:$B$16,2,FALSE)," - ",TEXT(Table164[[#This Row],[Series Number]],"0000")," - ",TEXT(VLOOKUP(Table164[[#This Row],[Location]],'Data Validation'!$A$20:$B$47,2,FALSE),"00")) -> #N/A | P44: =Table164[[#This Row],[Unit Value]]*Table164[[#This Row],[Qty | PCount]] -> 0 | Q44: =IF(Table164[[#This Row],[Unit Value]]<=4999,"Low-Value Asset","High-Value Asset") -> Low-Value Asset | AA44: =CONCATENATE(Table164[[#This Row],[Other Description]]," - ",IF(Table164[[#This Row],[Brand]]="n|a","",CONCATENATE("Brand: ",Table164[[#This Row],[Brand]]," - ")),IF(Table164[[#This Row],[Model]]="n|a","",CONCATENATE("Model: ",Table164[[#This Row],[Model]]," - ")),IF(Table164[[#This Row],[Serial Number]]="n|a","",CONCATENATE("SN: ",Table164[[#This Row],[Serial Number]]," - ")),IF(Table164[[#This Row],[Processor]]="n|a","",CONCATENATE("Processor: ",Table164[[#This Row],[Processor]]," - ")),IF(Table164[[#This Row],[RAM]]="n|a","",CONCATENATE("RAM: ",Table164[[#This Row],[RAM]]," - ")),IF(Table164[[#This Row],[Storage]]="n|a","",CONCATENATE("Storage: ",Table164[[#This Row],[Storage]]," - ")),IF(Table164[[#This Row],[Color]]="n|a","",CONCATENATE("Color: ",Table164[[#This Row],[Color]]))) -> - Brand: - Model: - SN: - Processor: - RAM: - Storage: - Color:
D45: =CONCATENATE(TEXT(Table164[[#This Row],[Date of Acquisition]],"yyyy")," - ", VLOOKUP(Table164[[#This Row],[Article]],'Data Validation'!$A$2:$B$16,2,FALSE)," - ",TEXT(Table164[[#This Row],[Series Number]],"0000")," - ",TEXT(VLOOKUP(Table164[[#This Row],[Location]],'Data Validation'!$A$20:$B$47,2,FALSE),"00")) -> #N/A | P45: =Table164[[#This Row],[Unit Value]]*Table164[[#This Row],[Qty | PCount]] -> 0 | Q45: =IF(Table164[[#This Row],[Unit Value]]<=4999,"Low-Value Asset","High-Value Asset") -> Low-Value Asset | AA45: =CONCATENATE(Table164[[#This Row],[Other Description]]," - ",IF(Table164[[#This Row],[Brand]]="n|a","",CONCATENATE("Brand: ",Table164[[#This Row],[Brand]]," - ")),IF(Table164[[#This Row],[Model]]="n|a","",CONCATENATE("Model: ",Table164[[#This Row],[Model]]," - ")),IF(Table164[[#This Row],[Serial Number]]="n|a","",CONCATENATE("SN: ",Table164[[#This Row],[Serial Number]]," - ")),IF(Table164[[#This Row],[Processor]]="n|a","",CONCATENATE("Processor: ",Table164[[#This Row],[Processor]]," - ")),IF(Table164[[#This Row],[RAM]]="n|a","",CONCATENATE("RAM: ",Table164[[#This Row],[RAM]]," - ")),IF(Table164[[#This Row],[Storage]]="n|a","",CONCATENATE("Storage: ",Table164[[#This Row],[Storage]]," - ")),IF(Table164[[#This Row],[Color]]="n|a","",CONCATENATE("Color: ",Table164[[#This Row],[Color]]))) -> - Brand: - Model: - SN: - Processor: - RAM: - Storage: - Color:
... D768: =CONCATENATE(TEXT(Table164[[#This Row],[Date of Acquisition]],"yyyy")," - ", VLOOKUP(Table164[[#This Row],[Article]],'Data Validation'!$A$2:$B$16,2,FALSE)," - ",TEXT(Table164[[#This Row],[Series Number]],"0000")," - ",TEXT(VLOOKUP(Table164[[#This Row],[Location]],'Data Validation'!$A$20:$B$47,2,FALSE),"00")) -> #N/A | P768: =Table164[[#This Row],[Unit Value]]*Table164[[#This Row],[Qty | PCount]] -> 0 | Q768: =IF(Table164[[#This Row],[Unit Value]]<=4999,"Low-Value Asset","High-Value Asset") -> Low-Value Asset | AA768: =CONCATENATE(Table164[[#This Row],[Other Description]]," - ",IF(Table164[[#This Row],[Brand]]="n|a","",CONCATENATE("Brand: ",Table164[[#This Row],[Brand]]," - ")),IF(Table164[[#This Row],[Model]]="n|a","",CONCATENATE("Model: ",Table164[[#This Row],[Model]]," - ")),IF(Table164[[#This Row],[Serial Number]]="n|a","",CONCATENATE("SN: ",Table164[[#This Row],[Serial Number]]," - ")),IF(Table164[[#This Row],[Processor]]="n|a","",CONCATENATE("Processor: ",Table164[[#This Row],[Processor]]," - ")),IF(Table164[[#This Row],[RAM]]="n|a","",CONCATENATE("RAM: ",Table164[[#This Row],[RAM]]," - ")),IF(Table164[[#This Row],[Storage]]="n|a","",CONCATENATE("Storage: ",Table164[[#This Row],[Storage]]," - ")),IF(Table164[[#This Row],[Color]]="n|a","",CONCATENATE("Color: ",Table164[[#This Row],[Color]]))) -> - Brand: - Model: - SN: - Processor: - RAM: - Storage: - Color:

Sheet Database PPE
A1: PAR Number | B1: Series Number | C1: Article | D1: Property Number | E1: Type of Properties | F1: Brand | G1: Model | H1: Serial Number | I1: Processor | J1: RAM | K1: Storage | L1: Color | M1: Other Description | N1: Unit of Measure | O1: Unit Value | P1: Total Value | Q1: Value Category | R1: Qty | PCard | S1: Qty | PCount | T1: S|O Qty | U1: S|O Value | V1: Date of Acquisition | W1: Location | X1: Accountable Person | Y1: Position | Z1: Source of Fund | AA1: Full Specifications | AB1: Issued ICS
D2: =CONCATENATE(TEXT(Table16[[#This Row],[Date of Acquisition]],"yyyy")," - ", VLOOKUP(Table16[[#This Row],[Article]],'Data Validation'!$A$2:$B$16,2,FALSE)," - ",TEXT(Table16[[#This Row],[Series Number]],"0000")," - ",TEXT(VLOOKUP(Table16[[#This Row],[Location]],'Data Validation'!$A$20:$B$47,2,FALSE),"00")) -> #N/A | P2: =Table16[[#This Row],[Unit Value]]*Table16[[#This Row],[Qty | PCount]] -> 0 | Q2: =IF(Table16[[#This Row],[Unit Value]]<=4999,"Low-Value Asset","High-Value Asset") -> Low-Value Asset | AA2: =CONCATENATE(Table16[[#This Row],[Other Description]]," - ",IF(Table16[[#This Row],[Brand]]="n|a","",CONCATENATE("Brand: ",Table16[[#This Row],[Brand]]," - ")),IF(Table16[[#This Row],[Model]]="n|a","",CONCATENATE("Model: ",Table16[[#This Row],[Model]]," - ")),IF(Table16[[#This Row],[Serial Number]]="n|a","",CONCATENATE("SN: ",Table16[[#This Row],[Serial Number]]," - ")),IF(Table16[[#This Row],[Processor]]="n|a","",CONCATENATE("Processor: ",Table16[[#This Row],[Processor]]," - ")),IF(Table16[[#This Row],[RAM]]="n|a","",CONCATENATE("RAM: ",Table16[[#This Row],[RAM]]," - ")),IF(Table16[[#This Row],[Storage]]="n|a","",CONCATENATE("Storage: ",Table16[[#This Row],[Storage]]," - ")),IF(Table16[[#This Row],[Color]]="n|a","",CONCATENATE("Color: ",Table16[[#This Row],[Color]]))) -> - Brand: - Model: - SN: - Processor: - RAM: - Storage: - Color:
D3: =CONCATENATE(TEXT(Table16[[#This Row],[Date of Acquisition]],"yyyy")," - ", VLOOKUP(Table16[[#This Row],[Article]],'Data Validation'!$A$2:$B$16,2,FALSE)," - ",TEXT(Table16[[#This Row],[Series Number]],"0000")," - ",TEXT(VLOOKUP(Table16[[#This Row],[Location]],'Data Validation'!$A$20:$B$47,2,FALSE),"00")) -> #N/A | P3: =Table16[[#This Row],[Unit Value]]*Table16[[#This Row],[Qty | PCount]] -> 0 | Q3: =IF(Table16[[#This Row],[Unit Value]]<=4999,"Low-Value Asset","High-Value Asset") -> Low-Value Asset | AA3: =CONCATENATE(Table16[[#This Row],[Other Description]]," - ",IF(Table16[[#This Row],[Brand]]="n|a","",CONCATENATE("Brand: ",Table16[[#This Row],[Brand]]," - ")),IF(Table16[[#This Row],[Model]]="n|a","",CONCATENATE("Model: ",Table16[[#This Row],[Model]]," - ")),IF(Table16[[#This Row],[Serial Number]]="n|a","",CONCATENATE("SN: ",Table16[[#This Row],[Serial Number]]," - ")),IF(Table16[[#This Row],[Processor]]="n|a","",CONCATENATE("Processor: ",Table16[[#This Row],[Processor]]," - ")),IF(Table16[[#This Row],[RAM]]="n|a","",CONCATENATE("RAM: ",Table16[[#This Row],[RAM]]," - ")),IF(Table16[[#This Row],[Storage]]="n|a","",CONCATENATE("Storage: ",Table16[[#This Row],[Storage]]," - ")),IF(Table16[[#This Row],[Color]]="n|a","",CONCATENATE("Color: ",Table16[[#This Row],[Color]]))) -> - Brand: - Model: - SN: - Processor: - RAM: - Storage: - Color:
D4: =CONCATENATE(TEXT(Table16[[#This Row],[Date of Acquisition]],"yyyy")," - ", VLOOKUP(Table16[[#This Row],[Article]],'Data Validation'!$A$2:$B$16,2,FALSE)," - ",TEXT(Table16[[#This Row],[Series Number]],"0000")," - ",TEXT(VLOOKUP(Table16[[#This Row],[Location]],'Data Validation'!$A$20:$B$47,2,FALSE),"00")) -> #N/A | P4: =Table16[[#This Row],[Unit Value]]*Table16[[#This Row],[Qty | PCount]] -> 0 | Q4: =IF(Table16[[#This Row],[Unit Value]]<=4999,"Low-Value Asset","High-Value Asset") -> Low-Value Asset | AA4: =CONCATENATE(Table16[[#This Row],[Other Description]]," - ",IF(Table16[[#This Row],[Brand]]="n|a","",CONCATENATE("Brand: ",Table16[[#This Row],[Brand]]," - ")),IF(Table16[[#This Row],[Model]]="n|a","",CONCATENATE("Model: ",Table16[[#This Row],[Model]]," - ")),IF(Table16[[#This Row],[Serial Number]]="n|a","",CONCATENATE("SN: ",Table16[[#This Row],[Serial Number]]," - ")),IF(Table16[[#This Row],[Processor]]="n|a","",CONCATENATE("Processor: ",Table16[[#This Row],[Processor]]," - ")),IF(Table16[[#This Row],[RAM]]="n|a","",CONCATENATE("RAM: ",Table16[[#This Row],[RAM]]," - ")),IF(Table16[[#This Row],[Storage]]="n|a","",CONCATENATE("Storage: ",Table16[[#This Row],[Storage]]," - ")),IF(Table16[[#This Row],[Color]]="n|a","",CONCATENATE("Color: ",Table16[[#This Row],[Color]]))) -> - Brand: - Model: - SN: - Processor: - RAM: - Storage: - Color:
D5: =CONCATENATE(TEXT(Table16[[#This Row],[Date of Acquisition]],"yyyy")," - ", VLOOKUP(Table16[[#This Row],[Article]],'Data Validation'!$A$2:$B$16,2,FALSE)," - ",TEXT(Table16[[#This Row],[Series Number]],"0000")," - ",TEXT(VLOOKUP(Table16[[#This Row],[Location]],'Data Validation'!$A$20:$B$47,2,FALSE),"00")) -> #N/A | P5: =Table16[[#This Row],[Unit Value]]*Table16[[#This Row],[Qty | PCount]] -> 0 | Q5: =IF(Table16[[#This Row],[Unit Value]]<=4999,"Low-Value Asset","High-Value Asset") -> Low-Value Asset | AA5: =CONCATENATE(Table16[[#This Row],[Other Description]]," - ",IF(Table16[[#This Row],[Brand]]="n|a","",CONCATENATE("Brand: ",Table16[[#This Row],[Brand]]," - ")),IF(Table16[[#This Row],[Model]]="n|a","",CONCATENATE("Model: ",Table16[[#This Row],[Model]]," - ")),IF(Table16[[#This Row],[Serial Number]]="n|a","",CONCATENATE("SN: ",Table16[[#This Row],[Serial Number]]," - ")),IF(Table16[[#This Row],[Processor]]="n|a","",CONCATENATE("Processor: ",Table16[[#This Row],[Processor]]," - ")),IF(Table16[[#This Row],[RAM]]="n|a","",CONCATENATE("RAM: ",Table16[[#This Row],[RAM]]," - ")),IF(Table16[[#This Row],[Storage]]="n|a","",CONCATENATE("Storage: ",Table16[[#This Row],[Storage]]," - ")),IF(Table16[[#This Row],[Color]]="n|a","",CONCATENATE("Color: ",Table16[[#This Row],[Color]]))) -> - Brand: - Model: - SN: - Processor: - RAM: - Storage: - Color:
D6: =CONCATENATE(TEXT(Table16[[#This Row],[Date of Acquisition]],"yyyy")," - ", VLOOKUP(Table16[[#This Row],[Article]],'Data Validation'!$A$2:$B$16,2,FALSE)," - ",TEXT(Table16[[#This Row],[Series Number]],"0000")," - ",TEXT(VLOOKUP(Table16[[#This Row],[Location]],'Data Validation'!$A$20:$B$47,2,FALSE),"00")) -> #N/A | P6: =Table16[[#This Row],[Unit Value]]*Table16[[#This Row],[Qty | PCount]] -> 0 | Q6: =IF(Table16[[#This Row],[Unit Value]]<=4999,"Low-Value Asset","High-Value Asset") -> Low-Value Asset | AA6: =CONCATENATE(Table16[[#This Row],[Other Description]]," - ",IF(Table16[[#This Row],[Brand]]="n|a","",CONCATENATE("Brand: ",Table16[[#This Row],[Brand]]," - ")),IF(Table16[[#This Row],[Model]]="n|a","",CONCATENATE("Model: ",Table16[[#This Row],[Model]]," - ")),IF(Table16[[#This Row],[Serial Number]]="n|a","",CONCATENATE("SN: ",Table16[[#This Row],[Serial Number]]," - ")),IF(Table16[[#This Row],[Processor]]="n|a","",CONCATENATE("Processor: ",Table16[[#This Row],[Processor]]," - ")),IF(Table16[[#This Row],[RAM]]="n|a","",CONCATENATE("RAM: ",Table16[[#This Row],[RAM]]," - ")),IF(Table16[[#This Row],[Storage]]="n|a","",CONCATENATE("Storage: ",Table16[[#This Row],[Storage]]," - ")),IF(Table16[[#This Row],[Color]]="n|a","",CONCATENATE("Color: ",Table16[[#This Row],[Color]]))) -> - Brand: - Model: - SN: - Processor: - RAM: - Storage: - Color: | AB6: Yes
D7: =CONCATENATE(TEXT(Table16[[#This Row],[Date of Acquisition]],"yyyy")," - ", VLOOKUP(Table16[[#This Row],[Article]],'Data Validation'!$A$2:$B$16,2,FALSE)," - ",TEXT(Table16[[#This Row],[Series Number]],"0000")," - ",TEXT(VLOOKUP(Table16[[#This Row],[Location]],'Data Validation'!$A$20:$B$47,2,FALSE),"00")) -> #N/A | P7: =Table16[[#This Row],[Unit Value]]*Table16[[#This Row],[Qty | PCount]] -> 0 | Q7: =IF(Table16[[#This Row],[Unit Value]]<=4999,"Low-Value Asset","High-Value Asset") -> Low-Value Asset | AA7: =CONCATENATE(Table16[[#This Row],[Other Description]]," - ",IF(Table16[[#This Row],[Brand]]="n|a","",CONCATENATE("Brand: ",Table16[[#This Row],[Brand]]," - ")),IF(Table16[[#This Row],[Model]]="n|a","",CONCATENATE("Model: ",Table16[[#This Row],[Model]]," - ")),IF(Table16[[#This Row],[Serial Number]]="n|a","",CONCATENATE("SN: ",Table16[[#This Row],[Serial Number]]," - ")),IF(Table16[[#This Row],[Processor]]="n|a","",CONCATENATE("Processor: ",Table16[[#This Row],[Processor]]," - ")),IF(Table16[[#This Row],[RAM]]="n|a","",CONCATENATE("RAM: ",Table16[[#This Row],[RAM]]," - ")),IF(Table16[[#This Row],[Storage]]="n|a","",CONCATENATE("Storage: ",Table16[[#This Row],[Storage]]," - ")),IF(Table16[[#This Row],[Color]]="n|a","",CONCATENATE("Color: ",Table16[[#This Row],[Color]]))) -> - Brand: - Model: - SN: - Processor: - RAM: - Storage: - Color:
D8: =CONCATENATE(TEXT(Table16[[#This Row],[Date of Acquisition]],"yyyy")," - ", VLOOKUP(Table16[[#This Row],[Article]],'Data Validation'!$A$2:$B$16,2,FALSE)," - ",TEXT(Table16[[#This Row],[Series Number]],"0000")," - ",TEXT(VLOOKUP(Table16[[#This Row],[Location]],'Data Validation'!$A$20:$B$47,2,FALSE),"00")) -> #N/A | P8: =Table16[[#This Row],[Unit Value]]*Table16[[#This Row],[Qty | PCount]] -> 0 | Q8: =IF(Table16[[#This Row],[Unit Value]]<=4999,"Low-Value Asset","High-Value Asset") -> Low-Value Asset | AA8: =CONCATENATE(Table16[[#This Row],[Other Description]]," - ",IF(Table16[[#This Row],[Brand]]="n|a","",CONCATENATE("Brand: ",Table16[[#This Row],[Brand]]," - ")),IF(Table16[[#This Row],[Model]]="n|a","",CONCATENATE("Model: ",Table16[[#This Row],[Model]]," - ")),IF(Table16[[#This Row],[Serial Number]]="n|a","",CONCATENATE("SN: ",Table16[[#This Row],[Serial Number]]," - ")),IF(Table16[[#This Row],[Processor]]="n|a","",CONCATENATE("Processor: ",Table16[[#This Row],[Processor]]," - ")),IF(Table16[[#This Row],[RAM]]="n|a","",CONCATENATE("RAM: ",Table16[[#This Row],[RAM]]," - ")),IF(Table16[[#This Row],[Storage]]="n|a","",CONCATENATE("Storage: ",Table16[[#This Row],[Storage]]," - ")),IF(Table16[[#This Row],[Color]]="n|a","",CONCATENATE("Color: ",Table16[[#This Row],[Color]]))) -> - Brand: - Model: - SN: - Processor: - RAM: - Storage: - Color:
D9: =CONCATENATE(TEXT(Table16[[#This Row],[Date of Acquisition]],"yyyy")," - ", VLOOKUP(Table16[[#This Row],[Article]],'Data Validation'!$A$2:$B$16,2,FALSE)," - ",TEXT(Table16[[#This Row],[Series Number]],"0000")," - ",TEXT(VLOOKUP(Table16[[#This Row],[Location]],'Data Validation'!$A$20:$B$47,2,FALSE),"00")) -> #N/A | P9: =Table16[[#This Row],[Unit Value]]*Table16[[#This Row],[Qty | PCount]] -> 0 | Q9: =IF(Table16[[#This Row],[Unit Value]]<=4999,"Low-Value Asset","High-Value Asset") -> Low-Value Asset | AA9: =CONCATENATE(Table16[[#This Row],[Other Description]]," - ",IF(Table16[[#This Row],[Brand]]="n|a","",CONCATENATE("Brand: ",Table16[[#This Row],[Brand]]," - ")),IF(Table16[[#This Row],[Model]]="n|a","",CONCATENATE("Model: ",Table16[[#This Row],[Model]]," - ")),IF(Table16[[#This Row],[Serial Number]]="n|a","",CONCATENATE("SN: ",Table16[[#This Row],[Serial Number]]," - ")),IF(Table16[[#This Row],[Processor]]="n|a","",CONCATENATE("Processor: ",Table16[[#This Row],[Processor]]," - ")),IF(Table16[[#This Row],[RAM]]="n|a","",CONCATENATE("RAM: ",Table16[[#This Row],[RAM]]," - ")),IF(Table16[[#This Row],[Storage]]="n|a","",CONCATENATE("Storage: ",Table16[[#This Row],[Storage]]," - ")),IF(Table16[[#This Row],[Color]]="n|a","",CONCATENATE("Color: ",Table16[[#This Row],[Color]]))) -> - Brand: - Model: - SN: - Processor: - RAM: - Storage: - Color:
D10: =CONCATENATE(TEXT(Table16[[#This Row],[Date of Acquisition]],"yyyy")," - ", VLOOKUP(Table16[[#This Row],[Article]],'Data Validation'!$A$2:$B$16,2,FALSE)," - ",TEXT(Table16[[#This Row],[Series Number]],"0000")," - ",TEXT(VLOOKUP(Table16[[#This Row],[Location]],'Data Validation'!$A$20:$B$47,2,FALSE),"00")) -> #N/A | P10: =Table16[[#This Row],[Unit Value]]*Table16[[#This Row],[Qty | PCount]] -> 0 | Q10: =IF(Table16[[#This Row],[Unit Value]]<=4999,"Low-Value Asset","High-Value Asset") -> Low-Value Asset | AA10: =CONCATENATE(Table16[[#This Row],[Other Description]]," - ",IF(Table16[[#This Row],[Brand]]="n|a","",CONCATENATE("Brand: ",Table16[[#This Row],[Brand]]," - ")),IF(Table16[[#This Row],[Model]]="n|a","",CONCATENATE("Model: ",Table16[[#This Row],[Model]]," - ")),IF(Table16[[#This Row],[Serial Number]]="n|a","",CONCATENATE("SN: ",Table16[[#This Row],[Serial Number]]," - ")),IF(Table16[[#This Row],[Processor]]="n|a","",CONCATENATE("Processor: ",Table16[[#This Row],[Processor]]," - ")),IF(Table16[[#This Row],[RAM]]="n|a","",CONCATENATE("RAM: ",Table16[[#This Row],[RAM]]," - ")),IF(Table16[[#This Row],[Storage]]="n|a","",CONCATENATE("Storage: ",Table16[[#This Row],[Storage]]," - ")),IF(Table16[[#This Row],[Color]]="n|a","",CONCATENATE("Color: ",Table16[[#This Row],[Color]]))) -> - Brand: - Model: - SN: - Processor: - RAM: - Storage: - Color:
D11: =CONCATENATE(TEXT(Table16[[#This Row],[Date of Acquisition]],"yyyy")," - ", VLOOKUP(Table16[[#This Row],[Article]],'Data Validation'!$A$2:$B$16,2,FALSE)," - ",TEXT(Table16[[#This Row],[Series Number]],"0000")," - ",TEXT(VLOOKUP(Table16[[#This Row],[Location]],'Data Validation'!$A$20:$B$47,2,FALSE),"00")) -> #N/A | P11: =Table16[[#This Row],[Unit Value]]*Table16[[#This Row],[Qty | PCount]] -> 0 | Q11: =IF(Table16[[#This Row],[Unit Value]]<=4999,"Low-Value Asset","High-Value Asset") -> Low-Value Asset | AA11: =CONCATENATE(Table16[[#This Row],[Other Description]]," - ",IF(Table16[[#This Row],[Brand]]="n|a","",CONCATENATE("Brand: ",Table16[[#This Row],[Brand]]," - ")),IF(Table16[[#This Row],[Model]]="n|a","",CONCATENATE("Model: ",Table16[[#This Row],[Model]]," - ")),IF(Table16[[#This Row],[Serial Number]]="n|a","",CONCATENATE("SN: ",Table16[[#This Row],[Serial Number]]," - ")),IF(Table16[[#This Row],[Processor]]="n|a","",CONCATENATE("Processor: ",Table16[[#This Row],[Processor]]," - ")),IF(Table16[[#This Row],[RAM]]="n|a","",CONCATENATE("RAM: ",Table16[[#This Row],[RAM]]," - ")),IF(Table16[[#This Row],[Storage]]="n|a","",CONCATENATE("Storage: ",Table16[[#This Row],[Storage]]," - ")),IF(Table16[[#This Row],[Color]]="n|a","",CONCATENATE("Color: ",Table16[[#This Row],[Color]]))) -> - Brand: - Model: - SN: - Processor: - RAM: - Storage: - Color:
D12: =CONCATENATE(TEXT(Table16[[#This Row],[Date of Acquisition]],"yyyy")," - ", VLOOKUP(Table16[[#This Row],[Article]],'Data Validation'!$A$2:$B$16,2,FALSE)," - ",TEXT(Table16[[#This Row],[Series Number]],"0000")," - ",TEXT(VLOOKUP(Table16[[#This Row],[Location]],'Data Validation'!$A$20:$B$47,2,FALSE),"00")) -> #N/A | P12: =Table16[[#This Row],[Unit Value]]*Table16[[#This Row],[Qty | PCount]] -> 0 | Q12: =IF(Table16[[#This Row],[Unit Value]]<=4999,"Low-Value Asset","High-Value Asset") -> Low-Value Asset | AA12: =CONCATENATE(Table16[[#This Row],[Other Description]]," - ",IF(Table16[[#This Row],[Brand]]="n|a","",CONCATENATE("Brand: ",Table16[[#This Row],[Brand]]," - ")),IF(Table16[[#This Row],[Model]]="n|a","",CONCATENATE("Model: ",Table16[[#This Row],[Model]]," - ")),IF(Table16[[#This Row],[Serial Number]]="n|a","",CONCATENATE("SN: ",Table16[[#This Row],[Serial Number]]," - ")),IF(Table16[[#This Row],[Processor]]="n|a","",CONCATENATE("Processor: ",Table16[[#This Row],[Processor]]," - ")),IF(Table16[[#This Row],[RAM]]="n|a","",CONCATENATE("RAM: ",Table16[[#This Row],[RAM]]," - ")),IF(Table16[[#This Row],[Storage]]="n|a","",CONCATENATE("Storage: ",Table16[[#This Row],[Storage]]," - ")),IF(Table16[[#This Row],[Color]]="n|a","",CONCATENATE("Color: ",Table16[[#This Row],[Color]]))) -> - Brand: - Model: - SN: - Processor: - RAM: - Storage: - Color:
D13: =CONCATENATE(TEXT(Table16[[#This Row],[Date of Acquisition]],"yyyy")," - ", VLOOKUP(Table16[[#This Row],[Article]],'Data Validation'!$A$2:$B$16,2,FALSE)," - ",TEXT(Table16[[#This Row],[Series Number]],"0000")," - ",TEXT(VLOOKUP(Table16[[#This Row],[Location]],'Data Validation'!$A$20:$B$47,2,FALSE),"00")) -> #N/A | P13: =Table16[[#This Row],[Unit Value]]*Table16[[#This Row],[Qty | PCount]] -> 0 | Q13: =IF(Table16[[#This Row],[Unit Value]]<=4999,"Low-Value Asset","High-Value Asset") -> Low-Value Asset | AA13: =CONCATENATE(Table16[[#This Row],[Other Description]]," - ",IF(Table16[[#This Row],[Brand]]="n|a","",CONCATENATE("Brand: ",Table16[[#This Row],[Brand]]," - ")),IF(Table16[[#This Row],[Model]]="n|a","",CONCATENATE("Model: ",Table16[[#This Row],[Model]]," - ")),IF(Table16[[#This Row],[Serial Number]]="n|a","",CONCATENATE("SN: ",Table16[[#This Row],[Serial Number]]," - ")),IF(Table16[[#This Row],[Processor]]="n|a","",CONCATENATE("Processor: ",Table16[[#This Row],[Processor]]," - ")),IF(Table16[[#This Row],[RAM]]="n|a","",CONCATENATE("RAM: ",Table16[[#This Row],[RAM]]," - ")),IF(Table16[[#This Row],[Storage]]="n|a","",CONCATENATE("Storage: ",Table16[[#This Row],[Storage]]," - ")),IF(Table16[[#This Row],[Color]]="n|a","",CONCATENATE("Color: ",Table16[[#This Row],[Color]]))) -> - Brand: - Model: - SN: - Processor: - RAM: - Storage: - Color:
D14: =CONCATENATE(TEXT(Table16[[#This Row],[Date of Acquisition]],"yyyy")," - ", VLOOKUP(Table16[[#This Row],[Article]],'Data Validation'!$A$2:$B$16,2,FALSE)," - ",TEXT(Table16[[#This Row],[Series Number]],"0000")," - ",TEXT(VLOOKUP(Table16[[#This Row],[Location]],'Data Validation'!$A$20:$B$47,2,FALSE),"00")) -> #N/A | P14: =Table16[[#This Row],[Unit Value]]*Table16[[#This Row],[Qty | PCount]] -> 0 | Q14: =IF(Table16[[#This Row],[Unit Value]]<=4999,"Low-Value Asset","High-Value Asset") -> Low-Value Asset | AA14: =CONCATENATE(Table16[[#This Row],[Other Description]]," - ",IF(Table16[[#This Row],[Brand]]="n|a","",CONCATENATE("Brand: ",Table16[[#This Row],[Brand]]," - ")),IF(Table16[[#This Row],[Model]]="n|a","",CONCATENATE("Model: ",Table16[[#This Row],[Model]]," - ")),IF(Table16[[#This Row],[Serial Number]]="n|a","",CONCATENATE("SN: ",Table16[[#This Row],[Serial Number]]," - ")),IF(Table16[[#This Row],[Processor]]="n|a","",CONCATENATE("Processor: ",Table16[[#This Row],[Processor]]," - ")),IF(Table16[[#This Row],[RAM]]="n|a","",CONCATENATE("RAM: ",Table16[[#This Row],[RAM]]," - ")),IF(Table16[[#This Row],[Storage]]="n|a","",CONCATENATE("Storage: ",Table16[[#This Row],[Storage]]," - ")),IF(Table16[[#This Row],[Color]]="n|a","",CONCATENATE("Color: ",Table16[[#This Row],[Color]]))) -> - Brand: - Model: - SN: - Processor: - RAM: - Storage: - Color:
D15: =CONCATENATE(TEXT(Table16[[#This Row],[Date of Acquisition]],"yyyy")," - ", VLOOKUP(Table16[[#This Row],[Article]],'Data Validation'!$A$2:$B$16,2,FALSE)," - ",TEXT(Table16[[#This Row],[Series Number]],"0000")," - ",TEXT(VLOOKUP(Table16[[#This Row],[Location]],'Data Validation'!$A$20:$B$47,2,FALSE),"00")) -> #N/A | P15: =Table16[[#This Row],[Unit Value]]*Table16[[#This Row],[Qty | PCount]] -> 0 | Q15: =IF(Table16[[#This Row],[Unit Value]]<=4999,"Low-Value Asset","High-Value Asset") -> Low-Value Asset | AA15: =CONCATENATE(Table16[[#This Row],[Other Description]]," - ",IF(Table16[[#This Row],[Brand]]="n|a","",CONCATENATE("Brand: ",Table16[[#This Row],[Brand]]," - ")),IF(Table16[[#This Row],[Model]]="n|a","",CONCATENATE("Model: ",Table16[[#This Row],[Model]]," - ")),IF(Table16[[#This Row],[Serial Number]]="n|a","",CONCATENATE("SN: ",Table16[[#This Row],[Serial Number]]," - ")),IF(Table16[[#This Row],[Processor]]="n|a","",CONCATENATE("Processor: ",Table16[[#This Row],[Processor]]," - ")),IF(Table16[[#This Row],[RAM]]="n|a","",CONCATENATE("RAM: ",Table16[[#This Row],[RAM]]," - ")),IF(Table16[[#This Row],[Storage]]="n|a","",CONCATENATE("Storage: ",Table16[[#This Row],[Storage]]," - ")),IF(Table16[[#This Row],[Color]]="n|a","",CONCATENATE("Color: ",Table16[[#This Row],[Color]]))) -> - Brand: - Model: - SN: - Processor: - RAM: - Storage: - Color:
D16: =CONCATENATE(TEXT(Table16[[#This Row],[Date of Acquisition]],"yyyy")," - ", VLOOKUP(Table16[[#This Row],[Article]],'Data Validation'!$A$2:$B$16,2,FALSE)," - ",TEXT(Table16[[#This Row],[Series Number]],"0000")," - ",TEXT(VLOOKUP(Table16[[#This Row],[Location]],'Data Validation'!$A$20:$B$47,2,FALSE),"00")) -> #N/A | P16: =Table16[[#This Row],[Unit Value]]*Table16[[#This Row],[Qty | PCount]] -> 0 | Q16: =IF(Table16[[#This Row],[Unit Value]]<=4999,"Low-Value Asset","High-Value Asset") -> Low-Value Asset | AA16: =CONCATENATE(Table16[[#This Row],[Other Description]]," - ",IF(Table16[[#This Row],[Brand]]="n|a","",CONCATENATE("Brand: ",Table16[[#This Row],[Brand]]," - ")),IF(Table16[[#This Row],[Model]]="n|a","",CONCATENATE("Model: ",Table16[[#This Row],[Model]]," - ")),IF(Table16[[#This Row],[Serial Number]]="n|a","",CONCATENATE("SN: ",Table16[[#This Row],[Serial Number]]," - ")),IF(Table16[[#This Row],[Processor]]="n|a","",CONCATENATE("Processor: ",Table16[[#This Row],[Processor]]," - ")),IF(Table16[[#This Row],[RAM]]="n|a","",CONCATENATE("RAM: ",Table16[[#This Row],[RAM]]," - ")),IF(Table16[[#This Row],[Storage]]="n|a","",CONCATENATE("Storage: ",Table16[[#This Row],[Storage]]," - ")),IF(Table16[[#This Row],[Color]]="n|a","",CONCATENATE("Color: ",Table16[[#This Row],[Color]]))) -> - Brand: - Model: - SN: - Processor: - RAM: - Storage: - Color:
D17: =CONCATENATE(TEXT(Table16[[#This Row],[Date of Acquisition]],"yyyy")," - ", VLOOKUP(Table16[[#This Row],[Article]],'Data Validation'!$A$2:$B$16,2,FALSE)," - ",TEXT(Table16[[#This Row],[Series Number]],"0000")," - ",TEXT(VLOOKUP(Table16[[#This Row],[Location]],'Data Validation'!$A$20:$B$47,2,FALSE),"00")) -> #N/A | P17: =Table16[[#This Row],[Unit Value]]*Table16[[#This Row],[Qty | PCount]] -> 0 | Q17: =IF(Table16[[#This Row],[Unit Value]]<=4999,"Low-Value Asset","High-Value Asset") -> Low-Value Asset | AA17: =CONCATENATE(Table16[[#This Row],[Other Description]]," - ",IF(Table16[[#This Row],[Brand]]="n|a","",CONCATENATE("Brand: ",Table16[[#This Row],[Brand]]," - ")),IF(Table16[[#This Row],[Model]]="n|a","",CONCATENATE("Model: ",Table16[[#This Row],[Model]]," - ")),IF(Table16[[#This Row],[Serial Number]]="n|a","",CONCATENATE("SN: ",Table16[[#This Row],[Serial Number]]," - ")),IF(Table16[[#This Row],[Processor]]="n|a","",CONCATENATE("Processor: ",Table16[[#This Row],[Processor]]," - ")),IF(Table16[[#This Row],[RAM]]="n|a","",CONCATENATE("RAM: ",Table16[[#This Row],[RAM]]," - ")),IF(Table16[[#This Row],[Storage]]="n|a","",CONCATENATE("Storage: ",Table16[[#This Row],[Storage]]," - ")),IF(Table16[[#This Row],[Color]]="n|a","",CONCATENATE("Color: ",Table16[[#This Row],[Color]]))) -> - Brand: - Model: - SN: - Processor: - RAM: - Storage: - Color:
D18: =CONCATENATE(TEXT(Table16[[#This Row],[Date of Acquisition]],"yyyy")," - ", VLOOKUP(Table16[[#This Row],[Article]],'Data Validation'!$A$2:$B$16,2,FALSE)," - ",TEXT(Table16[[#This Row],[Series Number]],"0000")," - ",TEXT(VLOOKUP(Table16[[#This Row],[Location]],'Data Validation'!$A$20:$B$47,2,FALSE),"00")) -> #N/A | P18: =Table16[[#This Row],[Unit Value]]*Table16[[#This Row],[Qty | PCount]] -> 0 | Q18: =IF(Table16[[#This Row],[Unit Value]]<=4999,"Low-Value Asset","High-Value Asset") -> Low-Value Asset | AA18: =CONCATENATE(Table16[[#This Row],[Other Description]]," - ",IF(Table16[[#This Row],[Brand]]="n|a","",CONCATENATE("Brand: ",Table16[[#This Row],[Brand]]," - ")),IF(Table16[[#This Row],[Model]]="n|a","",CONCATENATE("Model: ",Table16[[#This Row],[Model]]," - ")),IF(Table16[[#This Row],[Serial Number]]="n|a","",CONCATENATE("SN: ",Table16[[#This Row],[Serial Number]]," - ")),IF(Table16[[#This Row],[Processor]]="n|a","",CONCATENATE("Processor: ",Table16[[#This Row],[Processor]]," - ")),IF(Table16[[#This Row],[RAM]]="n|a","",CONCATENATE("RAM: ",Table16[[#This Row],[RAM]]," - ")),IF(Table16[[#This Row],[Storage]]="n|a","",CONCATENATE("Storage: ",Table16[[#This Row],[Storage]]," - ")),IF(Table16[[#This Row],[Color]]="n|a","",CONCATENATE("Color: ",Table16[[#This Row],[Color]]))) -> - Brand: - Model: - SN: - Processor: - RAM: - Storage: - Color:
... D38: =CONCATENATE(TEXT(Table16[[#This Row],[Date of Acquisition]],"yyyy")," - ", VLOOKUP(Table16[[#This Row],[Article]],'Data Validation'!$A$2:$B$16,2,FALSE)," - ",TEXT(Table16[[#This Row],[Series Number]],"0000")," - ",TEXT(VLOOKUP(Table16[[#This Row],[Location]],'Data Validation'!$A$20:$B$47,2,FALSE),"00")) -> #N/A | P38: =Table16[[#This Row],[Unit Value]]*Table16[[#This Row],[Qty | PCount]] -> 0 | Q38: =IF(Table16[[#This Row],[Unit Value]]<=4999,"Low-Value Asset","High-Value Asset") -> Low-Value Asset | AA38: =CONCATENATE(Table16[[#This Row],[Other Description]]," - ",IF(Table16[[#This Row],[Brand]]="n|a","",CONCATENATE("Brand: ",Table16[[#This Row],[Brand]]," - ")),IF(Table16[[#This Row],[Model]]="n|a","",CONCATENATE("Model: ",Table16[[#This Row],[Model]]," - ")),IF(Table16[[#This Row],[Serial Number]]="n|a","",CONCATENATE("SN: ",Table16[[#This Row],[Serial Number]]," - ")),IF(Table16[[#This Row],[Processor]]="n|a","",CONCATENATE("Processor: ",Table16[[#This Row],[Processor]]," - ")),IF(Table16[[#This Row],[RAM]]="n|a","",CONCATENATE("RAM: ",Table16[[#This Row],[RAM]]," - ")),IF(Table16[[#This Row],[Storage]]="n|a","",CONCATENATE("Storage: ",Table16[[#This Row],[Storage]]," - ")),IF(Table16[[#This Row],[Color]]="n|a","",CONCATENATE("Color: ",Table16[[#This Row],[Color]]))) -> - Brand: - Model: - SN: - Processor: - RAM: - Storage: - Color:
D39: =CONCATENATE(TEXT(Table16[[#This Row],[Date of Acquisition]],"yyyy")," - ", VLOOKUP(Table16[[#This Row],[Article]],'Data Validation'!$A$2:$B$16,2,FALSE)," - ",TEXT(Table16[[#This Row],[Series Number]],"0000")," - ",TEXT(VLOOKUP(Table16[[#This Row],[Location]],'Data Validation'!$A$20:$B$47,2,FALSE),"00")) -> #N/A | P39: =Table16[[#This Row],[Unit Value]]*Table16[[#This Row],[Qty | PCount]] -> 0 | Q39: =IF(Table16[[#This Row],[Unit Value]]<=4999,"Low-Value Asset","High-Value Asset") -> Low-Value Asset | AA39: =CONCATENATE(Table16[[#This Row],[Other Description]]," - ",IF(Table16[[#This Row],[Brand]]="n|a","",CONCATENATE("Brand: ",Table16[[#This Row],[Brand]]," - ")),IF(Table16[[#This Row],[Model]]="n|a","",CONCATENATE("Model: ",Table16[[#This Row],[Model]]," - ")),IF(Table16[[#This Row],[Serial Number]]="n|a","",CONCATENATE("SN: ",Table16[[#This Row],[Serial Number]]," - ")),IF(Table16[[#This Row],[Processor]]="n|a","",CONCATENATE("Processor: ",Table16[[#This Row],[Processor]]," - ")),IF(Table16[[#This Row],[RAM]]="n|a","",CONCATENATE("RAM: ",Table16[[#This Row],[RAM]]," - ")),IF(Table16[[#This Row],[Storage]]="n|a","",CONCATENATE("Storage: ",Table16[[#This Row],[Storage]]," - ")),IF(Table16[[#This Row],[Color]]="n|a","",CONCATENATE("Color: ",Table16[[#This Row],[Color]]))) -> - Brand: - Model: - SN: - Processor: - RAM: - Storage: - Color: | AD39: Angelo Pasion, Chester Cabuco, Rex Tosco, Arlie Amor Guinto
D40: =CONCATENATE(TEXT(Table16[[#This Row],[Date of Acquisition]],"yyyy")," - ", VLOOKUP(Table16[[#This Row],[Article]],'Data Validation'!$A$2:$B$16,2,FALSE)," - ",TEXT(Table16[[#This Row],[Series Number]],"0000")," - ",TEXT(VLOOKUP(Table16[[#This Row],[Location]],'Data Validation'!$A$20:$B$47,2,FALSE),"00")) -> #N/A | P40: =Table16[[#This Row],[Unit Value]]*Table16[[#This Row],[Qty | PCount]] -> 0 | Q40: =IF(Table16[[#This Row],[Unit Value]]<=4999,"Low-Value Asset","High-Value Asset") -> Low-Value Asset | AA40: =CONCATENATE(Table16[[#This Row],[Other Description]]," - ",IF(Table16[[#This Row],[Brand]]="n|a","",CONCATENATE("Brand: ",Table16[[#This Row],[Brand]]," - ")),IF(Table16[[#This Row],[Model]]="n|a","",CONCATENATE("Model: ",Table16[[#This Row],[Model]]," - ")),IF(Table16[[#This Row],[Serial Number]]="n|a","",CONCATENATE("SN: ",Table16[[#This Row],[Serial Number]]," - ")),IF(Table16[[#This Row],[Processor]]="n|a","",CONCATENATE("Processor: ",Table16[[#This Row],[Processor]]," - ")),IF(Table16[[#This Row],[RAM]]="n|a","",CONCATENATE("RAM: ",Table16[[#This Row],[RAM]]," - ")),IF(Table16[[#This Row],[Storage]]="n|a","",CONCATENATE("Storage: ",Table16[[#This Row],[Storage]]," - ")),IF(Table16[[#This Row],[Color]]="n|a","",CONCATENATE("Color: ",Table16[[#This Row],[Color]]))) -> - Brand: - Model: - SN: - Processor: - RAM: - Storage: - Color:
D41: =CONCATENATE(TEXT(Table16[[#This Row],[Date of Acquisition]],"yyyy")," - ", VLOOKUP(Table16[[#This Row],[Article]],'Data Validation'!$A$2:$B$16,2,FALSE)," - ",TEXT(Table16[[#This Row],[Series Number]],"0000")," - ",TEXT(VLOOKUP(Table16[[#This Row],[Location]],'Data Validation'!$A$20:$B$47,2,FALSE),"00")) -> #N/A | P41: =Table16[[#This Row],[Unit Value]]*Table16[[#This Row],[Qty | PCount]] -> 0 | Q41: =IF(Table16[[#This Row],[Unit Value]]<=4999,"Low-Value Asset","High-Value Asset") -> Low-Value Asset | AA41: =CONCATENATE(Table16[[#This Row],[Other Description]]," - ",IF(Table16[[#This Row],[Brand]]="n|a","",CONCATENATE("Brand: ",Table16[[#This Row],[Brand]]," - ")),IF(Table16[[#This Row],[Model]]="n|a","",CONCATENATE("Model: ",Table16[[#This Row],[Model]]," - ")),IF(Table16[[#This Row],[Serial Number]]="n|a","",CONCATENATE("SN: ",Table16[[#This Row],[Serial Number]]," - ")),IF(Table16[[#This Row],[Processor]]="n|a","",CONCATENATE("Processor: ",Table16[[#This Row],[Processor]]," - ")),IF(Table16[[#This Row],[RAM]]="n|a","",CONCATENATE("RAM: ",Table16[[#This Row],[RAM]]," - ")),IF(Table16[[#This Row],[Storage]]="n|a","",CONCATENATE("Storage: ",Table16[[#This Row],[Storage]]," - ")),IF(Table16[[#This Row],[Color]]="n|a","",CONCATENATE("Color: ",Table16[[#This Row],[Color]]))) -> - Brand: - Model: - SN: - Processor: - RAM: - Storage: - Color:
D42: =CONCATENATE(TEXT(Table16[[#This Row],[Date of Acquisition]],"yyyy")," - ", VLOOKUP(Table16[[#This Row],[Article]],'Data Validation'!$A$2:$B$16,2,FALSE)," - ",TEXT(Table16[[#This Row],[Series Number]],"0000")," - ",TEXT(VLOOKUP(Table16[[#This Row],[Location]],'Data Validation'!$A$20:$B$47,2,FALSE),"00")) -> #N/A | P42: =Table16[[#This Row],[Unit Value]]*Table16[[#This Row],[Qty | PCount]] -> 0 | Q42: =IF(Table16[[#This Row],[Unit Value]]<=4999,"Low-Value Asset","High-Value Asset") -> Low-Value Asset | AA42: =CONCATENATE(Table16[[#This Row],[Other Description]]," - ",IF(Table16[[#This Row],[Brand]]="n|a","",CONCATENATE("Brand: ",Table16[[#This Row],[Brand]]," - ")),IF(Table16[[#This Row],[Model]]="n|a","",CONCATENATE("Model: ",Table16[[#This Row],[Model]]," - ")),IF(Table16[[#This Row],[Serial Number]]="n|a","",CONCATENATE("SN: ",Table16[[#This Row],[Serial Number]]," - ")),IF(Table16[[#This Row],[Processor]]="n|a","",CONCATENATE("Processor: ",Table16[[#This Row],[Processor]]," - ")),IF(Table16[[#This Row],[RAM]]="n|a","",CONCATENATE("RAM: ",Table16[[#This Row],[RAM]]," - ")),IF(Table16[[#This Row],[Storage]]="n|a","",CONCATENATE("Storage: ",Table16[[#This Row],[Storage]]," - ")),IF(Table16[[#This Row],[Color]]="n|a","",CONCATENATE("Color: ",Table16[[#This Row],[Color]]))) -> - Brand: - Model: - SN: - Processor: - RAM: - Storage: - Color:
D43: =CONCATENATE(TEXT(Table16[[#This Row],[Date of Acquisition]],"yyyy")," - ", VLOOKUP(Table16[[#This Row],[Article]],'Data Validation'!$A$2:$B$16,2,FALSE)," - ",TEXT(Table16[[#This Row],[Series Number]],"0000")," - ",TEXT(VLOOKUP(Table16[[#This Row],[Location]],'Data Validation'!$A$20:$B$47,2,FALSE),"00")) -> #N/A | P43: =Table16[[#This Row],[Unit Value]]*Table16[[#This Row],[Qty | PCount]] -> 0 | Q43: =IF(Table16[[#This Row],[Unit Value]]<=4999,"Low-Value Asset","High-Value Asset") -> Low-Value Asset | AA43: =CONCATENATE(Table16[[#This Row],[Other Description]]," - ",IF(Table16[[#This Row],[Brand]]="n|a","",CONCATENATE("Brand: ",Table16[[#This Row],[Brand]]," - ")),IF(Table16[[#This Row],[Model]]="n|a","",CONCATENATE("Model: ",Table16[[#This Row],[Model]]," - ")),IF(Table16[[#This Row],[Serial Number]]="n|a","",CONCATENATE("SN: ",Table16[[#This Row],[Serial Number]]," - ")),IF(Table16[[#This Row],[Processor]]="n|a","",CONCATENATE("Processor: ",Table16[[#This Row],[Processor]]," - ")),IF(Table16[[#This Row],[RAM]]="n|a","",CONCATENATE("RAM: ",Table16[[#This Row],[RAM]]," - ")),IF(Table16[[#This Row],[Storage]]="n|a","",CONCATENATE("Storage: ",Table16[[#This Row],[Storage]]," - ")),IF(Table16[[#This Row],[Color]]="n|a","",CONCATENATE("Color: ",Table16[[#This Row],[Color]]))) -> - Brand: - Model: - SN: - Processor: - RAM: - Storage: - Color:
D44: =CONCATENATE(TEXT(Table16[[#This Row],[Date of Acquisition]],"yyyy")," - ", VLOOKUP(Table16[[#This Row],[Article]],'Data Validation'!$A$2:$B$16,2,FALSE)," - ",TEXT(Table16[[#This Row],[Series Number]],"0000")," - ",TEXT(VLOOKUP(Table16[[#This Row],[Location]],'Data Validation'!$A$20:$B$47,2,FALSE),"00")) -> #N/A | P44: =Table16[[#This Row],[Unit Value]]*Table16[[#This Row],[Qty | PCount]] -> 0 | Q44: =IF(Table16[[#This Row],[Unit Value]]<=4999,"Low-Value Asset","High-Value Asset") -> Low-Value Asset | AA44: =CONCATENATE(Table16[[#This Row],[Other Description]]," - ",IF(Table16[[#This Row],[Brand]]="n|a","",CONCATENATE("Brand: ",Table16[[#This Row],[Brand]]," - ")),IF(Table16[[#This Row],[Model]]="n|a","",CONCATENATE("Model: ",Table16[[#This Row],[Model]]," - ")),IF(Table16[[#This Row],[Serial Number]]="n|a","",CONCATENATE("SN: ",Table16[[#This Row],[Serial Number]]," - ")),IF(Table16[[#This Row],[Processor]]="n|a","",CONCATENATE("Processor: ",Table16[[#This Row],[Processor]]," - ")),IF(Table16[[#This Row],[RAM]]="n|a","",CONCATENATE("RAM: ",Table16[[#This Row],[RAM]]," - ")),IF(Table16[[#This Row],[Storage]]="n|a","",CONCATENATE("Storage: ",Table16[[#This Row],[Storage]]," - ")),IF(Table16[[#This Row],[Color]]="n|a","",CONCATENATE("Color: ",Table16[[#This Row],[Color]]))) -> - Brand: - Model: - SN: - Processor: - RAM: - Storage: - Color:
D45: =CONCATENATE(TEXT(Table16[[#This Row],[Date of Acquisition]],"yyyy")," - ", VLOOKUP(Table16[[#This Row],[Article]],'Data Validation'!$A$2:$B$16,2,FALSE)," - ",TEXT(Table16[[#This Row],[Series Number]],"0000")," - ",TEXT(VLOOKUP(Table16[[#This Row],[Location]],'Data Validation'!$A$20:$B$47,2,FALSE),"00")) -> #N/A | P45: =Table16[[#This Row],[Unit Value]]*Table16[[#This Row],[Qty | PCount]] -> 0 | Q45: =IF(Table16[[#This Row],[Unit Value]]<=4999,"Low-Value Asset","High-Value Asset") -> Low-Value Asset | AA45: =CONCATENATE(Table16[[#This Row],[Other Description]]," - ",IF(Table16[[#This Row],[Brand]]="n|a","",CONCATENATE("Brand: ",Table16[[#This Row],[Brand]]," - ")),IF(Table16[[#This Row],[Model]]="n|a","",CONCATENATE("Model: ",Table16[[#This Row],[Model]]," - ")),IF(Table16[[#This Row],[Serial Number]]="n|a","",CONCATENATE("SN: ",Table16[[#This Row],[Serial Number]]," - ")),IF(Table16[[#This Row],[Processor]]="n|a","",CONCATENATE("Processor: ",Table16[[#This Row],[Processor]]," - ")),IF(Table16[[#This Row],[RAM]]="n|a","",CONCATENATE("RAM: ",Table16[[#This Row],[RAM]]," - ")),IF(Table16[[#This Row],[Storage]]="n|a","",CONCATENATE("Storage: ",Table16[[#This Row],[Storage]]," - ")),IF(Table16[[#This Row],[Color]]="n|a","",CONCATENATE("Color: ",Table16[[#This Row],[Color]]))) -> - Brand: - Model: - SN: - Processor: - RAM: - Storage: - Color:
D46: =CONCATENATE(TEXT(Table16[[#This Row],[Date of Acquisition]],"yyyy")," - ", VLOOKUP(Table16[[#This Row],[Article]],'Data Validation'!$A$2:$B$16,2,FALSE)," - ",TEXT(Table16[[#This Row],[Series Number]],"0000")," - ",TEXT(VLOOKUP(Table16[[#This Row],[Location]],'Data Validation'!$A$20:$B$47,2,FALSE),"00")) -> #N/A | P46: =Table16[[#This Row],[Unit Value]]*Table16[[#This Row],[Qty | PCount]] -> 0 | Q46: =IF(Table16[[#This Row],[Unit Value]]<=4999,"Low-Value Asset","High-Value Asset") -> Low-Value Asset | AA46: =CONCATENATE(Table16[[#This Row],[Other Description]]," - ",IF(Table16[[#This Row],[Brand]]="n|a","",CONCATENATE("Brand: ",Table16[[#This Row],[Brand]]," - ")),IF(Table16[[#This Row],[Model]]="n|a","",CONCATENATE("Model: ",Table16[[#This Row],[Model]]," - ")),IF(Table16[[#This Row],[Serial Number]]="n|a","",CONCATENATE("SN: ",Table16[[#This Row],[Serial Number]]," - ")),IF(Table16[[#This Row],[Processor]]="n|a","",CONCATENATE("Processor: ",Table16[[#This Row],[Processor]]," - ")),IF(Table16[[#This Row],[RAM]]="n|a","",CONCATENATE("RAM: ",Table16[[#This Row],[RAM]]," - ")),IF(Table16[[#This Row],[Storage]]="n|a","",CONCATENATE("Storage: ",Table16[[#This Row],[Storage]]," - ")),IF(Table16[[#This Row],[Color]]="n|a","",CONCATENATE("Color: ",Table16[[#This Row],[Color]]))) -> - Brand: - Model: - SN: - Processor: - RAM: - Storage: - Color:
D47: =CONCATENATE(TEXT(Table16[[#This Row],[Date of Acquisition]],"yyyy")," - ", VLOOKUP(Table16[[#This Row],[Article]],'Data Validation'!$A$2:$B$16,2,FALSE)," - ",TEXT(Table16[[#This Row],[Series Number]],"0000")," - ",TEXT(VLOOKUP(Table16[[#This Row],[Location]],'Data Validation'!$A$20:$B$47,2,FALSE),"00")) -> #N/A | P47: =Table16[[#This Row],[Unit Value]]*Table16[[#This Row],[Qty | PCount]] -> 0 | Q47: =IF(Table16[[#This Row],[Unit Value]]<=4999,"Low-Value Asset","High-Value Asset") -> Low-Value Asset | AA47: =CONCATENATE(Table16[[#This Row],[Other Description]]," - ",IF(Table16[[#This Row],[Brand]]="n|a","",CONCATENATE("Brand: ",Table16[[#This Row],[Brand]]," - ")),IF(Table16[[#This Row],[Model]]="n|a","",CONCATENATE("Model: ",Table16[[#This Row],[Model]]," - ")),IF(Table16[[#This Row],[Serial Number]]="n|a","",CONCATENATE("SN: ",Table16[[#This Row],[Serial Number]]," - ")),IF(Table16[[#This Row],[Processor]]="n|a","",CONCATENATE("Processor: ",Table16[[#This Row],[Processor]]," - ")),IF(Table16[[#This Row],[RAM]]="n|a","",CONCATENATE("RAM: ",Table16[[#This Row],[RAM]]," - ")),IF(Table16[[#This Row],[Storage]]="n|a","",CONCATENATE("Storage: ",Table16[[#This Row],[Storage]]," - ")),IF(Table16[[#This Row],[Color]]="n|a","",CONCATENATE("Color: ",Table16[[#This Row],[Color]]))) -> - Brand: - Model: - SN: - Processor: - RAM: - Storage: - Color:
D48: =CONCATENATE(TEXT(Table16[[#This Row],[Date of Acquisition]],"yyyy")," - ", VLOOKUP(Table16[[#This Row],[Article]],'Data Validation'!$A$2:$B$16,2,FALSE)," - ",TEXT(Table16[[#This Row],[Series Number]],"0000")," - ",TEXT(VLOOKUP(Table16[[#This Row],[Location]],'Data Validation'!$A$20:$B$47,2,FALSE),"00")) -> #N/A | P48: =Table16[[#This Row],[Unit Value]]*Table16[[#This Row],[Qty | PCount]] -> 0 | Q48: =IF(Table16[[#This Row],[Unit Value]]<=4999,"Low-Value Asset","High-Value Asset") -> Low-Value Asset | AA48: =CONCATENATE(Table16[[#This Row],[Other Description]]," - ",IF(Table16[[#This Row],[Brand]]="n|a","",CONCATENATE("Brand: ",Table16[[#This Row],[Brand]]," - ")),IF(Table16[[#This Row],[Model]]="n|a","",CONCATENATE("Model: ",Table16[[#This Row],[Model]]," - ")),IF(Table16[[#This Row],[Serial Number]]="n|a","",CONCATENATE("SN: ",Table16[[#This Row],[Serial Number]]," - ")),IF(Table16[[#This Row],[Processor]]="n|a","",CONCATENATE("Processor: ",Table16[[#This Row],[Processor]]," - ")),IF(Table16[[#This Row],[RAM]]="n|a","",CONCATENATE("RAM: ",Table16[[#This Row],[RAM]]," - ")),IF(Table16[[#This Row],[Storage]]="n|a","",CONCATENATE("Storage: ",Table16[[#This Row],[Storage]]," - ")),IF(Table16[[#This Row],[Color]]="n|a","",CONCATENATE("Color: ",Table16[[#This Row],[Color]]))) -> - Brand: - Model: - SN: - Processor: - RAM: - Storage: - Color:
D49: =CONCATENATE(TEXT(Table16[[#This Row],[Date of Acquisition]],"yyyy")," - ", VLOOKUP(Table16[[#This Row],[Article]],'Data Validation'!$A$2:$B$16,2,FALSE)," - ",TEXT(Table16[[#This Row],[Series Number]],"0000")," - ",TEXT(VLOOKUP(Table16[[#This Row],[Location]],'Data Validation'!$A$20:$B$47,2,FALSE),"00")) -> #N/A | P49: =Table16[[#This Row],[Unit Value]]*Table16[[#This Row],[Qty | PCount]] -> 0 | Q49: =IF(Table16[[#This Row],[Unit Value]]<=4999,"Low-Value Asset","High-Value Asset") -> Low-Value Asset | AA49: =CONCATENATE(Table16[[#This Row],[Other Description]]," - ",IF(Table16[[#This Row],[Brand]]="n|a","",CONCATENATE("Brand: ",Table16[[#This Row],[Brand]]," - ")),IF(Table16[[#This Row],[Model]]="n|a","",CONCATENATE("Model: ",Table16[[#This Row],[Model]]," - ")),IF(Table16[[#This Row],[Serial Number]]="n|a","",CONCATENATE("SN: ",Table16[[#This Row],[Serial Number]]," - ")),IF(Table16[[#This Row],[Processor]]="n|a","",CONCATENATE("Processor: ",Table16[[#This Row],[Processor]]," - ")),IF(Table16[[#This Row],[RAM]]="n|a","",CONCATENATE("RAM: ",Table16[[#This Row],[RAM]]," - ")),IF(Table16[[#This Row],[Storage]]="n|a","",CONCATENATE("Storage: ",Table16[[#This Row],[Storage]]," - ")),IF(Table16[[#This Row],[Color]]="n|a","",CONCATENATE("Color: ",Table16[[#This Row],[Color]]))) -> - Brand: - Model: - SN: - Processor: - RAM: - Storage: - Color:
D50: =CONCATENATE(TEXT(Table16[[#This Row],[Date of Acquisition]],"yyyy")," - ", VLOOKUP(Table16[[#This Row],[Article]],'Data Validation'!$A$2:$B$16,2,FALSE)," - ",TEXT(Table16[[#This Row],[Series Number]],"0000")," - ",TEXT(VLOOKUP(Table16[[#This Row],[Location]],'Data Validation'!$A$20:$B$47,2,FALSE),"00")) -> #N/A | P50: =Table16[[#This Row],[Unit Value]]*Table16[[#This Row],[Qty | PCount]] -> 0 | Q50: =IF(Table16[[#This Row],[Unit Value]]<=4999,"Low-Value Asset","High-Value Asset") -> Low-Value Asset | AA50: =CONCATENATE(Table16[[#This Row],[Other Description]]," - ",IF(Table16[[#This Row],[Brand]]="n|a","",CONCATENATE("Brand: ",Table16[[#This Row],[Brand]]," - ")),IF(Table16[[#This Row],[Model]]="n|a","",CONCATENATE("Model: ",Table16[[#This Row],[Model]]," - ")),IF(Table16[[#This Row],[Serial Number]]="n|a","",CONCATENATE("SN: ",Table16[[#This Row],[Serial Number]]," - ")),IF(Table16[[#This Row],[Processor]]="n|a","",CONCATENATE("Processor: ",Table16[[#This Row],[Processor]]," - ")),IF(Table16[[#This Row],[RAM]]="n|a","",CONCATENATE("RAM: ",Table16[[#This Row],[RAM]]," - ")),IF(Table16[[#This Row],[Storage]]="n|a","",CONCATENATE("Storage: ",Table16[[#This Row],[Storage]]," - ")),IF(Table16[[#This Row],[Color]]="n|a","",CONCATENATE("Color: ",Table16[[#This Row],[Color]]))) -> - Brand: - Model: - SN: - Processor: - RAM: - Storage: - Color:
D51: =CONCATENATE(TEXT(Table16[[#This Row],[Date of Acquisition]],"yyyy")," - ", VLOOKUP(Table16[[#This Row],[Article]],'Data Validation'!$A$2:$B$16,2,FALSE)," - ",TEXT(Table16[[#This Row],[Series Number]],"0000")," - ",TEXT(VLOOKUP(Table16[[#This Row],[Location]],'Data Validation'!$A$20:$B$47,2,FALSE),"00")) -> #N/A | P51: =Table16[[#This Row],[Unit Value]]*Table16[[#This Row],[Qty | PCount]] -> 0 | Q51: =IF(Table16[[#This Row],[Unit Value]]<=4999,"Low-Value Asset","High-Value Asset") -> Low-Value Asset | AA51: =CONCATENATE(Table16[[#This Row],[Other Description]]," - ",IF(Table16[[#This Row],[Brand]]="n|a","",CONCATENATE("Brand: ",Table16[[#This Row],[Brand]]," - ")),IF(Table16[[#This Row],[Model]]="n|a","",CONCATENATE("Model: ",Table16[[#This Row],[Model]]," - ")),IF(Table16[[#This Row],[Serial Number]]="n|a","",CONCATENATE("SN: ",Table16[[#This Row],[Serial Number]]," - ")),IF(Table16[[#This Row],[Processor]]="n|a","",CONCATENATE("Processor: ",Table16[[#This Row],[Processor]]," - ")),IF(Table16[[#This Row],[RAM]]="n|a","",CONCATENATE("RAM: ",Table16[[#This Row],[RAM]]," - ")),IF(Table16[[#This Row],[Storage]]="n|a","",CONCATENATE("Storage: ",Table16[[#This Row],[Storage]]," - ")),IF(Table16[[#This Row],[Color]]="n|a","",CONCATENATE("Color: ",Table16[[#This Row],[Color]]))) -> - Brand: - Model: - SN: - Processor: - RAM: - Storage: - Color:
... D86: =CONCATENATE(TEXT(Table16[[#This Row],[Date of Acquisition]],"yyyy")," - ", VLOOKUP(Table16[[#This Row],[Article]],'Data Validation'!$A$2:$B$16,2,FALSE)," - ",TEXT(Table16[[#This Row],[Series Number]],"0000")," - ",TEXT(VLOOKUP(Table16[[#This Row],[Location]],'Data Validation'!$A$20:$B$47,2,FALSE),"00")) -> #N/A | P86: =Table16[[#This Row],[Unit Value]]*Table16[[#This Row],[Qty | PCount]] -> 0 | Q86: =IF(Table16[[#This Row],[Unit Value]]<=4999,"Low-Value Asset","High-Value Asset") -> Low-Value Asset | AA86: =CONCATENATE(Table16[[#This Row],[Other Description]]," - ",IF(Table16[[#This Row],[Brand]]="n|a","",CONCATENATE("Brand: ",Table16[[#This Row],[Brand]]," - ")),IF(Table16[[#This Row],[Model]]="n|a","",CONCATENATE("Model: ",Table16[[#This Row],[Model]]," - ")),IF(Table16[[#This Row],[Serial Number]]="n|a","",CONCATENATE("SN: ",Table16[[#This Row],[Serial Number]]," - ")),IF(Table16[[#This Row],[Processor]]="n|a","",CONCATENATE("Processor: ",Table16[[#This Row],[Processor]]," - ")),IF(Table16[[#This Row],[RAM]]="n|a","",CONCATENATE("RAM: ",Table16[[#This Row],[RAM]]," - ")),IF(Table16[[#This Row],[Storage]]="n|a","",CONCATENATE("Storage: ",Table16[[#This Row],[Storage]]," - ")),IF(Table16[[#This Row],[Color]]="n|a","",CONCATENATE("Color: ",Table16[[#This Row],[Color]]))) -> - Brand: - Model: - SN: - Processor: - RAM: - Storage: - Color:

Sheet LR Schools
A1: ICS Number | B1: Series Number | C1: Article | D1: Property Number | E1: Type of Properties | F1: Supplier | G1: Subject | H1: Quarter | I1: Grade Level | J1: Delivery Receipt Number | K1: Contract Number | L1: PTR Number | M1: Origin | N1: Title | O1: Unit of Measure | P1: Unit Value | Q1: Total Value | R1: Value Category | S1: Qty | PCard | T1: Qty | PCount | U1: S|O Qty | V1: S|O Value | W1: Date of Acquisition | X1: Location | Y1: Accountable Person | Z1: Position | AA1: Source of Fund | AB1: Full Specifications
D2: =CONCATENATE(TEXT(Table13[[#This Row],[Date of Acquisition]],"yyyy")," - ", VLOOKUP(Table13[[#This Row],[Article]],'Data Validation'!$A$2:$B$16,2,FALSE)," - ",TEXT(Table13[[#This Row],[Series Number]],"0000")," - ",TEXT(VLOOKUP(Table13[[#This Row],[Location]],'Data Validation'!$A$20:$B$47,2,FALSE),"00")) -> #N/A | Q2: =Table13[[#This Row],[Unit Value]]*Table13[[#This Row],[Qty | PCount]] -> 0 | R2: =IF(Table13[[#This Row],[Unit Value]]<=4999,"Low-Value Asset","High-Value Asset") -> Low-Value Asset | AB2: =CONCATENATE(Table13[[#This Row],[Title]]," - ",IF(Table13[[#This Row],[Supplier]]="n|a","",CONCATENATE("Supplier: ",Table13[[#This Row],[Supplier]]," - ")),IF(Table13[[#This Row],[Subject]]="n|a","",CONCATENATE("Subject: ",Table13[[#This Row],[Subject]]," - ")),IF(Table13[[#This Row],[Quarter]]="n|a","",CONCATENATE("Quarter: ",Table13[[#This Row],[Quarter]]," - ")),IF(Table13[[#This Row],[Grade Level]]="n|a","",CONCATENATE("Grade Level: ",Table13[[#This Row],[Grade Level]]," - ")),IF(Table13[[#This Row],[Delivery Receipt Number]]="n|a","",CONCATENATE("DR No: ",Table13[[#This Row],[Delivery Receipt Number]]," - ")),IF(Table13[[#This Row],[Contract Number]]="n|a","",CONCATENATE("CN: ",Table13[[#This Row],[Contract Number]]," - ")),IF(Table13[[#This Row],[PTR Number]]="n|a","",CONCATENATE("PTR No: ",Table13[[#This Row],[PTR Number]]," - ")),IF(Table13[[#This Row],[Origin]]="n|a","",CONCATENATE("Origin: ",Table13[[#This Row],[Origin]]))) -> - Supplier: - Subject: - Quarter: - Grade Level: - DR No: - CN: - PTR No: - Origin:
D3: =CONCATENATE(TEXT(Table13[[#This Row],[Date of Acquisition]],"yyyy")," - ", VLOOKUP(Table13[[#This Row],[Article]],'Data Validation'!$A$2:$B$16,2,FALSE)," - ",TEXT(Table13[[#This Row],[Series Number]],"0000")," - ",TEXT(VLOOKUP(Table13[[#This Row],[Location]],'Data Validation'!$A$20:$B$47,2,FALSE),"00")) -> #N/A | Q3: =Table13[[#This Row],[Unit Value]]*Table13[[#This Row],[Qty | PCount]] -> 0 | R3: =IF(Table13[[#This Row],[Unit Value]]<=4999,"Low-Value Asset","High-Value Asset") -> Low-Value Asset | AB3: =CONCATENATE(Table13[[#This Row],[Title]]," - ",IF(Table13[[#This Row],[Supplier]]="n|a","",CONCATENATE("Supplier: ",Table13[[#This Row],[Supplier]]," - ")),IF(Table13[[#This Row],[Subject]]="n|a","",CONCATENATE("Subject: ",Table13[[#This Row],[Subject]]," - ")),IF(Table13[[#This Row],[Quarter]]="n|a","",CONCATENATE("Quarter: ",Table13[[#This Row],[Quarter]]," - ")),IF(Table13[[#This Row],[Grade Level]]="n|a","",CONCATENATE("Grade Level: ",Table13[[#This Row],[Grade Level]]," - ")),IF(Table13[[#This Row],[Delivery Receipt Number]]="n|a","",CONCATENATE("DR No: ",Table13[[#This Row],[Delivery Receipt Number]]," - ")),IF(Table13[[#This Row],[Contract Number]]="n|a","",CONCATENATE("CN: ",Table13[[#This Row],[Contract Number]]," - ")),IF(Table13[[#This Row],[PTR Number]]="n|a","",CONCATENATE("PTR No: ",Table13[[#This Row],[PTR Number]]," - ")),IF(Table13[[#This Row],[Origin]]="n|a","",CONCATENATE("Origin: ",Table13[[#This Row],[Origin]]))) -> - Supplier: - Subject: - Quarter: - Grade Level: - DR No: - CN: - PTR No: - Origin:
D4: =CONCATENATE(TEXT(Table13[[#This Row],[Date of Acquisition]],"yyyy")," - ", VLOOKUP(Table13[[#This Row],[Article]],'Data Validation'!$A$2:$B$16,2,FALSE)," - ",TEXT(Table13[[#This Row],[Series Number]],"0000")," - ",TEXT(VLOOKUP(Table13[[#This Row],[Location]],'Data Validation'!$A$20:$B$47,2,FALSE),"00")) -> #N/A | Q4: =Table13[[#This Row],[Unit Value]]*Table13[[#This Row],[Qty | PCount]] -> 0 | R4: =IF(Table13[[#This Row],[Unit Value]]<=4999,"Low-Value Asset","High-Value Asset") -> Low-Value Asset | AB4: =CONCATENATE(Table13[[#This Row],[Title]]," - ",IF(Table13[[#This Row],[Supplier]]="n|a","",CONCATENATE("Supplier: ",Table13[[#This Row],[Supplier]]," - ")),IF(Table13[[#This Row],[Subject]]="n|a","",CONCATENATE("Subject: ",Table13[[#This Row],[Subject]]," - ")),IF(Table13[[#This Row],[Quarter]]="n|a","",CONCATENATE("Quarter: ",Table13[[#This Row],[Quarter]]," - ")),IF(Table13[[#This Row],[Grade Level]]="n|a","",CONCATENATE("Grade Level: ",Table13[[#This Row],[Grade Level]]," - ")),IF(Table13[[#This Row],[Delivery Receipt Number]]="n|a","",CONCATENATE("DR No: ",Table13[[#This Row],[Delivery Receipt Number]]," - ")),IF(Table13[[#This Row],[Contract Number]]="n|a","",CONCATENATE("CN: ",Table13[[#This Row],[Contract Number]]," - ")),IF(Table13[[#This Row],[PTR Number]]="n|a","",CONCATENATE("PTR No: ",Table13[[#This Row],[PTR Number]]," - ")),IF(Table13[[#This Row],[Origin]]="n|a","",CONCATENATE("Origin: ",Table13[[#This Row],[Origin]]))) -> - Supplier: - Subject: - Quarter: - Grade Level: - DR No: - CN: - PTR No: - Origin:
D5: =CONCATENATE(TEXT(Table13[[#This Row],[Date of Acquisition]],"yyyy")," - ", VLOOKUP(Table13[[#This Row],[Article]],'Data Validation'!$A$2:$B$16,2,FALSE)," - ",TEXT(Table13[[#This Row],[Series Number]],"0000")," - ",TEXT(VLOOKUP(Table13[[#This Row],[Location]],'Data Validation'!$A$20:$B$47,2,FALSE),"00")) -> #N/A | Q5: =Table13[[#This Row],[Unit Value]]*Table13[[#This Row],[Qty | PCount]] -> 0 | R5: =IF(Table13[[#This Row],[Unit Value]]<=4999,"Low-Value Asset","High-Value Asset") -> Low-Value Asset | AB5: =CONCATENATE(Table13[[#This Row],[Title]]," - ",IF(Table13[[#This Row],[Supplier]]="n|a","",CONCATENATE("Supplier: ",Table13[[#This Row],[Supplier]]," - ")),IF(Table13[[#This Row],[Subject]]="n|a","",CONCATENATE("Subject: ",Table13[[#This Row],[Subject]]," - ")),IF(Table13[[#This Row],[Quarter]]="n|a","",CONCATENATE("Quarter: ",Table13[[#This Row],[Quarter]]," - ")),IF(Table13[[#This Row],[Grade Level]]="n|a","",CONCATENATE("Grade Level: ",Table13[[#This Row],[Grade Level]]," - ")),IF(Table13[[#This Row],[Delivery Receipt Number]]="n|a","",CONCATENATE("DR No: ",Table13[[#This Row],[Delivery Receipt Number]]," - ")),IF(Table13[[#This Row],[Contract Number]]="n|a","",CONCATENATE("CN: ",Table13[[#This Row],[Contract Number]]," - ")),IF(Table13[[#This Row],[PTR Number]]="n|a","",CONCATENATE("PTR No: ",Table13[[#This Row],[PTR Number]]," - ")),IF(Table13[[#This Row],[Origin]]="n|a","",CONCATENATE("Origin: ",Table13[[#This Row],[Origin]]))) -> - Supplier: - Subject: - Quarter: - Grade Level: - DR No: - CN: - PTR No: - Origin:
D6: =CONCATENATE(TEXT(Table13[[#This Row],[Date of Acquisition]],"yyyy")," - ", VLOOKUP(Table13[[#This Row],[Article]],'Data Validation'!$A$2:$B$16,2,FALSE)," - ",TEXT(Table13[[#This Row],[Series Number]],"0000")," - ",TEXT(VLOOKUP(Table13[[#This Row],[Location]],'Data Validation'!$A$20:$B$47,2,FALSE),"00")) -> #N/A | Q6: =Table13[[#This Row],[Unit Value]]*Table13[[#This Row],[Qty | PCount]] -> 0 | R6: =IF(Table13[[#This Row],[Unit Value]]<=4999,"Low-Value Asset","High-Value Asset") -> Low-Value Asset | AB6: =CONCATENATE(Table13[[#This Row],[Title]]," - ",IF(Table13[[#This Row],[Supplier]]="n|a","",CONCATENATE("Supplier: ",Table13[[#This Row],[Supplier]]," - ")),IF(Table13[[#This Row],[Subject]]="n|a","",CONCATENATE("Subject: ",Table13[[#This Row],[Subject]]," - ")),IF(Table13[[#This Row],[Quarter]]="n|a","",CONCATENATE("Quarter: ",Table13[[#This Row],[Quarter]]," - ")),IF(Table13[[#This Row],[Grade Level]]="n|a","",CONCATENATE("Grade Level: ",Table13[[#This Row],[Grade Level]]," - ")),IF(Table13[[#This Row],[Delivery Receipt Number]]="n|a","",CONCATENATE("DR No: ",Table13[[#This Row],[Delivery Receipt Number]]," - ")),IF(Table13[[#This Row],[Contract Number]]="n|a","",CONCATENATE("CN: ",Table13[[#This Row],[Contract Number]]," - ")),IF(Table13[[#This Row],[PTR Number]]="n|a","",CONCATENATE("PTR No: ",Table13[[#This Row],[PTR Number]]," - ")),IF(Table13[[#This Row],[Origin]]="n|a","",CONCATENATE("Origin: ",Table13[[#This Row],[Origin]]))) -> - Supplier: - Subject: - Quarter: - Grade Level: - DR No: - CN: - PTR No: - Origin:
D7: =CONCATENATE(TEXT(Table13[[#This Row],[Date of Acquisition]],"yyyy")," - ", VLOOKUP(Table13[[#This Row],[Article]],'Data Validation'!$A$2:$B$16,2,FALSE)," - ",TEXT(Table13[[#This Row],[Series Number]],"0000")," - ",TEXT(VLOOKUP(Table13[[#This Row],[Location]],'Data Validation'!$A$20:$B$47,2,FALSE),"00")) -> #N/A | Q7: =Table13[[#This Row],[Unit Value]]*Table13[[#This Row],[Qty | PCount]] -> 0 | R7: =IF(Table13[[#This Row],[Unit Value]]<=4999,"Low-Value Asset","High-Value Asset") -> Low-Value Asset | AB7: =CONCATENATE(Table13[[#This Row],[Title]]," - ",IF(Table13[[#This Row],[Supplier]]="n|a","",CONCATENATE("Supplier: ",Table13[[#This Row],[Supplier]]," - ")),IF(Table13[[#This Row],[Subject]]="n|a","",CONCATENATE("Subject: ",Table13[[#This Row],[Subject]]," - ")),IF(Table13[[#This Row],[Quarter]]="n|a","",CONCATENATE("Quarter: ",Table13[[#This Row],[Quarter]]," - ")),IF(Table13[[#This Row],[Grade Level]]="n|a","",CONCATENATE("Grade Level: ",Table13[[#This Row],[Grade Level]]," - ")),IF(Table13[[#This Row],[Delivery Receipt Number]]="n|a","",CONCATENATE("DR No: ",Table13[[#This Row],[Delivery Receipt Number]]," - ")),IF(Table13[[#This Row],[Contract Number]]="n|a","",CONCATENATE("CN: ",Table13[[#This Row],[Contract Number]]," - ")),IF(Table13[[#This Row],[PTR Number]]="n|a","",CONCATENATE("PTR No: ",Table13[[#This Row],[PTR Number]]," - ")),IF(Table13[[#This Row],[Origin]]="n|a","",CONCATENATE("Origin: ",Table13[[#This Row],[Origin]]))) -> - Supplier: - Subject: - Quarter: - Grade Level: - DR No: - CN: - PTR No: - Origin:
D8: =CONCATENATE(TEXT(Table13[[#This Row],[Date of Acquisition]],"yyyy")," - ", VLOOKUP(Table13[[#This Row],[Article]],'Data Validation'!$A$2:$B$16,2,FALSE)," - ",TEXT(Table13[[#This Row],[Series Number]],"0000")," - ",TEXT(VLOOKUP(Table13[[#This Row],[Location]],'Data Validation'!$A$20:$B$47,2,FALSE),"00")) -> #N/A | Q8: =Table13[[#This Row],[Unit Value]]*Table13[[#This Row],[Qty | PCount]] -> 0 | R8: =IF(Table13[[#This Row],[Unit Value]]<=4999,"Low-Value Asset","High-Value Asset") -> Low-Value Asset | AB8: =CONCATENATE(Table13[[#This Row],[Title]]," - ",IF(Table13[[#This Row],[Supplier]]="n|a","",CONCATENATE("Supplier: ",Table13[[#This Row],[Supplier]]," - ")),IF(Table13[[#This Row],[Subject]]="n|a","",CONCATENATE("Subject: ",Table13[[#This Row],[Subject]]," - ")),IF(Table13[[#This Row],[Quarter]]="n|a","",CONCATENATE("Quarter: ",Table13[[#This Row],[Quarter]]," - ")),IF(Table13[[#This Row],[Grade Level]]="n|a","",CONCATENATE("Grade Level: ",Table13[[#This Row],[Grade Level]]," - ")),IF(Table13[[#This Row],[Delivery Receipt Number]]="n|a","",CONCATENATE("DR No: ",Table13[[#This Row],[Delivery Receipt Number]]," - ")),IF(Table13[[#This Row],[Contract Number]]="n|a","",CONCATENATE("CN: ",Table13[[#This Row],[Contract Number]]," - ")),IF(Table13[[#This Row],[PTR Number]]="n|a","",CONCATENATE("PTR No: ",Table13[[#This Row],[PTR Number]]," - ")),IF(Table13[[#This Row],[Origin]]="n|a","",CONCATENATE("Origin: ",Table13[[#This Row],[Origin]]))) -> - Supplier: - Subject: - Quarter: - Grade Level: - DR No: - CN: - PTR No: - Origin:
D9: =CONCATENATE(TEXT(Table13[[#This Row],[Date of Acquisition]],"yyyy")," - ", VLOOKUP(Table13[[#This Row],[Article]],'Data Validation'!$A$2:$B$16,2,FALSE)," - ",TEXT(Table13[[#This Row],[Series Number]],"0000")," - ",TEXT(VLOOKUP(Table13[[#This Row],[Location]],'Data Validation'!$A$20:$B$47,2,FALSE),"00")) -> #N/A | Q9: =Table13[[#This Row],[Unit Value]]*Table13[[#This Row],[Qty | PCount]] -> 0 | R9: =IF(Table13[[#This Row],[Unit Value]]<=4999,"Low-Value Asset","High-Value Asset") -> Low-Value Asset | AB9: =CONCATENATE(Table13[[#This Row],[Title]]," - ",IF(Table13[[#This Row],[Supplier]]="n|a","",CONCATENATE("Supplier: ",Table13[[#This Row],[Supplier]]," - ")),IF(Table13[[#This Row],[Subject]]="n|a","",CONCATENATE("Subject: ",Table13[[#This Row],[Subject]]," - ")),IF(Table13[[#This Row],[Quarter]]="n|a","",CONCATENATE("Quarter: ",Table13[[#This Row],[Quarter]]," - ")),IF(Table13[[#This Row],[Grade Level]]="n|a","",CONCATENATE("Grade Level: ",Table13[[#This Row],[Grade Level]]," - ")),IF(Table13[[#This Row],[Delivery Receipt Number]]="n|a","",CONCATENATE("DR No: ",Table13[[#This Row],[Delivery Receipt Number]]," - ")),IF(Table13[[#This Row],[Contract Number]]="n|a","",CONCATENATE("CN: ",Table13[[#This Row],[Contract Number]]," - ")),IF(Table13[[#This Row],[PTR Number]]="n|a","",CONCATENATE("PTR No: ",Table13[[#This Row],[PTR Number]]," - ")),IF(Table13[[#This Row],[Origin]]="n|a","",CONCATENATE("Origin: ",Table13[[#This Row],[Origin]]))) -> - Supplier: - Subject: - Quarter: - Grade Level: - DR No: - CN: - PTR No: - Origin:
D10: =CONCATENATE(TEXT(Table13[[#This Row],[Date of Acquisition]],"yyyy")," - ", VLOOKUP(Table13[[#This Row],[Article]],'Data Validation'!$A$2:$B$16,2,FALSE)," - ",TEXT(Table13[[#This Row],[Series Number]],"0000")," - ",TEXT(VLOOKUP(Table13[[#This Row],[Location]],'Data Validation'!$A$20:$B$47,2,FALSE),"00")) -> #N/A | Q10: =Table13[[#This Row],[Unit Value]]*Table13[[#This Row],[Qty | PCount]] -> 0 | R10: =IF(Table13[[#This Row],[Unit Value]]<=4999,"Low-Value Asset","High-Value Asset") -> Low-Value Asset | AB10: =CONCATENATE(Table13[[#This Row],[Title]]," - ",IF(Table13[[#This Row],[Supplier]]="n|a","",CONCATENATE("Supplier: ",Table13[[#This Row],[Supplier]]," - ")),IF(Table13[[#This Row],[Subject]]="n|a","",CONCATENATE("Subject: ",Table13[[#This Row],[Subject]]," - ")),IF(Table13[[#This Row],[Quarter]]="n|a","",CONCATENATE("Quarter: ",Table13[[#This Row],[Quarter]]," - ")),IF(Table13[[#This Row],[Grade Level]]="n|a","",CONCATENATE("Grade Level: ",Table13[[#This Row],[Grade Level]]," - ")),IF(Table13[[#This Row],[Delivery Receipt Number]]="n|a","",CONCATENATE("DR No: ",Table13[[#This Row],[Delivery Receipt Number]]," - ")),IF(Table13[[#This Row],[Contract Number]]="n|a","",CONCATENATE("CN: ",Table13[[#This Row],[Contract Number]]," - ")),IF(Table13[[#This Row],[PTR Number]]="n|a","",CONCATENATE("PTR No: ",Table13[[#This Row],[PTR Number]]," - ")),IF(Table13[[#This Row],[Origin]]="n|a","",CONCATENATE("Origin: ",Table13[[#This Row],[Origin]]))) -> - Supplier: - Subject: - Quarter: - Grade Level: - DR No: - CN: - PTR No: - Origin:
D11: =CONCATENATE(TEXT(Table13[[#This Row],[Date of Acquisition]],"yyyy")," - ", VLOOKUP(Table13[[#This Row],[Article]],'Data Validation'!$A$2:$B$16,2,FALSE)," - ",TEXT(Table13[[#This Row],[Series Number]],"0000")," - ",TEXT(VLOOKUP(Table13[[#This Row],[Location]],'Data Validation'!$A$20:$B$47,2,FALSE),"00")) -> #N/A | Q11: =Table13[[#This Row],[Unit Value]]*Table13[[#This Row],[Qty | PCount]] -> 0 | R11: =IF(Table13[[#This Row],[Unit Value]]<=4999,"Low-Value Asset","High-Value Asset") -> Low-Value Asset | AB11: =CONCATENATE(Table13[[#This Row],[Title]]," - ",IF(Table13[[#This Row],[Supplier]]="n|a","",CONCATENATE("Supplier: ",Table13[[#This Row],[Supplier]]," - ")),IF(Table13[[#This Row],[Subject]]="n|a","",CONCATENATE("Subject: ",Table13[[#This Row],[Subject]]," - ")),IF(Table13[[#This Row],[Quarter]]="n|a","",CONCATENATE("Quarter: ",Table13[[#This Row],[Quarter]]," - ")),IF(Table13[[#This Row],[Grade Level]]="n|a","",CONCATENATE("Grade Level: ",Table13[[#This Row],[Grade Level]]," - ")),IF(Table13[[#This Row],[Delivery Receipt Number]]="n|a","",CONCATENATE("DR No: ",Table13[[#This Row],[Delivery Receipt Number]]," - ")),IF(Table13[[#This Row],[Contract Number]]="n|a","",CONCATENATE("CN: ",Table13[[#This Row],[Contract Number]]," - ")),IF(Table13[[#This Row],[PTR Number]]="n|a","",CONCATENATE("PTR No: ",Table13[[#This Row],[PTR Number]]," - ")),IF(Table13[[#This Row],[Origin]]="n|a","",CONCATENATE("Origin: ",Table13[[#This Row],[Origin]]))) -> - Supplier: - Subject: - Quarter: - Grade Level: - DR No: - CN: - PTR No: - Origin:
D12: =CONCATENATE(TEXT(Table13[[#This Row],[Date of Acquisition]],"yyyy")," - ", VLOOKUP(Table13[[#This Row],[Article]],'Data Validation'!$A$2:$B$16,2,FALSE)," - ",TEXT(Table13[[#This Row],[Series Number]],"0000")," - ",TEXT(VLOOKUP(Table13[[#This Row],[Location]],'Data Validation'!$A$20:$B$47,2,FALSE),"00")) -> #N/A | Q12: =Table13[[#This Row],[Unit Value]]*Table13[[#This Row],[Qty | PCount]] -> 0 | R12: =IF(Table13[[#This Row],[Unit Value]]<=4999,"Low-Value Asset","High-Value Asset") -> Low-Value Asset | AB12: =CONCATENATE(Table13[[#This Row],[Title]]," - ",IF(Table13[[#This Row],[Supplier]]="n|a","",CONCATENATE("Supplier: ",Table13[[#This Row],[Supplier]]," - ")),IF(Table13[[#This Row],[Subject]]="n|a","",CONCATENATE("Subject: ",Table13[[#This Row],[Subject]]," - ")),IF(Table13[[#This Row],[Quarter]]="n|a","",CONCATENATE("Quarter: ",Table13[[#This Row],[Quarter]]," - ")),IF(Table13[[#This Row],[Grade Level]]="n|a","",CONCATENATE("Grade Level: ",Table13[[#This Row],[Grade Level]]," - ")),IF(Table13[[#This Row],[Delivery Receipt Number]]="n|a","",CONCATENATE("DR No: ",Table13[[#This Row],[Delivery Receipt Number]]," - ")),IF(Table13[[#This Row],[Contract Number]]="n|a","",CONCATENATE("CN: ",Table13[[#This Row],[Contract Number]]," - ")),IF(Table13[[#This Row],[PTR Number]]="n|a","",CONCATENATE("PTR No: ",Table13[[#This Row],[PTR Number]]," - ")),IF(Table13[[#This Row],[Origin]]="n|a","",CONCATENATE("Origin: ",Table13[[#This Row],[Origin]]))) -> - Supplier: - Subject: - Quarter: - Grade Level: - DR No: - CN: - PTR No: - Origin:
D13: =CONCATENATE(TEXT(Table13[[#This Row],[Date of Acquisition]],"yyyy")," - ", VLOOKUP(Table13[[#This Row],[Article]],'Data Validation'!$A$2:$B$16,2,FALSE)," - ",TEXT(Table13[[#This Row],[Series Number]],"0000")," - ",TEXT(VLOOKUP(Table13[[#This Row],[Location]],'Data Validation'!$A$20:$B$47,2,FALSE),"00")) -> #N/A | Q13: =Table13[[#This Row],[Unit Value]]*Table13[[#This Row],[Qty | PCount]] -> 0 | R13: =IF(Table13[[#This Row],[Unit Value]]<=4999,"Low-Value Asset","High-Value Asset") -> Low-Value Asset | AB13: =CONCATENATE(Table13[[#This Row],[Title]]," - ",IF(Table13[[#This Row],[Supplier]]="n|a","",CONCATENATE("Supplier: ",Table13[[#This Row],[Supplier]]," - ")),IF(Table13[[#This Row],[Subject]]="n|a","",CONCATENATE("Subject: ",Table13[[#This Row],[Subject]]," - ")),IF(Table13[[#This Row],[Quarter]]="n|a","",CONCATENATE("Quarter: ",Table13[[#This Row],[Quarter]]," - ")),IF(Table13[[#This Row],[Grade Level]]="n|a","",CONCATENATE("Grade Level: ",Table13[[#This Row],[Grade Level]]," - ")),IF(Table13[[#This Row],[Delivery Receipt Number]]="n|a","",CONCATENATE("DR No: ",Table13[[#This Row],[Delivery Receipt Number]]," - ")),IF(Table13[[#This Row],[Contract Number]]="n|a","",CONCATENATE("CN: ",Table13[[#This Row],[Contract Number]]," - ")),IF(Table13[[#This Row],[PTR Number]]="n|a","",CONCATENATE("PTR No: ",Table13[[#This Row],[PTR Number]]," - ")),IF(Table13[[#This Row],[Origin]]="n|a","",CONCATENATE("Origin: ",Table13[[#This Row],[Origin]]))) -> - Supplier: - Subject: - Quarter: - Grade Level: - DR No: - CN: - PTR No: - Origin:
... D2090: =CONCATENATE(TEXT(Table13[[#This Row],[Date of Acquisition]],"yyyy")," - ", VLOOKUP(Table13[[#This Row],[Article]],'Data Validation'!$A$2:$B$16,2,FALSE)," - ",TEXT(Table13[[#This Row],[Series Number]],"0000")," - ",TEXT(VLOOKUP(Table13[[#This Row],[Location]],'Data Validation'!$A$20:$B$47,2,FALSE),"00")) -> #N/A | Q2090: =Table13[[#This Row],[Unit Value]]*Table13[[#This Row],[Qty | PCount]] -> 0 | R2090: =IF(Table13[[#This Row],[Unit Value]]<=4999,"Low-Value Asset","High-Value Asset") -> Low-Value Asset | AB2090: =CONCATENATE(Table13[[#This Row],[Title]]," - ",IF(Table13[[#This Row],[Supplier]]="n|a","",CONCATENATE("Supplier: ",Table13[[#This Row],[Supplier]]," - ")),IF(Table13[[#This Row],[Subject]]="n|a","",CONCATENATE("Subject: ",Table13[[#This Row],[Subject]]," - ")),IF(Table13[[#This Row],[Quarter]]="n|a","",CONCATENATE("Quarter: ",Table13[[#This Row],[Quarter]]," - ")),IF(Table13[[#This Row],[Grade Level]]="n|a","",CONCATENATE("Grade Level: ",Table13[[#This Row],[Grade Level]]," - ")),IF(Table13[[#This Row],[Delivery Receipt Number]]="n|a","",CONCATENATE("DR No: ",Table13[[#This Row],[Delivery Receipt Number]]," - ")),IF(Table13[[#This Row],[Contract Number]]="n|a","",CONCATENATE("CN: ",Table13[[#This Row],[Contract Number]]," - ")),IF(Table13[[#This Row],[PTR Number]]="n|a","",CONCATENATE("PTR No: ",Table13[[#This Row],[PTR Number]]," - ")),IF(Table13[[#This Row],[Origin]]="n|a","",CONCATENATE("Origin: ",Table13[[#This Row],[Origin]]))) -> - Supplier: - Subject: - Quarter: - Grade Level: - DR No: - CN: - PTR No: - Origin:
D2091: 2023 - 07 - 00 - 0818 - 18 | Q2091: 1560 | R2091: Low-Value Asset | AB2091: =CONCATENATE(Table13[[#This Row],[Title]]," - ",IF(Table13[[#This Row],[Supplier]]="n|a","",CONCATENATE("Supplier: ",Table13[[#This Row],[Supplier]]," - ")),IF(Table13[[#This Row],[Subject]]="n|a","",CONCATENATE("Subject: ",Table13[[#This Row],[Subject]]," - ")),IF(Table13[[#This Row],[Quarter]]="n|a","",CONCATENATE("Quarter: ",Table13[[#This Row],[Quarter]]," - ")),IF(Table13[[#This Row],[Grade Level]]="n|a","",CONCATENATE("Grade Level: ",Table13[[#This Row],[Grade Level]]," - ")),IF(Table13[[#This Row],[Delivery Receipt Number]]="n|a","",CONCATENATE("DR No: ",Table13[[#This Row],[Delivery Receipt Number]]," - ")),IF(Table13[[#This Row],[Contract Number]]="n|a","",CONCATENATE("CN: ",Table13[[#This Row],[Contract Number]]," - ")),IF(Table13[[#This Row],[PTR Number]]="n|a","",CONCATENATE("PTR No: ",Table13[[#This Row],[PTR Number]]," - ")),IF(Table13[[#This Row],[Origin]]="n|a","",CONCATENATE("Origin: ",Table13[[#This Row],[Origin]]))) -> - Supplier: - Subject: - Quarter: - Grade Level: - DR No: - CN: - PTR No: - Origin:
D2092: 2023 - 07 - 00 - 0819 - 18 | Q2092: 1430 | R2092: Low-Value Asset | AB2092: =CONCATENATE(Table13[[#This Row],[Title]]," - ",IF(Table13[[#This Row],[Supplier]]="n|a","",CONCATENATE("Supplier: ",Table13[[#This Row],[Supplier]]," - ")),IF(Table13[[#This Row],[Subject]]="n|a","",CONCATENATE("Subject: ",Table13[[#This Row],[Subject]]," - ")),IF(Table13[[#This Row],[Quarter]]="n|a","",CONCATENATE("Quarter: ",Table13[[#This Row],[Quarter]]," - ")),IF(Table13[[#This Row],[Grade Level]]="n|a","",CONCATENATE("Grade Level: ",Table13[[#This Row],[Grade Level]]," - ")),IF(Table13[[#This Row],[Delivery Receipt Number]]="n|a","",CONCATENATE("DR No: ",Table13[[#This Row],[Delivery Receipt Number]]," - ")),IF(Table13[[#This Row],[Contract Number]]="n|a","",CONCATENATE("CN: ",Table13[[#This Row],[Contract Number]]," - ")),IF(Table13[[#This Row],[PTR Number]]="n|a","",CONCATENATE("PTR No: ",Table13[[#This Row],[PTR Number]]," - ")),IF(Table13[[#This Row],[Origin]]="n|a","",CONCATENATE("Origin: ",Table13[[#This Row],[Origin]]))) -> - Supplier: - Subject: - Quarter: - Grade Level: - DR No: - CN: - PTR No: - Origin:
D2093: 2023 - 07 - 00 - 0829 - 18 | Q2093: 1430 | R2093: Low-Value Asset | AB2093: =CONCATENATE(Table13[[#This Row],[Title]]," - ",IF(Table13[[#This Row],[Supplier]]="n|a","",CONCATENATE("Supplier: ",Table13[[#This Row],[Supplier]]," - ")),IF(Table13[[#This Row],[Subject]]="n|a","",CONCATENATE("Subject: ",Table13[[#This Row],[Subject]]," - ")),IF(Table13[[#This Row],[Quarter]]="n|a","",CONCATENATE("Quarter: ",Table13[[#This Row],[Quarter]]," - ")),IF(Table13[[#This Row],[Grade Level]]="n|a","",CONCATENATE("Grade Level: ",Table13[[#This Row],[Grade Level]]," - ")),IF(Table13[[#This Row],[Delivery Receipt Number]]="n|a","",CONCATENATE("DR No: ",Table13[[#This Row],[Delivery Receipt Number]]," - ")),IF(Table13[[#This Row],[Contract Number]]="n|a","",CONCATENATE("CN: ",Table13[[#This Row],[Contract Number]]," - ")),IF(Table13[[#This Row],[PTR Number]]="n|a","",CONCATENATE("PTR No: ",Table13[[#This Row],[PTR Number]]," - ")),IF(Table13[[#This Row],[Origin]]="n|a","",CONCATENATE("Origin: ",Table13[[#This Row],[Origin]]))) -> - Supplier: - Subject: - Quarter: - Grade Level: - DR No: - CN: - PTR No: - Origin:
D2094: 2023 - 07 - 00 - 0830 - 18 | Q2094: 1495 | R2094: Low-Value Asset | AB2094: =CONCATENATE(Table13[[#This Row],[Title]]," - ",IF(Table13[[#This Row],[Supplier]]="n|a","",CONCATENATE("Supplier: ",Table13[[#This Row],[Supplier]]," - ")),IF(Table13[[#This Row],[Subject]]="n|a","",CONCATENATE("Subject: ",Table13[[#This Row],[Subject]]," - ")),IF(Table13[[#This Row],[Quarter]]="n|a","",CONCATENATE("Quarter: ",Table13[[#This Row],[Quarter]]," - ")),IF(Table13[[#This Row],[Grade Level]]="n|a","",CONCATENATE("Grade Level: ",Table13[[#This Row],[Grade Level]]," - ")),IF(Table13[[#This Row],[Delivery Receipt Number]]="n|a","",CONCATENATE("DR No: ",Table13[[#This Row],[Delivery Receipt Number]]," - ")),IF(Table13[[#This Row],[Contract Number]]="n|a","",CONCATENATE("CN: ",Table13[[#This Row],[Contract Number]]," - ")),IF(Table13[[#This Row],[PTR Number]]="n|a","",CONCATENATE("PTR No: ",Table13[[#This Row],[PTR Number]]," - ")),IF(Table13[[#This Row],[Origin]]="n|a","",CONCATENATE("Origin: ",Table13[[#This Row],[Origin]]))) -> - Supplier: - Subject: - Quarter: - Grade Level: - DR No: - CN: - PTR No: - Origin:
D2095: 2023 - 07 - 00 - 0831 - 18 | Q2095: 1560 | R2095: Low-Value Asset | AB2095: =CONCATENATE(Table13[[#This Row],[Title]]," - ",IF(Table13[[#This Row],[Supplier]]="n|a","",CONCATENATE("Supplier: ",Table13[[#This Row],[Supplier]]," - ")),IF(Table13[[#This Row],[Subject]]="n|a","",CONCATENATE("Subject: ",Table13[[#This Row],[Subject]]," - ")),IF(Table13[[#This Row],[Quarter]]="n|a","",CONCATENATE("Quarter: ",Table13[[#This Row],[Quarter]]," - ")),IF(Table13[[#This Row],[Grade Level]]="n|a","",CONCATENATE("Grade Level: ",Table13[[#This Row],[Grade Level]]," - ")),IF(Table13[[#This Row],[Delivery Receipt Number]]="n|a","",CONCATENATE("DR No: ",Table13[[#This Row],[Delivery Receipt Number]]," - ")),IF(Table13[[#This Row],[Contract Number]]="n|a","",CONCATENATE("CN: ",Table13[[#This Row],[Contract Number]]," - ")),IF(Table13[[#This Row],[PTR Number]]="n|a","",CONCATENATE("PTR No: ",Table13[[#This Row],[PTR Number]]," - ")),IF(Table13[[#This Row],[Origin]]="n|a","",CONCATENATE("Origin: ",Table13[[#This Row],[Origin]]))) -> - Supplier: - Subject: - Quarter: - Grade Level: - DR No: - CN: - PTR No: - Origin:
D2096: 2023 - 07 - 00 - 0832 - 18 | Q2096: 1430 | R2096: Low-Value Asset | AB2096: =CONCATENATE(Table13[[#This Row],[Title]]," - ",IF(Table13[[#This Row],[Supplier]]="n|a","",CONCATENATE("Supplier: ",Table13[[#This Row],[Supplier]]," - ")),IF(Table13[[#This Row],[Subject]]="n|a","",CONCATENATE("Subject: ",Table13[[#This Row],[Subject]]," - ")),IF(Table13[[#This Row],[Quarter]]="n|a","",CONCATENATE("Quarter: ",Table13[[#This Row],[Quarter]]," - ")),IF(Table13[[#This Row],[Grade Level]]="n|a","",CONCATENATE("Grade Level: ",Table13[[#This Row],[Grade Level]]," - ")),IF(Table13[[#This Row],[Delivery Receipt Number]]="n|a","",CONCATENATE("DR No: ",Table13[[#This Row],[Delivery Receipt Number]]," - ")),IF(Table13[[#This Row],[Contract Number]]="n|a","",CONCATENATE("CN: ",Table13[[#This Row],[Contract Number]]," - ")),IF(Table13[[#This Row],[PTR Number]]="n|a","",CONCATENATE("PTR No: ",Table13[[#This Row],[PTR Number]]," - ")),IF(Table13[[#This Row],[Origin]]="n|a","",CONCATENATE("Origin: ",Table13[[#This Row],[Origin]]))) -> - Supplier: - Subject: - Quarter: - Grade Level: - DR No: - CN: - PTR No: - Origin:
D2097: 2023 - 07 - 00 - 0833 - 18 | Q2097: 1495 | R2097: Low-Value Asset | AB2097: =CONCATENATE(Table13[[#This Row],[Title]]," - ",IF(Table13[[#This Row],[Supplier]]="n|a","",CONCATENATE("Supplier: ",Table13[[#This Row],[Supplier]]," - ")),IF(Table13[[#This Row],[Subject]]="n|a","",CONCATENATE("Subject: ",Table13[[#This Row],[Subject]]," - ")),IF(Table13[[#This Row],[Quarter]]="n|a","",CONCATENATE("Quarter: ",Table13[[#This Row],[Quarter]]," - ")),IF(Table13[[#This Row],[Grade Level]]="n|a","",CONCATENATE("Grade Level: ",Table13[[#This Row],[Grade Level]]," - ")),IF(Table13[[#This Row],[Delivery Receipt Number]]="n|a","",CONCATENATE("DR No: ",Table13[[#This Row],[Delivery Receipt Number]]," - ")),IF(Table13[[#This Row],[Contract Number]]="n|a","",CONCATENATE("CN: ",Table13[[#This Row],[Contract Number]]," - ")),IF(Table13[[#This Row],[PTR Number]]="n|a","",CONCATENATE("PTR No: ",Table13[[#This Row],[PTR Number]]," - ")),IF(Table13[[#This Row],[Origin]]="n|a","",CONCATENATE("Origin: ",Table13[[#This Row],[Origin]]))) -> - Supplier: - Subject: - Quarter: - Grade Level: - DR No: - CN: - PTR No: - Origin:
D2098: 2023 - 07 - 00 - 0834 - 18 | Q2098: 1365 | R2098: Low-Value Asset | AB2098: =CONCATENATE(Table13[[#This Row],[Title]]," - ",IF(Table13[[#This Row],[Supplier]]="n|a","",CONCATENATE("Supplier: ",Table13[[#This Row],[Supplier]]," - ")),IF(Table13[[#This Row],[Subject]]="n|a","",CONCATENATE("Subject: ",Table13[[#This Row],[Subject]]," - ")),IF(Table13[[#This Row],[Quarter]]="n|a","",CONCATENATE("Quarter: ",Table13[[#This Row],[Quarter]]," - ")),IF(Table13[[#This Row],[Grade Level]]="n|a","",CONCATENATE("Grade Level: ",Table13[[#This Row],[Grade Level]]," - ")),IF(Table13[[#This Row],[Delivery Receipt Number]]="n|a","",CONCATENATE("DR No: ",Table13[[#This Row],[Delivery Receipt Number]]," - ")),IF(Table13[[#This Row],[Contract Number]]="n|a","",CONCATENATE("CN: ",Table13[[#This Row],[Contract Number]]," - ")),IF(Table13[[#This Row],[PTR Number]]="n|a","",CONCATENATE("PTR No: ",Table13[[#This Row],[PTR Number]]," - ")),IF(Table13[[#This Row],[Origin]]="n|a","",CONCATENATE("Origin: ",Table13[[#This Row],[Origin]]))) -> - Supplier: - Subject: - Quarter: - Grade Level: - DR No: - CN: - PTR No: - Origin:
D2099: 2023 - 07 - 00 - 0835 - 18 | Q2099: 1365 | R2099: Low-Value Asset | AB2099: =CONCATENATE(Table13[[#This Row],[Title]]," - ",IF(Table13[[#This Row],[Supplier]]="n|a","",CONCATENATE("Supplier: ",Table13[[#This Row],[Supplier]]," - ")),IF(Table13[[#This Row],[Subject]]="n|a","",CONCATENATE("Subject: ",Table13[[#This Row],[Subject]]," - ")),IF(Table13[[#This Row],[Quarter]]="n|a","",CONCATENATE("Quarter: ",Table13[[#This Row],[Quarter]]," - ")),IF(Table13[[#This Row],[Grade Level]]="n|a","",CONCATENATE("Grade Level: ",Table13[[#This Row],[Grade Level]]," - ")),IF(Table13[[#This Row],[Delivery Receipt Number]]="n|a","",CONCATENATE("DR No: ",Table13[[#This Row],[Delivery Receipt Number]]," - ")),IF(Table13[[#This Row],[Contract Number]]="n|a","",CONCATENATE("CN: ",Table13[[#This Row],[Contract Number]]," - ")),IF(Table13[[#This Row],[PTR Number]]="n|a","",CONCATENATE("PTR No: ",Table13[[#This Row],[PTR Number]]," - ")),IF(Table13[[#This Row],[Origin]]="n|a","",CONCATENATE("Origin: ",Table13[[#This Row],[Origin]]))) -> - Supplier: - Subject: - Quarter: - Grade Level: - DR No: - CN: - PTR No: - Origin:
D2100: 2023 - 07 - 00 - 0836 - 18 | Q2100: 1495 | R2100: Low-Value Asset | AB2100: =CONCATENATE(Table13[[#This Row],[Title]]," - ",IF(Table13[[#This Row],[Supplier]]="n|a","",CONCATENATE("Supplier: ",Table13[[#This Row],[Supplier]]," - ")),IF(Table13[[#This Row],[Subject]]="n|a","",CONCATENATE("Subject: ",Table13[[#This Row],[Subject]]," - ")),IF(Table13[[#This Row],[Quarter]]="n|a","",CONCATENATE("Quarter: ",Table13[[#This Row],[Quarter]]," - ")),IF(Table13[[#This Row],[Grade Level]]="n|a","",CONCATENATE("Grade Level: ",Table13[[#This Row],[Grade Level]]," - ")),IF(Table13[[#This Row],[Delivery Receipt Number]]="n|a","",CONCATENATE("DR No: ",Table13[[#This Row],[Delivery Receipt Number]]," - ")),IF(Table13[[#This Row],[Contract Number]]="n|a","",CONCATENATE("CN: ",Table13[[#This Row],[Contract Number]]," - ")),IF(Table13[[#This Row],[PTR Number]]="n|a","",CONCATENATE("PTR No: ",Table13[[#This Row],[PTR Number]]," - ")),IF(Table13[[#This Row],[Origin]]="n|a","",CONCATENATE("Origin: ",Table13[[#This Row],[Origin]]))) -> - Supplier: - Subject: - Quarter: - Grade Level: - DR No: - CN: - PTR No: - Origin:
D2101: 2023 - 07 - 00 - 0837 - 18 | Q2101: 1625 | R2101: Low-Value Asset | AB2101: =CONCATENATE(Table13[[#This Row],[Title]]," - ",IF(Table13[[#This Row],[Supplier]]="n|a","",CONCATENATE("Supplier: ",Table13[[#This Row],[Supplier]]," - ")),IF(Table13[[#This Row],[Subject]]="n|a","",CONCATENATE("Subject: ",Table13[[#This Row],[Subject]]," - ")),IF(Table13[[#This Row],[Quarter]]="n|a","",CONCATENATE("Quarter: ",Table13[[#This Row],[Quarter]]," - ")),IF(Table13[[#This Row],[Grade Level]]="n|a","",CONCATENATE("Grade Level: ",Table13[[#This Row],[Grade Level]]," - ")),IF(Table13[[#This Row],[Delivery Receipt Number]]="n|a","",CONCATENATE("DR No: ",Table13[[#This Row],[Delivery Receipt Number]]," - ")),IF(Table13[[#This Row],[Contract Number]]="n|a","",CONCATENATE("CN: ",Table13[[#This Row],[Contract Number]]," - ")),IF(Table13[[#This Row],[PTR Number]]="n|a","",CONCATENATE("PTR No: ",Table13[[#This Row],[PTR Number]]," - ")),IF(Table13[[#This Row],[Origin]]="n|a","",CONCATENATE("Origin: ",Table13[[#This Row],[Origin]]))) -> - Supplier: - Subject: - Quarter: - Grade Level: - DR No: - CN: - PTR No: - Origin:
D2102: 2023 - 07 - 00 - 0838 - 18 | Q2102: 1430 | R2102: Low-Value Asset | AB2102: =CONCATENATE(Table13[[#This Row],[Title]]," - ",IF(Table13[[#This Row],[Supplier]]="n|a","",CONCATENATE("Supplier: ",Table13[[#This Row],[Supplier]]," - ")),IF(Table13[[#This Row],[Subject]]="n|a","",CONCATENATE("Subject: ",Table13[[#This Row],[Subject]]," - ")),IF(Table13[[#This Row],[Quarter]]="n|a","",CONCATENATE("Quarter: ",Table13[[#This Row],[Quarter]]," - ")),IF(Table13[[#This Row],[Grade Level]]="n|a","",CONCATENATE("Grade Level: ",Table13[[#This Row],[Grade Level]]," - ")),IF(Table13[[#This Row],[Delivery Receipt Number]]="n|a","",CONCATENATE("DR No: ",Table13[[#This Row],[Delivery Receipt Number]]," - ")),IF(Table13[[#This Row],[Contract Number]]="n|a","",CONCATENATE("CN: ",Table13[[#This Row],[Contract Number]]," - ")),IF(Table13[[#This Row],[PTR Number]]="n|a","",CONCATENATE("PTR No: ",Table13[[#This Row],[PTR Number]]," - ")),IF(Table13[[#This Row],[Origin]]="n|a","",CONCATENATE("Origin: ",Table13[[#This Row],[Origin]]))) -> - Supplier: - Subject: - Quarter: - Grade Level: - DR No: - CN: - PTR No: - Origin:
... D2107: 2023 - 07 - 00 - 0843 - 18 | Q2107: 1755 | R2107: Low-Value Asset | AB2107: =CONCATENATE(Table13[[#This Row],[Title]]," - ",IF(Table13[[#This Row],[Supplier]]="n|a","",CONCATENATE("Supplier: ",Table13[[#This Row],[Supplier]]," - ")),IF(Table13[[#This Row],[Subject]]="n|a","",CONCATENATE("Subject: ",Table13[[#This Row],[Subject]]," - ")),IF(Table13[[#This Row],[Quarter]]="n|a","",CONCATENATE("Quarter: ",Table13[[#This Row],[Quarter]]," - ")),IF(Table13[[#This Row],[Grade Level]]="n|a","",CONCATENATE("Grade Level: ",Table13[[#This Row],[Grade Level]]," - ")),IF(Table13[[#This Row],[Delivery Receipt Number]]="n|a","",CONCATENATE("DR No: ",Table13[[#This Row],[Delivery Receipt Number]]," - ")),IF(Table13[[#This Row],[Contract Number]]="n|a","",CONCATENATE("CN: ",Table13[[#This Row],[Contract Number]]," - ")),IF(Table13[[#This Row],[PTR Number]]="n|a","",CONCATENATE("PTR No: ",Table13[[#This Row],[PTR Number]]," - ")),IF(Table13[[#This Row],[Origin]]="n|a","",CONCATENATE("Origin: ",Table13[[#This Row],[Origin]]))) -> - Supplier: - Subject: - Quarter: - Grade Level: - DR No: - CN: - PTR No: - Origin:
D2108: =CONCATENATE(TEXT(Table13[[#This Row],[Date of Acquisition]],"yyyy")," - ", VLOOKUP(Table13[[#This Row],[Article]],'Data Validation'!$A$2:$B$16,2,FALSE)," - ",TEXT(Table13[[#This Row],[Series Number]],"0000")," - ",TEXT(VLOOKUP(Table13[[#This Row],[Location]],'Data Validation'!$A$20:$B$47,2,FALSE),"00")) -> #N/A | Q2108: =Table13[[#This Row],[Unit Value]]*Table13[[#This Row],[Qty | PCount]] -> 0 | R2108: =IF(Table13[[#This Row],[Unit Value]]<=4999,"Low-Value Asset","High-Value Asset") -> Low-Value Asset | AB2108: =CONCATENATE(Table13[[#This Row],[Title]]," - ",IF(Table13[[#This Row],[Supplier]]="n|a","",CONCATENATE("Supplier: ",Table13[[#This Row],[Supplier]]," - ")),IF(Table13[[#This Row],[Subject]]="n|a","",CONCATENATE("Subject: ",Table13[[#This Row],[Subject]]," - ")),IF(Table13[[#This Row],[Quarter]]="n|a","",CONCATENATE("Quarter: ",Table13[[#This Row],[Quarter]]," - ")),IF(Table13[[#This Row],[Grade Level]]="n|a","",CONCATENATE("Grade Level: ",Table13[[#This Row],[Grade Level]]," - ")),IF(Table13[[#This Row],[Delivery Receipt Number]]="n|a","",CONCATENATE("DR No: ",Table13[[#This Row],[Delivery Receipt Number]]," - ")),IF(Table13[[#This Row],[Contract Number]]="n|a","",CONCATENATE("CN: ",Table13[[#This Row],[Contract Number]]," - ")),IF(Table13[[#This Row],[PTR Number]]="n|a","",CONCATENATE("PTR No: ",Table13[[#This Row],[PTR Number]]," - ")),IF(Table13[[#This Row],[Origin]]="n|a","",CONCATENATE("Origin: ",Table13[[#This Row],[Origin]]))) -> - Supplier: - Subject: - Quarter: - Grade Level: - DR No: - CN: - PTR No: - Origin:
D2109: =CONCATENATE(TEXT(Table13[[#This Row],[Date of Acquisition]],"yyyy")," - ", VLOOKUP(Table13[[#This Row],[Article]],'Data Validation'!$A$2:$B$16,2,FALSE)," - ",TEXT(Table13[[#This Row],[Series Number]],"0000")," - ",TEXT(VLOOKUP(Table13[[#This Row],[Location]],'Data Validation'!$A$20:$B$47,2,FALSE),"00")) -> #N/A | Q2109: =Table13[[#This Row],[Unit Value]]*Table13[[#This Row],[Qty | PCount]] -> 0 | R2109: =IF(Table13[[#This Row],[Unit Value]]<=4999,"Low-Value Asset","High-Value Asset") -> Low-Value Asset | AB2109: =CONCATENATE(Table13[[#This Row],[Title]]," - ",IF(Table13[[#This Row],[Supplier]]="n|a","",CONCATENATE("Supplier: ",Table13[[#This Row],[Supplier]]," - ")),IF(Table13[[#This Row],[Subject]]="n|a","",CONCATENATE("Subject: ",Table13[[#This Row],[Subject]]," - ")),IF(Table13[[#This Row],[Quarter]]="n|a","",CONCATENATE("Quarter: ",Table13[[#This Row],[Quarter]]," - ")),IF(Table13[[#This Row],[Grade Level]]="n|a","",CONCATENATE("Grade Level: ",Table13[[#This Row],[Grade Level]]," - ")),IF(Table13[[#This Row],[Delivery Receipt Number]]="n|a","",CONCATENATE("DR No: ",Table13[[#This Row],[Delivery Receipt Number]]," - ")),IF(Table13[[#This Row],[Contract Number]]="n|a","",CONCATENATE("CN: ",Table13[[#This Row],[Contract Number]]," - ")),IF(Table13[[#This Row],[PTR Number]]="n|a","",CONCATENATE("PTR No: ",Table13[[#This Row],[PTR Number]]," - ")),IF(Table13[[#This Row],[Origin]]="n|a","",CONCATENATE("Origin: ",Table13[[#This Row],[Origin]]))) -> - Supplier: - Subject: - Quarter: - Grade Level: - DR No: - CN: - PTR No: - Origin:
D2110: =CONCATENATE(TEXT(Table13[[#This Row],[Date of Acquisition]],"yyyy")," - ", VLOOKUP(Table13[[#This Row],[Article]],'Data Validation'!$A$2:$B$16,2,FALSE)," - ",TEXT(Table13[[#This Row],[Series Number]],"0000")," - ",TEXT(VLOOKUP(Table13[[#This Row],[Location]],'Data Validation'!$A$20:$B$47,2,FALSE),"00")) -> #N/A | Q2110: =Table13[[#This Row],[Unit Value]]*Table13[[#This Row],[Qty | PCount]] -> 0 | R2110: =IF(Table13[[#This Row],[Unit Value]]<=4999,"Low-Value Asset","High-Value Asset") -> Low-Value Asset | AB2110: =CONCATENATE(Table13[[#This Row],[Title]]," - ",IF(Table13[[#This Row],[Supplier]]="n|a","",CONCATENATE("Supplier: ",Table13[[#This Row],[Supplier]]," - ")),IF(Table13[[#This Row],[Subject]]="n|a","",CONCATENATE("Subject: ",Table13[[#This Row],[Subject]]," - ")),IF(Table13[[#This Row],[Quarter]]="n|a","",CONCATENATE("Quarter: ",Table13[[#This Row],[Quarter]]," - ")),IF(Table13[[#This Row],[Grade Level]]="n|a","",CONCATENATE("Grade Level: ",Table13[[#This Row],[Grade Level]]," - ")),IF(Table13[[#This Row],[Delivery Receipt Number]]="n|a","",CONCATENATE("DR No: ",Table13[[#This Row],[Delivery Receipt Number]]," - ")),IF(Table13[[#This Row],[Contract Number]]="n|a","",CONCATENATE("CN: ",Table13[[#This Row],[Contract Number]]," - ")),IF(Table13[[#This Row],[PTR Number]]="n|a","",CONCATENATE("PTR No: ",Table13[[#This Row],[PTR Number]]," - ")),IF(Table13[[#This Row],[Origin]]="n|a","",CONCATENATE("Origin: ",Table13[[#This Row],[Origin]]))) -> - Supplier: - Subject: - Quarter: - Grade Level: - DR No: - CN: - PTR No: - Origin:
D2111: =CONCATENATE(TEXT(Table13[[#This Row],[Date of Acquisition]],"yyyy")," - ", VLOOKUP(Table13[[#This Row],[Article]],'Data Validation'!$A$2:$B$16,2,FALSE)," - ",TEXT(Table13[[#This Row],[Series Number]],"0000")," - ",TEXT(VLOOKUP(Table13[[#This Row],[Location]],'Data Validation'!$A$20:$B$47,2,FALSE),"00")) -> #N/A | Q2111: =Table13[[#This Row],[Unit Value]]*Table13[[#This Row],[Qty | PCount]] -> 0 | R2111: =IF(Table13[[#This Row],[Unit Value]]<=4999,"Low-Value Asset","High-Value Asset") -> Low-Value Asset | AB2111: =CONCATENATE(Table13[[#This Row],[Title]]," - ",IF(Table13[[#This Row],[Supplier]]="n|a","",CONCATENATE("Supplier: ",Table13[[#This Row],[Supplier]]," - ")),IF(Table13[[#This Row],[Subject]]="n|a","",CONCATENATE("Subject: ",Table13[[#This Row],[Subject]]," - ")),IF(Table13[[#This Row],[Quarter]]="n|a","",CONCATENATE("Quarter: ",Table13[[#This Row],[Quarter]]," - ")),IF(Table13[[#This Row],[Grade Level]]="n|a","",CONCATENATE("Grade Level: ",Table13[[#This Row],[Grade Level]]," - ")),IF(Table13[[#This Row],[Delivery Receipt Number]]="n|a","",CONCATENATE("DR No: ",Table13[[#This Row],[Delivery Receipt Number]]," - ")),IF(Table13[[#This Row],[Contract Number]]="n|a","",CONCATENATE("CN: ",Table13[[#This Row],[Contract Number]]," - ")),IF(Table13[[#This Row],[PTR Number]]="n|a","",CONCATENATE("PTR No: ",Table13[[#This Row],[PTR Number]]," - ")),IF(Table13[[#This Row],[Origin]]="n|a","",CONCATENATE("Origin: ",Table13[[#This Row],[Origin]]))) -> - Supplier: - Subject: - Quarter: - Grade Level: - DR No: - CN: - PTR No: - Origin:
D2112: =CONCATENATE(TEXT(Table13[[#This Row],[Date of Acquisition]],"yyyy")," - ", VLOOKUP(Table13[[#This Row],[Article]],'Data Validation'!$A$2:$B$16,2,FALSE)," - ",TEXT(Table13[[#This Row],[Series Number]],"0000")," - ",TEXT(VLOOKUP(Table13[[#This Row],[Location]],'Data Validation'!$A$20:$B$47,2,FALSE),"00")) -> #N/A | Q2112: =Table13[[#This Row],[Unit Value]]*Table13[[#This Row],[Qty | PCount]] -> 0 | R2112: =IF(Table13[[#This Row],[Unit Value]]<=4999,"Low-Value Asset","High-Value Asset") -> Low-Value Asset | AB2112: =CONCATENATE(Table13[[#This Row],[Title]]," - ",IF(Table13[[#This Row],[Supplier]]="n|a","",CONCATENATE("Supplier: ",Table13[[#This Row],[Supplier]]," - ")),IF(Table13[[#This Row],[Subject]]="n|a","",CONCATENATE("Subject: ",Table13[[#This Row],[Subject]]," - ")),IF(Table13[[#This Row],[Quarter]]="n|a","",CONCATENATE("Quarter: ",Table13[[#This Row],[Quarter]]," - ")),IF(Table13[[#This Row],[Grade Level]]="n|a","",CONCATENATE("Grade Level: ",Table13[[#This Row],[Grade Level]]," - ")),IF(Table13[[#This Row],[Delivery Receipt Number]]="n|a","",CONCATENATE("DR No: ",Table13[[#This Row],[Delivery Receipt Number]]," - ")),IF(Table13[[#This Row],[Contract Number]]="n|a","",CONCATENATE("CN: ",Table13[[#This Row],[Contract Number]]," - ")),IF(Table13[[#This Row],[PTR Number]]="n|a","",CONCATENATE("PTR No: ",Table13[[#This Row],[PTR Number]]," - ")),IF(Table13[[#This Row],[Origin]]="n|a","",CONCATENATE("Origin: ",Table13[[#This Row],[Origin]]))) -> - Supplier: - Subject: - Quarter: - Grade Level: - DR No: - CN: - PTR No: - Origin:
D2113: =CONCATENATE(TEXT(Table13[[#This Row],[Date of Acquisition]],"yyyy")," - ", VLOOKUP(Table13[[#This Row],[Article]],'Data Validation'!$A$2:$B$16,2,FALSE)," - ",TEXT(Table13[[#This Row],[Series Number]],"0000")," - ",TEXT(VLOOKUP(Table13[[#This Row],[Location]],'Data Validation'!$A$20:$B$47,2,FALSE),"00")) -> #N/A | Q2113: =Table13[[#This Row],[Unit Value]]*Table13[[#This Row],[Qty | PCount]] -> 0 | R2113: =IF(Table13[[#This Row],[Unit Value]]<=4999,"Low-Value Asset","High-Value Asset") -> Low-Value Asset | AB2113: =CONCATENATE(Table13[[#This Row],[Title]]," - ",IF(Table13[[#This Row],[Supplier]]="n|a","",CONCATENATE("Supplier: ",Table13[[#This Row],[Supplier]]," - ")),IF(Table13[[#This Row],[Subject]]="n|a","",CONCATENATE("Subject: ",Table13[[#This Row],[Subject]]," - ")),IF(Table13[[#This Row],[Quarter]]="n|a","",CONCATENATE("Quarter: ",Table13[[#This Row],[Quarter]]," - ")),IF(Table13[[#This Row],[Grade Level]]="n|a","",CONCATENATE("Grade Level: ",Table13[[#This Row],[Grade Level]]," - ")),IF(Table13[[#This Row],[Delivery Receipt Number]]="n|a","",CONCATENATE("DR No: ",Table13[[#This Row],[Delivery Receipt Number]]," - ")),IF(Table13[[#This Row],[Contract Number]]="n|a","",CONCATENATE("CN: ",Table13[[#This Row],[Contract Number]]," - ")),IF(Table13[[#This Row],[PTR Number]]="n|a","",CONCATENATE("PTR No: ",Table13[[#This Row],[PTR Number]]," - ")),IF(Table13[[#This Row],[Origin]]="n|a","",CONCATENATE("Origin: ",Table13[[#This Row],[Origin]]))) -> - Supplier: - Subject: - Quarter: - Grade Level: - DR No: - CN: - PTR No: - Origin:
D2114: =CONCATENATE(TEXT(Table13[[#This Row],[Date of Acquisition]],"yyyy")," - ", VLOOKUP(Table13[[#This Row],[Article]],'Data Validation'!$A$2:$B$16,2,FALSE)," - ",TEXT(Table13[[#This Row],[Series Number]],"0000")," - ",TEXT(VLOOKUP(Table13[[#This Row],[Location]],'Data Validation'!$A$20:$B$47,2,FALSE),"00")) -> #N/A | Q2114: =Table13[[#This Row],[Unit Value]]*Table13[[#This Row],[Qty | PCount]] -> 0 | R2114: =IF(Table13[[#This Row],[Unit Value]]<=4999,"Low-Value Asset","High-Value Asset") -> Low-Value Asset | AB2114: =CONCATENATE(Table13[[#This Row],[Title]]," - ",IF(Table13[[#This Row],[Supplier]]="n|a","",CONCATENATE("Supplier: ",Table13[[#This Row],[Supplier]]," - ")),IF(Table13[[#This Row],[Subject]]="n|a","",CONCATENATE("Subject: ",Table13[[#This Row],[Subject]]," - ")),IF(Table13[[#This Row],[Quarter]]="n|a","",CONCATENATE("Quarter: ",Table13[[#This Row],[Quarter]]," - ")),IF(Table13[[#This Row],[Grade Level]]="n|a","",CONCATENATE("Grade Level: ",Table13[[#This Row],[Grade Level]]," - ")),IF(Table13[[#This Row],[Delivery Receipt Number]]="n|a","",CONCATENATE("DR No: ",Table13[[#This Row],[Delivery Receipt Number]]," - ")),IF(Table13[[#This Row],[Contract Number]]="n|a","",CONCATENATE("CN: ",Table13[[#This Row],[Contract Number]]," - ")),IF(Table13[[#This Row],[PTR Number]]="n|a","",CONCATENATE("PTR No: ",Table13[[#This Row],[PTR Number]]," - ")),IF(Table13[[#This Row],[Origin]]="n|a","",CONCATENATE("Origin: ",Table13[[#This Row],[Origin]]))) -> - Supplier: - Subject: - Quarter: - Grade Level: - DR No: - CN: - PTR No: - Origin:
D2115: =CONCATENATE(TEXT(Table13[[#This Row],[Date of Acquisition]],"yyyy")," - ", VLOOKUP(Table13[[#This Row],[Article]],'Data Validation'!$A$2:$B$16,2,FALSE)," - ",TEXT(Table13[[#This Row],[Series Number]],"0000")," - ",TEXT(VLOOKUP(Table13[[#This Row],[Location]],'Data Validation'!$A$20:$B$47,2,FALSE),"00")) -> #N/A | Q2115: =Table13[[#This Row],[Unit Value]]*Table13[[#This Row],[Qty | PCount]] -> 0 | R2115: =IF(Table13[[#This Row],[Unit Value]]<=4999,"Low-Value Asset","High-Value Asset") -> Low-Value Asset | AB2115: =CONCATENATE(Table13[[#This Row],[Title]]," - ",IF(Table13[[#This Row],[Supplier]]="n|a","",CONCATENATE("Supplier: ",Table13[[#This Row],[Supplier]]," - ")),IF(Table13[[#This Row],[Subject]]="n|a","",CONCATENATE("Subject: ",Table13[[#This Row],[Subject]]," - ")),IF(Table13[[#This Row],[Quarter]]="n|a","",CONCATENATE("Quarter: ",Table13[[#This Row],[Quarter]]," - ")),IF(Table13[[#This Row],[Grade Level]]="n|a","",CONCATENATE("Grade Level: ",Table13[[#This Row],[Grade Level]]," - ")),IF(Table13[[#This Row],[Delivery Receipt Number]]="n|a","",CONCATENATE("DR No: ",Table13[[#This Row],[Delivery Receipt Number]]," - ")),IF(Table13[[#This Row],[Contract Number]]="n|a","",CONCATENATE("CN: ",Table13[[#This Row],[Contract Number]]," - ")),IF(Table13[[#This Row],[PTR Number]]="n|a","",CONCATENATE("PTR No: ",Table13[[#This Row],[PTR Number]]," - ")),IF(Table13[[#This Row],[Origin]]="n|a","",CONCATENATE("Origin: ",Table13[[#This Row],[Origin]]))) -> - Supplier: - Subject: - Quarter: - Grade Level: - DR No: - CN: - PTR No: - Origin:
D2116: =CONCATENATE(TEXT(Table13[[#This Row],[Date of Acquisition]],"yyyy")," - ", VLOOKUP(Table13[[#This Row],[Article]],'Data Validation'!$A$2:$B$16,2,FALSE)," - ",TEXT(Table13[[#This Row],[Series Number]],"0000")," - ",TEXT(VLOOKUP(Table13[[#This Row],[Location]],'Data Validation'!$A$20:$B$47,2,FALSE),"00")) -> #N/A | Q2116: =Table13[[#This Row],[Unit Value]]*Table13[[#This Row],[Qty | PCount]] -> 0 | R2116: =IF(Table13[[#This Row],[Unit Value]]<=4999,"Low-Value Asset","High-Value Asset") -> Low-Value Asset | AB2116: =CONCATENATE(Table13[[#This Row],[Title]]," - ",IF(Table13[[#This Row],[Supplier]]="n|a","",CONCATENATE("Supplier: ",Table13[[#This Row],[Supplier]]," - ")),IF(Table13[[#This Row],[Subject]]="n|a","",CONCATENATE("Subject: ",Table13[[#This Row],[Subject]]," - ")),IF(Table13[[#This Row],[Quarter]]="n|a","",CONCATENATE("Quarter: ",Table13[[#This Row],[Quarter]]," - ")),IF(Table13[[#This Row],[Grade Level]]="n|a","",CONCATENATE("Grade Level: ",Table13[[#This Row],[Grade Level]]," - ")),IF(Table13[[#This Row],[Delivery Receipt Number]]="n|a","",CONCATENATE("DR No: ",Table13[[#This Row],[Delivery Receipt Number]]," - ")),IF(Table13[[#This Row],[Contract Number]]="n|a","",CONCATENATE("CN: ",Table13[[#This Row],[Contract Number]]," - ")),IF(Table13[[#This Row],[PTR Number]]="n|a","",CONCATENATE("PTR No: ",Table13[[#This Row],[PTR Number]]," - ")),IF(Table13[[#This Row],[Origin]]="n|a","",CONCATENATE("Origin: ",Table13[[#This Row],[Origin]]))) -> - Supplier: - Subject: - Quarter: - Grade Level: - DR No: - CN: - PTR No: - Origin:
D2117: =CONCATENATE(TEXT(Table13[[#This Row],[Date of Acquisition]],"yyyy")," - ", VLOOKUP(Table13[[#This Row],[Article]],'Data Validation'!$A$2:$B$16,2,FALSE)," - ",TEXT(Table13[[#This Row],[Series Number]],"0000")," - ",TEXT(VLOOKUP(Table13[[#This Row],[Location]],'Data Validation'!$A$20:$B$47,2,FALSE),"00")) -> #N/A | Q2117: =Table13[[#This Row],[Unit Value]]*Table13[[#This Row],[Qty | PCount]] -> 0 | R2117: =IF(Table13[[#This Row],[Unit Value]]<=4999,"Low-Value Asset","High-Value Asset") -> Low-Value Asset | AB2117: =CONCATENATE(Table13[[#This Row],[Title]]," - ",IF(Table13[[#This Row],[Supplier]]="n|a","",CONCATENATE("Supplier: ",Table13[[#This Row],[Supplier]]," - ")),IF(Table13[[#This Row],[Subject]]="n|a","",CONCATENATE("Subject: ",Table13[[#This Row],[Subject]]," - ")),IF(Table13[[#This Row],[Quarter]]="n|a","",CONCATENATE("Quarter: ",Table13[[#This Row],[Quarter]]," - ")),IF(Table13[[#This Row],[Grade Level]]="n|a","",CONCATENATE("Grade Level: ",Table13[[#This Row],[Grade Level]]," - ")),IF(Table13[[#This Row],[Delivery Receipt Number]]="n|a","",CONCATENATE("DR No: ",Table13[[#This Row],[Delivery Receipt Number]]," - ")),IF(Table13[[#This Row],[Contract Number]]="n|a","",CONCATENATE("CN: ",Table13[[#This Row],[Contract Number]]," - ")),IF(Table13[[#This Row],[PTR Number]]="n|a","",CONCATENATE("PTR No: ",Table13[[#This Row],[PTR Number]]," - ")),IF(Table13[[#This Row],[Origin]]="n|a","",CONCATENATE("Origin: ",Table13[[#This Row],[Origin]]))) -> - Supplier: - Subject: - Quarter: - Grade Level: - DR No: - CN: - PTR No: - Origin:
D2118: =CONCATENATE(TEXT(Table13[[#This Row],[Date of Acquisition]],"yyyy")," - ", VLOOKUP(Table13[[#This Row],[Article]],'Data Validation'!$A$2:$B$16,2,FALSE)," - ",TEXT(Table13[[#This Row],[Series Number]],"0000")," - ",TEXT(VLOOKUP(Table13[[#This Row],[Location]],'Data Validation'!$A$20:$B$47,2,FALSE),"00")) -> #N/A | Q2118: =Table13[[#This Row],[Unit Value]]*Table13[[#This Row],[Qty | PCount]] -> 0 | R2118: =IF(Table13[[#This Row],[Unit Value]]<=4999,"Low-Value Asset","High-Value Asset") -> Low-Value Asset | AB2118: =CONCATENATE(Table13[[#This Row],[Title]]," - ",IF(Table13[[#This Row],[Supplier]]="n|a","",CONCATENATE("Supplier: ",Table13[[#This Row],[Supplier]]," - ")),IF(Table13[[#This Row],[Subject]]="n|a","",CONCATENATE("Subject: ",Table13[[#This Row],[Subject]]," - ")),IF(Table13[[#This Row],[Quarter]]="n|a","",CONCATENATE("Quarter: ",Table13[[#This Row],[Quarter]]," - ")),IF(Table13[[#This Row],[Grade Level]]="n|a","",CONCATENATE("Grade Level: ",Table13[[#This Row],[Grade Level]]," - ")),IF(Table13[[#This Row],[Delivery Receipt Number]]="n|a","",CONCATENATE("DR No: ",Table13[[#This Row],[Delivery Receipt Number]]," - ")),IF(Table13[[#This Row],[Contract Number]]="n|a","",CONCATENATE("CN: ",Table13[[#This Row],[Contract Number]]," - ")),IF(Table13[[#This Row],[PTR Number]]="n|a","",CONCATENATE("PTR No: ",Table13[[#This Row],[PTR Number]]," - ")),IF(Table13[[#This Row],[Origin]]="n|a","",CONCATENATE("Origin: ",Table13[[#This Row],[Origin]]))) -> - Supplier: - Subject: - Quarter: - Grade Level: - DR No: - CN: - PTR No: - Origin:
D2119: =CONCATENATE(TEXT(Table13[[#This Row],[Date of Acquisition]],"yyyy")," - ", VLOOKUP(Table13[[#This Row],[Article]],'Data Validation'!$A$2:$B$16,2,FALSE)," - ",TEXT(Table13[[#This Row],[Series Number]],"0000")," - ",TEXT(VLOOKUP(Table13[[#This Row],[Location]],'Data Validation'!$A$20:$B$47,2,FALSE),"00")) -> #N/A | Q2119: =Table13[[#This Row],[Unit Value]]*Table13[[#This Row],[Qty | PCount]] -> 0 | R2119: =IF(Table13[[#This Row],[Unit Value]]<=4999,"Low-Value Asset","High-Value Asset") -> Low-Value Asset | AB2119: =CONCATENATE(Table13[[#This Row],[Title]]," - ",IF(Table13[[#This Row],[Supplier]]="n|a","",CONCATENATE("Supplier: ",Table13[[#This Row],[Supplier]]," - ")),IF(Table13[[#This Row],[Subject]]="n|a","",CONCATENATE("Subject: ",Table13[[#This Row],[Subject]]," - ")),IF(Table13[[#This Row],[Quarter]]="n|a","",CONCATENATE("Quarter: ",Table13[[#This Row],[Quarter]]," - ")),IF(Table13[[#This Row],[Grade Level]]="n|a","",CONCATENATE("Grade Level: ",Table13[[#This Row],[Grade Level]]," - ")),IF(Table13[[#This Row],[Delivery Receipt Number]]="n|a","",CONCATENATE("DR No: ",Table13[[#This Row],[Delivery Receipt Number]]," - ")),IF(Table13[[#This Row],[Contract Number]]="n|a","",CONCATENATE("CN: ",Table13[[#This Row],[Contract Number]]," - ")),IF(Table13[[#This Row],[PTR Number]]="n|a","",CONCATENATE("PTR No: ",Table13[[#This Row],[PTR Number]]," - ")),IF(Table13[[#This Row],[Origin]]="n|a","",CONCATENATE("Origin: ",Table13[[#This Row],[Origin]]))) -> - Supplier: - Subject: - Quarter: - Grade Level: - DR No: - CN: - PTR No: - Origin:
... D4289: =CONCATENATE(TEXT(Table13[[#This Row],[Date of Acquisition]],"yyyy")," - ", VLOOKUP(Table13[[#This Row],[Article]],'Data Validation'!$A$2:$B$16,2,FALSE)," - ",TEXT(Table13[[#This Row],[Series Number]],"0000")," - ",TEXT(VLOOKUP(Table13[[#This Row],[Location]],'Data Validation'!$A$20:$B$47,2,FALSE),"00")) -> #N/A | Q4289: =Table13[[#This Row],[Unit Value]]*Table13[[#This Row],[Qty | PCount]] -> 0 | R4289: =IF(Table13[[#This Row],[Unit Value]]<=4999,"Low-Value Asset","High-Value Asset") -> Low-Value Asset | AB4289: =CONCATENATE(Table13[[#This Row],[Title]]," - ",IF(Table13[[#This Row],[Supplier]]="n|a","",CONCATENATE("Supplier: ",Table13[[#This Row],[Supplier]]," - ")),IF(Table13[[#This Row],[Subject]]="n|a","",CONCATENATE("Subject: ",Table13[[#This Row],[Subject]]," - ")),IF(Table13[[#This Row],[Quarter]]="n|a","",CONCATENATE("Quarter: ",Table13[[#This Row],[Quarter]]," - ")),IF(Table13[[#This Row],[Grade Level]]="n|a","",CONCATENATE("Grade Level: ",Table13[[#This Row],[Grade Level]]," - ")),IF(Table13[[#This Row],[Delivery Receipt Number]]="n|a","",CONCATENATE("DR No: ",Table13[[#This Row],[Delivery Receipt Number]]," - ")),IF(Table13[[#This Row],[Contract Number]]="n|a","",CONCATENATE("CN: ",Table13[[#This Row],[Contract Number]]," - ")),IF(Table13[[#This Row],[PTR Number]]="n|a","",CONCATENATE("PTR No: ",Table13[[#This Row],[PTR Number]]," - ")),IF(Table13[[#This Row],[Origin]]="n|a","",CONCATENATE("Origin: ",Table13[[#This Row],[Origin]]))) -> - Supplier: - Subject: - Quarter: - Grade Level: - DR No: - CN: - PTR No: - Origin:
D4290: 2021 - 07 - 00 - 0000 - 11 | Q4290: 330.3 | R4290: Low-Value Asset | AB4290: MODULE 6: Sequence and Working Backward - Supplier: Rex Book Store Inc. - Subject: Mathematics - Quarter: 3 - Grade Level: Grade 5 - DR No: - - CN: 2021-BLR2(009-018)-BIV-CB003-C013 - PTR No: PTR-REX-21-11-0061 - Origin: Central Office
D4291: 2021 - 07 - 00 - 0000 - 11 | Q4291: 330.3 | R4291: Low-Value Asset | AB4291: MODULE 6: Sequence and Working Backward - Supplier: Rex Book Store Inc. - Subject: Mathematics - Quarter: 3 - Grade Level: Grade 5 - DR No: - - CN: 2021-BLR2(009-018)-BIV-CB003-C013 - PTR No: PTR-REX-21-11-0061 - Origin: Central Office
D4292: =CONCATENATE(TEXT(Table13[[#This Row],[Date of Acquisition]],"yyyy")," - ", VLOOKUP(Table13[[#This Row],[Article]],'Data Validation'!$A$2:$B$16,2,FALSE)," - ",TEXT(Table13[[#This Row],[Series Number]],"0000")," - ",TEXT(VLOOKUP(Table13[[#This Row],[Location]],'Data Validation'!$A$20:$B$47,2,FALSE),"00")) -> #N/A | Q4292: =Table13[[#This Row],[Unit Value]]*Table13[[#This Row],[Qty | PCount]] -> 0 | R4292: =IF(Table13[[#This Row],[Unit Value]]<=4999,"Low-Value Asset","High-Value Asset") -> Low-Value Asset | AB4292: =CONCATENATE(Table13[[#This Row],[Title]]," - ",IF(Table13[[#This Row],[Supplier]]="n|a","",CONCATENATE("Supplier: ",Table13[[#This Row],[Supplier]]," - ")),IF(Table13[[#This Row],[Subject]]="n|a","",CONCATENATE("Subject: ",Table13[[#This Row],[Subject]]," - ")),IF(Table13[[#This Row],[Quarter]]="n|a","",CONCATENATE("Quarter: ",Table13[[#This Row],[Quarter]]," - ")),IF(Table13[[#This Row],[Grade Level]]="n|a","",CONCATENATE("Grade Level: ",Table13[[#This Row],[Grade Level]]," - ")),IF(Table13[[#This Row],[Delivery Receipt Number]]="n|a","",CONCATENATE("DR No: ",Table13[[#This Row],[Delivery Receipt Number]]," - ")),IF(Table13[[#This Row],[Contract Number]]="n|a","",CONCATENATE("CN: ",Table13[[#This Row],[Contract Number]]," - ")),IF(Table13[[#This Row],[PTR Number]]="n|a","",CONCATENATE("PTR No: ",Table13[[#This Row],[PTR Number]]," - ")),IF(Table13[[#This Row],[Origin]]="n|a","",CONCATENATE("Origin: ",Table13[[#This Row],[Origin]]))) -> - Supplier: - Subject: - Quarter: - Grade Level: - DR No: - CN: - PTR No: - Origin:
D4293: =CONCATENATE(TEXT(Table13[[#This Row],[Date of Acquisition]],"yyyy")," - ", VLOOKUP(Table13[[#This Row],[Article]],'Data Validation'!$A$2:$B$16,2,FALSE)," - ",TEXT(Table13[[#This Row],[Series Number]],"0000")," - ",TEXT(VLOOKUP(Table13[[#This Row],[Location]],'Data Validation'!$A$20:$B$47,2,FALSE),"00")) -> #N/A | Q4293: =Table13[[#This Row],[Unit Value]]*Table13[[#This Row],[Qty | PCount]] -> 0 | R4293: =IF(Table13[[#This Row],[Unit Value]]<=4999,"Low-Value Asset","High-Value Asset") -> Low-Value Asset | AB4293: =CONCATENATE(Table13[[#This Row],[Title]]," - ",IF(Table13[[#This Row],[Supplier]]="n|a","",CONCATENATE("Supplier: ",Table13[[#This Row],[Supplier]]," - ")),IF(Table13[[#This Row],[Subject]]="n|a","",CONCATENATE("Subject: ",Table13[[#This Row],[Subject]]," - ")),IF(Table13[[#This Row],[Quarter]]="n|a","",CONCATENATE("Quarter: ",Table13[[#This Row],[Quarter]]," - ")),IF(Table13[[#This Row],[Grade Level]]="n|a","",CONCATENATE("Grade Level: ",Table13[[#This Row],[Grade Level]]," - ")),IF(Table13[[#This Row],[Delivery Receipt Number]]="n|a","",CONCATENATE("DR No: ",Table13[[#This Row],[Delivery Receipt Number]]," - ")),IF(Table13[[#This Row],[Contract Number]]="n|a","",CONCATENATE("CN: ",Table13[[#This Row],[Contract Number]]," - ")),IF(Table13[[#This Row],[PTR Number]]="n|a","",CONCATENATE("PTR No: ",Table13[[#This Row],[PTR Number]]," - ")),IF(Table13[[#This Row],[Origin]]="n|a","",CONCATENATE("Origin: ",Table13[[#This Row],[Origin]]))) -> - Supplier: - Subject: - Quarter: - Grade Level: - DR No: - CN: - PTR No: - Origin:
D4294: =CONCATENATE(TEXT(Table13[[#This Row],[Date of Acquisition]],"yyyy")," - ", VLOOKUP(Table13[[#This Row],[Article]],'Data Validation'!$A$2:$B$16,2,FALSE)," - ",TEXT(Table13[[#This Row],[Series Number]],"0000")," - ",TEXT(VLOOKUP(Table13[[#This Row],[Location]],'Data Validation'!$A$20:$B$47,2,FALSE),"00")) -> #N/A | Q4294: =Table13[[#This Row],[Unit Value]]*Table13[[#This Row],[Qty | PCount]] -> 0 | R4294: =IF(Table13[[#This Row],[Unit Value]]<=4999,"Low-Value Asset","High-Value Asset") -> Low-Value Asset | AB4294: =CONCATENATE(Table13[[#This Row],[Title]]," - ",IF(Table13[[#This Row],[Supplier]]="n|a","",CONCATENATE("Supplier: ",Table13[[#This Row],[Supplier]]," - ")),IF(Table13[[#This Row],[Subject]]="n|a","",CONCATENATE("Subject: ",Table13[[#This Row],[Subject]]," - ")),IF(Table13[[#This Row],[Quarter]]="n|a","",CONCATENATE("Quarter: ",Table13[[#This Row],[Quarter]]," - ")),IF(Table13[[#This Row],[Grade Level]]="n|a","",CONCATENATE("Grade Level: ",Table13[[#This Row],[Grade Level]]," - ")),IF(Table13[[#This Row],[Delivery Receipt Number]]="n|a","",CONCATENATE("DR No: ",Table13[[#This Row],[Delivery Receipt Number]]," - ")),IF(Table13[[#This Row],[Contract Number]]="n|a","",CONCATENATE("CN: ",Table13[[#This Row],[Contract Number]]," - ")),IF(Table13[[#This Row],[PTR Number]]="n|a","",CONCATENATE("PTR No: ",Table13[[#This Row],[PTR Number]]," - ")),IF(Table13[[#This Row],[Origin]]="n|a","",CONCATENATE("Origin: ",Table13[[#This Row],[Origin]]))) -> - Supplier: - Subject: - Quarter: - Grade Level: - DR No: - CN: - PTR No: - Origin:
D4295: =CONCATENATE(TEXT(Table13[[#This Row],[Date of Acquisition]],"yyyy")," - ", VLOOKUP(Table13[[#This Row],[Article]],'Data Validation'!$A$2:$B$16,2,FALSE)," - ",TEXT(Table13[[#This Row],[Series Number]],"0000")," - ",TEXT(VLOOKUP(Table13[[#This Row],[Location]],'Data Validation'!$A$20:$B$47,2,FALSE),"00")) -> #N/A | Q4295: =Table13[[#This Row],[Unit Value]]*Table13[[#This Row],[Qty | PCount]] -> 0 | R4295: =IF(Table13[[#This Row],[Unit Value]]<=4999,"Low-Value Asset","High-Value Asset") -> Low-Value Asset | AB4295: =CONCATENATE(Table13[[#This Row],[Title]]," - ",IF(Table13[[#This Row],[Supplier]]="n|a","",CONCATENATE("Supplier: ",Table13[[#This Row],[Supplier]]," - ")),IF(Table13[[#This Row],[Subject]]="n|a","",CONCATENATE("Subject: ",Table13[[#This Row],[Subject]]," - ")),IF(Table13[[#This Row],[Quarter]]="n|a","",CONCATENATE("Quarter: ",Table13[[#This Row],[Quarter]]," - ")),IF(Table13[[#This Row],[Grade Level]]="n|a","",CONCATENATE("Grade Level: ",Table13[[#This Row],[Grade Level]]," - ")),IF(Table13[[#This Row],[Delivery Receipt Number]]="n|a","",CONCATENATE("DR No: ",Table13[[#This Row],[Delivery Receipt Number]]," - ")),IF(Table13[[#This Row],[Contract Number]]="n|a","",CONCATENATE("CN: ",Table13[[#This Row],[Contract Number]]," - ")),IF(Table13[[#This Row],[PTR Number]]="n|a","",CONCATENATE("PTR No: ",Table13[[#This Row],[PTR Number]]," - ")),IF(Table13[[#This Row],[Origin]]="n|a","",CONCATENATE("Origin: ",Table13[[#This Row],[Origin]]))) -> - Supplier: - Subject: - Quarter: - Grade Level: - DR No: - CN: - PTR No: - Origin:
D4296: =CONCATENATE(TEXT(Table13[[#This Row],[Date of Acquisition]],"yyyy")," - ", VLOOKUP(Table13[[#This Row],[Article]],'Data Validation'!$A$2:$B$16,2,FALSE)," - ",TEXT(Table13[[#This Row],[Series Number]],"0000")," - ",TEXT(VLOOKUP(Table13[[#This Row],[Location]],'Data Validation'!$A$20:$B$47,2,FALSE),"00")) -> #N/A | Q4296: =Table13[[#This Row],[Unit Value]]*Table13[[#This Row],[Qty | PCount]] -> 0 | R4296: =IF(Table13[[#This Row],[Unit Value]]<=4999,"Low-Value Asset","High-Value Asset") -> Low-Value Asset | AB4296: =CONCATENATE(Table13[[#This Row],[Title]]," - ",IF(Table13[[#This Row],[Supplier]]="n|a","",CONCATENATE("Supplier: ",Table13[[#This Row],[Supplier]]," - ")),IF(Table13[[#This Row],[Subject]]="n|a","",CONCATENATE("Subject: ",Table13[[#This Row],[Subject]]," - ")),IF(Table13[[#This Row],[Quarter]]="n|a","",CONCATENATE("Quarter: ",Table13[[#This Row],[Quarter]]," - ")),IF(Table13[[#This Row],[Grade Level]]="n|a","",CONCATENATE("Grade Level: ",Table13[[#This Row],[Grade Level]]," - ")),IF(Table13[[#This Row],[Delivery Receipt Number]]="n|a","",CONCATENATE("DR No: ",Table13[[#This Row],[Delivery Receipt Number]]," - ")),IF(Table13[[#This Row],[Contract Number]]="n|a","",CONCATENATE("CN: ",Table13[[#This Row],[Contract Number]]," - ")),IF(Table13[[#This Row],[PTR Number]]="n|a","",CONCATENATE("PTR No: ",Table13[[#This Row],[PTR Number]]," - ")),IF(Table13[[#This Row],[Origin]]="n|a","",CONCATENATE("Origin: ",Table13[[#This Row],[Origin]]))) -> - Supplier: - Subject: - Quarter: - Grade Level: - DR No: - CN: - PTR No: - Origin:
D4297: =CONCATENATE(TEXT(Table13[[#This Row],[Date of Acquisition]],"yyyy")," - ", VLOOKUP(Table13[[#This Row],[Article]],'Data Validation'!$A$2:$B$16,2,FALSE)," - ",TEXT(Table13[[#This Row],[Series Number]],"0000")," - ",TEXT(VLOOKUP(Table13[[#This Row],[Location]],'Data Validation'!$A$20:$B$47,2,FALSE),"00")) -> #N/A | Q4297: =Table13[[#This Row],[Unit Value]]*Table13[[#This Row],[Qty | PCount]] -> 0 | R4297: =IF(Table13[[#This Row],[Unit Value]]<=4999,"Low-Value Asset","High-Value Asset") -> Low-Value Asset | AB4297: =CONCATENATE(Table13[[#This Row],[Title]]," - ",IF(Table13[[#This Row],[Supplier]]="n|a","",CONCATENATE("Supplier: ",Table13[[#This Row],[Supplier]]," - ")),IF(Table13[[#This Row],[Subject]]="n|a","",CONCATENATE("Subject: ",Table13[[#This Row],[Subject]]," - ")),IF(Table13[[#This Row],[Quarter]]="n|a","",CONCATENATE("Quarter: ",Table13[[#This Row],[Quarter]]," - ")),IF(Table13[[#This Row],[Grade Level]]="n|a","",CONCATENATE("Grade Level: ",Table13[[#This Row],[Grade Level]]," - ")),IF(Table13[[#This Row],[Delivery Receipt Number]]="n|a","",CONCATENATE("DR No: ",Table13[[#This Row],[Delivery Receipt Number]]," - ")),IF(Table13[[#This Row],[Contract Number]]="n|a","",CONCATENATE("CN: ",Table13[[#This Row],[Contract Number]]," - ")),IF(Table13[[#This Row],[PTR Number]]="n|a","",CONCATENATE("PTR No: ",Table13[[#This Row],[PTR Number]]," - ")),IF(Table13[[#This Row],[Origin]]="n|a","",CONCATENATE("Origin: ",Table13[[#This Row],[Origin]]))) -> - Supplier: - Subject: - Quarter: - Grade Level: - DR No: - CN: - PTR No: - Origin:
D4298: 2021 - 07 - 00 - 0000 - 05 | Q4298: 1101 | R4298: Low-Value Asset | AB4298: MODULE 6: Sequence and Working Backward - Supplier: Rex Book Store Inc. - Subject: Mathematics - Quarter: 3 - Grade Level: Grade 5 - DR No: - - CN: 2021-BLR2(009-018)-BIV-CB003-C013 - PTR No: PTR-REX-21-11-0061 - Origin: Central Office
D4299: 2021 - 07 - 00 - 0000 - 05 | Q4299: 1101 | R4299: Low-Value Asset | AB4299: MODULE 6: Sequence and Working Backward - Supplier: Rex Book Store Inc. - Subject: Mathematics - Quarter: 3 - Grade Level: Grade 5 - DR No: - - CN: 2021-BLR2(009-018)-BIV-CB003-C013 - PTR No: PTR-REX-21-11-0061 - Origin: Central Office
D4300: =CONCATENATE(TEXT(Table13[[#This Row],[Date of Acquisition]],"yyyy")," - ", VLOOKUP(Table13[[#This Row],[Article]],'Data Validation'!$A$2:$B$16,2,FALSE)," - ",TEXT(Table13[[#This Row],[Series Number]],"0000")," - ",TEXT(VLOOKUP(Table13[[#This Row],[Location]],'Data Validation'!$A$20:$B$47,2,FALSE),"00")) -> #N/A | Q4300: =Table13[[#This Row],[Unit Value]]*Table13[[#This Row],[Qty | PCount]] -> 0 | R4300: =IF(Table13[[#This Row],[Unit Value]]<=4999,"Low-Value Asset","High-Value Asset") -> Low-Value Asset | AB4300: =CONCATENATE(Table13[[#This Row],[Title]]," - ",IF(Table13[[#This Row],[Supplier]]="n|a","",CONCATENATE("Supplier: ",Table13[[#This Row],[Supplier]]," - ")),IF(Table13[[#This Row],[Subject]]="n|a","",CONCATENATE("Subject: ",Table13[[#This Row],[Subject]]," - ")),IF(Table13[[#This Row],[Quarter]]="n|a","",CONCATENATE("Quarter: ",Table13[[#This Row],[Quarter]]," - ")),IF(Table13[[#This Row],[Grade Level]]="n|a","",CONCATENATE("Grade Level: ",Table13[[#This Row],[Grade Level]]," - ")),IF(Table13[[#This Row],[Delivery Receipt Number]]="n|a","",CONCATENATE("DR No: ",Table13[[#This Row],[Delivery Receipt Number]]," - ")),IF(Table13[[#This Row],[Contract Number]]="n|a","",CONCATENATE("CN: ",Table13[[#This Row],[Contract Number]]," - ")),IF(Table13[[#This Row],[PTR Number]]="n|a","",CONCATENATE("PTR No: ",Table13[[#This Row],[PTR Number]]," - ")),IF(Table13[[#This Row],[Origin]]="n|a","",CONCATENATE("Origin: ",Table13[[#This Row],[Origin]]))) -> - Supplier: - Subject: - Quarter: - Grade Level: - DR No: - CN: - PTR No: - Origin:
D4301: =CONCATENATE(TEXT(Table13[[#This Row],[Date of Acquisition]],"yyyy")," - ", VLOOKUP(Table13[[#This Row],[Article]],'Data Validation'!$A$2:$B$16,2,FALSE)," - ",TEXT(Table13[[#This Row],[Series Number]],"0000")," - ",TEXT(VLOOKUP(Table13[[#This Row],[Location]],'Data Validation'!$A$20:$B$47,2,FALSE),"00")) -> #N/A | Q4301: =Table13[[#This Row],[Unit Value]]*Table13[[#This Row],[Qty | PCount]] -> 0 | R4301: =IF(Table13[[#This Row],[Unit Value]]<=4999,"Low-Value Asset","High-Value Asset") -> Low-Value Asset | AB4301: =CONCATENATE(Table13[[#This Row],[Title]]," - ",IF(Table13[[#This Row],[Supplier]]="n|a","",CONCATENATE("Supplier: ",Table13[[#This Row],[Supplier]]," - ")),IF(Table13[[#This Row],[Subject]]="n|a","",CONCATENATE("Subject: ",Table13[[#This Row],[Subject]]," - ")),IF(Table13[[#This Row],[Quarter]]="n|a","",CONCATENATE("Quarter: ",Table13[[#This Row],[Quarter]]," - ")),IF(Table13[[#This Row],[Grade Level]]="n|a","",CONCATENATE("Grade Level: ",Table13[[#This Row],[Grade Level]]," - ")),IF(Table13[[#This Row],[Delivery Receipt Number]]="n|a","",CONCATENATE("DR No: ",Table13[[#This Row],[Delivery Receipt Number]]," - ")),IF(Table13[[#This Row],[Contract Number]]="n|a","",CONCATENATE("CN: ",Table13[[#This Row],[Contract Number]]," - ")),IF(Table13[[#This Row],[PTR Number]]="n|a","",CONCATENATE("PTR No: ",Table13[[#This Row],[PTR Number]]," - ")),IF(Table13[[#This Row],[Origin]]="n|a","",CONCATENATE("Origin: ",Table13[[#This Row],[Origin]]))) -> - Supplier: - Subject: - Quarter: - Grade Level: - DR No: - CN: - PTR No: - Origin:
D4302: =CONCATENATE(TEXT(Table13[[#This Row],[Date of Acquisition]],"yyyy")," - ", VLOOKUP(Table13[[#This Row],[Article]],'Data Validation'!$A$2:$B$16,2,FALSE)," - ",TEXT(Table13[[#This Row],[Series Number]],"0000")," - ",TEXT(VLOOKUP(Table13[[#This Row],[Location]],'Data Validation'!$A$20:$B$47,2,FALSE),"00")) -> #N/A | Q4302: =Table13[[#This Row],[Unit Value]]*Table13[[#This Row],[Qty | PCount]] -> 0 | R4302: =IF(Table13[[#This Row],[Unit Value]]<=4999,"Low-Value Asset","High-Value Asset") -> Low-Value Asset | AB4302: =CONCATENATE(Table13[[#This Row],[Title]]," - ",IF(Table13[[#This Row],[Supplier]]="n|a","",CONCATENATE("Supplier: ",Table13[[#This Row],[Supplier]]," - ")),IF(Table13[[#This Row],[Subject]]="n|a","",CONCATENATE("Subject: ",Table13[[#This Row],[Subject]]," - ")),IF(Table13[[#This Row],[Quarter]]="n|a","",CONCATENATE("Quarter: ",Table13[[#This Row],[Quarter]]," - ")),IF(Table13[[#This Row],[Grade Level]]="n|a","",CONCATENATE("Grade Level: ",Table13[[#This Row],[Grade Level]]," - ")),IF(Table13[[#This Row],[Delivery Receipt Number]]="n|a","",CONCATENATE("DR No: ",Table13[[#This Row],[Delivery Receipt Number]]," - ")),IF(Table13[[#This Row],[Contract Number]]="n|a","",CONCATENATE("CN: ",Table13[[#This Row],[Contract Number]]," - ")),IF(Table13[[#This Row],[PTR Number]]="n|a","",CONCATENATE("PTR No: ",Table13[[#This Row],[PTR Number]]," - ")),IF(Table13[[#This Row],[Origin]]="n|a","",CONCATENATE("Origin: ",Table13[[#This Row],[Origin]]))) -> - Supplier: - Subject: - Quarter: - Grade Level: - DR No: - CN: - PTR No: - Origin:
D4303: =CONCATENATE(TEXT(Table13[[#This Row],[Date of Acquisition]],"yyyy")," - ", VLOOKUP(Table13[[#This Row],[Article]],'Data Validation'!$A$2:$B$16,2,FALSE)," - ",TEXT(Table13[[#This Row],[Series Number]],"0000")," - ",TEXT(VLOOKUP(Table13[[#This Row],[Location]],'Data Validation'!$A$20:$B$47,2,FALSE),"00")) -> #N/A | Q4303: =Table13[[#This Row],[Unit Value]]*Table13[[#This Row],[Qty | PCount]] -> 0 | R4303: =IF(Table13[[#This Row],[Unit Value]]<=4999,"Low-Value Asset","High-Value Asset") -> Low-Value Asset | AB4303: =CONCATENATE(Table13[[#This Row],[Title]]," - ",IF(Table13[[#This Row],[Supplier]]="n|a","",CONCATENATE("Supplier: ",Table13[[#This Row],[Supplier]]," - ")),IF(Table13[[#This Row],[Subject]]="n|a","",CONCATENATE("Subject: ",Table13[[#This Row],[Subject]]," - ")),IF(Table13[[#This Row],[Quarter]]="n|a","",CONCATENATE("Quarter: ",Table13[[#This Row],[Quarter]]," - ")),IF(Table13[[#This Row],[Grade Level]]="n|a","",CONCATENATE("Grade Level: ",Table13[[#This Row],[Grade Level]]," - ")),IF(Table13[[#This Row],[Delivery Receipt Number]]="n|a","",CONCATENATE("DR No: ",Table13[[#This Row],[Delivery Receipt Number]]," - ")),IF(Table13[[#This Row],[Contract Number]]="n|a","",CONCATENATE("CN: ",Table13[[#This Row],[Contract Number]]," - ")),IF(Table13[[#This Row],[PTR Number]]="n|a","",CONCATENATE("PTR No: ",Table13[[#This Row],[PTR Number]]," - ")),IF(Table13[[#This Row],[Origin]]="n|a","",CONCATENATE("Origin: ",Table13[[#This Row],[Origin]]))) -> - Supplier: - Subject: - Quarter: - Grade Level: - DR No: - CN: - PTR No: - Origin:
D4304: =CONCATENATE(TEXT(Table13[[#This Row],[Date of Acquisition]],"yyyy")," - ", VLOOKUP(Table13[[#This Row],[Article]],'Data Validation'!$A$2:$B$16,2,FALSE)," - ",TEXT(Table13[[#This Row],[Series Number]],"0000")," - ",TEXT(VLOOKUP(Table13[[#This Row],[Location]],'Data Validation'!$A$20:$B$47,2,FALSE),"00")) -> #N/A | Q4304: =Table13[[#This Row],[Unit Value]]*Table13[[#This Row],[Qty | PCount]] -> 0 | R4304: =IF(Table13[[#This Row],[Unit Value]]<=4999,"Low-Value Asset","High-Value Asset") -> Low-Value Asset | AB4304: =CONCATENATE(Table13[[#This Row],[Title]]," - ",IF(Table13[[#This Row],[Supplier]]="n|a","",CONCATENATE("Supplier: ",Table13[[#This Row],[Supplier]]," - ")),IF(Table13[[#This Row],[Subject]]="n|a","",CONCATENATE("Subject: ",Table13[[#This Row],[Subject]]," - ")),IF(Table13[[#This Row],[Quarter]]="n|a","",CONCATENATE("Quarter: ",Table13[[#This Row],[Quarter]]," - ")),IF(Table13[[#This Row],[Grade Level]]="n|a","",CONCATENATE("Grade Level: ",Table13[[#This Row],[Grade Level]]," - ")),IF(Table13[[#This Row],[Delivery Receipt Number]]="n|a","",CONCATENATE("DR No: ",Table13[[#This Row],[Delivery Receipt Number]]," - ")),IF(Table13[[#This Row],[Contract Number]]="n|a","",CONCATENATE("CN: ",Table13[[#This Row],[Contract Number]]," - ")),IF(Table13[[#This Row],[PTR Number]]="n|a","",CONCATENATE("PTR No: ",Table13[[#This Row],[PTR Number]]," - ")),IF(Table13[[#This Row],[Origin]]="n|a","",CONCATENATE("Origin: ",Table13[[#This Row],[Origin]]))) -> - Supplier: - Subject: - Quarter: - Grade Level: - DR No: - CN: - PTR No: - Origin:
D4305: =CONCATENATE(TEXT(Table13[[#This Row],[Date of Acquisition]],"yyyy")," - ", VLOOKUP(Table13[[#This Row],[Article]],'Data Validation'!$A$2:$B$16,2,FALSE)," - ",TEXT(Table13[[#This Row],[Series Number]],"0000")," - ",TEXT(VLOOKUP(Table13[[#This Row],[Location]],'Data Validation'!$A$20:$B$47,2,FALSE),"00")) -> #N/A | Q4305: =Table13[[#This Row],[Unit Value]]*Table13[[#This Row],[Qty | PCount]] -> 0 | R4305: =IF(Table13[[#This Row],[Unit Value]]<=4999,"Low-Value Asset","High-Value Asset") -> Low-Value Asset | AB4305: =CONCATENATE(Table13[[#This Row],[Title]]," - ",IF(Table13[[#This Row],[Supplier]]="n|a","",CONCATENATE("Supplier: ",Table13[[#This Row],[Supplier]]," - ")),IF(Table13[[#This Row],[Subject]]="n|a","",CONCATENATE("Subject: ",Table13[[#This Row],[Subject]]," - ")),IF(Table13[[#This Row],[Quarter]]="n|a","",CONCATENATE("Quarter: ",Table13[[#This Row],[Quarter]]," - ")),IF(Table13[[#This Row],[Grade Level]]="n|a","",CONCATENATE("Grade Level: ",Table13[[#This Row],[Grade Level]]," - ")),IF(Table13[[#This Row],[Delivery Receipt Number]]="n|a","",CONCATENATE("DR No: ",Table13[[#This Row],[Delivery Receipt Number]]," - ")),IF(Table13[[#This Row],[Contract Number]]="n|a","",CONCATENATE("CN: ",Table13[[#This Row],[Contract Number]]," - ")),IF(Table13[[#This Row],[PTR Number]]="n|a","",CONCATENATE("PTR No: ",Table13[[#This Row],[PTR Number]]," - ")),IF(Table13[[#This Row],[Origin]]="n|a","",CONCATENATE("Origin: ",Table13[[#This Row],[Origin]]))) -> - Supplier: - Subject: - Quarter: - Grade Level: - DR No: - CN: - PTR No: - Origin:
D4306: 2021 - 07 - 00 - 0000 - 13 | Q4306: 220.2 | R4306: Low-Value Asset | AB4306: MODULE 6: Sequence and Working Backward - Supplier: Rex Book Store Inc. - Subject: Mathematics - Quarter: 3 - Grade Level: Grade 5 - DR No: - - CN: 2021-BLR2(009-018)-BIV-CB003-C013 - PTR No: PTR-REX-21-11-0061 - Origin: Central Office
D4307: 2021 - 07 - 00 - 0000 - 13 | Q4307: 220.2 | R4307: Low-Value Asset | AB4307: MODULE 6: Sequence and Working Backward - Supplier: Rex Book Store Inc. - Subject: Mathematics - Quarter: 3 - Grade Level: Grade 5 - DR No: - - CN: 2021-BLR2(009-018)-BIV-CB003-C013 - PTR No: PTR-REX-21-11-0061 - Origin: Central Office
D4308: =CONCATENATE(TEXT(Table13[[#This Row],[Date of Acquisition]],"yyyy")," - ", VLOOKUP(Table13[[#This Row],[Article]],'Data Validation'!$A$2:$B$16,2,FALSE)," - ",TEXT(Table13[[#This Row],[Series Number]],"0000")," - ",TEXT(VLOOKUP(Table13[[#This Row],[Location]],'Data Validation'!$A$20:$B$47,2,FALSE),"00")) -> #N/A | Q4308: =Table13[[#This Row],[Unit Value]]*Table13[[#This Row],[Qty | PCount]] -> 0 | R4308: =IF(Table13[[#This Row],[Unit Value]]<=4999,"Low-Value Asset","High-Value Asset") -> Low-Value Asset | AB4308: =CONCATENATE(Table13[[#This Row],[Title]]," - ",IF(Table13[[#This Row],[Supplier]]="n|a","",CONCATENATE("Supplier: ",Table13[[#This Row],[Supplier]]," - ")),IF(Table13[[#This Row],[Subject]]="n|a","",CONCATENATE("Subject: ",Table13[[#This Row],[Subject]]," - ")),IF(Table13[[#This Row],[Quarter]]="n|a","",CONCATENATE("Quarter: ",Table13[[#This Row],[Quarter]]," - ")),IF(Table13[[#This Row],[Grade Level]]="n|a","",CONCATENATE("Grade Level: ",Table13[[#This Row],[Grade Level]]," - ")),IF(Table13[[#This Row],[Delivery Receipt Number]]="n|a","",CONCATENATE("DR No: ",Table13[[#This Row],[Delivery Receipt Number]]," - ")),IF(Table13[[#This Row],[Contract Number]]="n|a","",CONCATENATE("CN: ",Table13[[#This Row],[Contract Number]]," - ")),IF(Table13[[#This Row],[PTR Number]]="n|a","",CONCATENATE("PTR No: ",Table13[[#This Row],[PTR Number]]," - ")),IF(Table13[[#This Row],[Origin]]="n|a","",CONCATENATE("Origin: ",Table13[[#This Row],[Origin]]))) -> - Supplier: - Subject: - Quarter: - Grade Level: - DR No: - CN: - PTR No: - Origin:
D4309: =CONCATENATE(TEXT(Table13[[#This Row],[Date of Acquisition]],"yyyy")," - ", VLOOKUP(Table13[[#This Row],[Article]],'Data Validation'!$A$2:$B$16,2,FALSE)," - ",TEXT(Table13[[#This Row],[Series Number]],"0000")," - ",TEXT(VLOOKUP(Table13[[#This Row],[Location]],'Data Validation'!$A$20:$B$47,2,FALSE),"00")) -> #N/A | Q4309: =Table13[[#This Row],[Unit Value]]*Table13[[#This Row],[Qty | PCount]] -> 0 | R4309: =IF(Table13[[#This Row],[Unit Value]]<=4999,"Low-Value Asset","High-Value Asset") -> Low-Value Asset | AB4309: =CONCATENATE(Table13[[#This Row],[Title]]," - ",IF(Table13[[#This Row],[Supplier]]="n|a","",CONCATENATE("Supplier: ",Table13[[#This Row],[Supplier]]," - ")),IF(Table13[[#This Row],[Subject]]="n|a","",CONCATENATE("Subject: ",Table13[[#This Row],[Subject]]," - ")),IF(Table13[[#This Row],[Quarter]]="n|a","",CONCATENATE("Quarter: ",Table13[[#This Row],[Quarter]]," - ")),IF(Table13[[#This Row],[Grade Level]]="n|a","",CONCATENATE("Grade Level: ",Table13[[#This Row],[Grade Level]]," - ")),IF(Table13[[#This Row],[Delivery Receipt Number]]="n|a","",CONCATENATE("DR No: ",Table13[[#This Row],[Delivery Receipt Number]]," - ")),IF(Table13[[#This Row],[Contract Number]]="n|a","",CONCATENATE("CN: ",Table13[[#This Row],[Contract Number]]," - ")),IF(Table13[[#This Row],[PTR Number]]="n|a","",CONCATENATE("PTR No: ",Table13[[#This Row],[PTR Number]]," - ")),IF(Table13[[#This Row],[Origin]]="n|a","",CONCATENATE("Origin: ",Table13[[#This Row],[Origin]]))) -> - Supplier: - Subject: - Quarter: - Grade Level: - DR No: - CN: - PTR No: - Origin:
D4310: =CONCATENATE(TEXT(Table13[[#This Row],[Date of Acquisition]],"yyyy")," - ", VLOOKUP(Table13[[#This Row],[Article]],'Data Validation'!$A$2:$B$16,2,FALSE)," - ",TEXT(Table13[[#This Row],[Series Number]],"0000")," - ",TEXT(VLOOKUP(Table13[[#This Row],[Location]],'Data Validation'!$A$20:$B$47,2,FALSE),"00")) -> #N/A | Q4310: =Table13[[#This Row],[Unit Value]]*Table13[[#This Row],[Qty | PCount]] -> 0 | R4310: =IF(Table13[[#This Row],[Unit Value]]<=4999,"Low-Value Asset","High-Value Asset") -> Low-Value Asset | AB4310: =CONCATENATE(Table13[[#This Row],[Title]]," - ",IF(Table13[[#This Row],[Supplier]]="n|a","",CONCATENATE("Supplier: ",Table13[[#This Row],[Supplier]]," - ")),IF(Table13[[#This Row],[Subject]]="n|a","",CONCATENATE("Subject: ",Table13[[#This Row],[Subject]]," - ")),IF(Table13[[#This Row],[Quarter]]="n|a","",CONCATENATE("Quarter: ",Table13[[#This Row],[Quarter]]," - ")),IF(Table13[[#This Row],[Grade Level]]="n|a","",CONCATENATE("Grade Level: ",Table13[[#This Row],[Grade Level]]," - ")),IF(Table13[[#This Row],[Delivery Receipt Number]]="n|a","",CONCATENATE("DR No: ",Table13[[#This Row],[Delivery Receipt Number]]," - ")),IF(Table13[[#This Row],[Contract Number]]="n|a","",CONCATENATE("CN: ",Table13[[#This Row],[Contract Number]]," - ")),IF(Table13[[#This Row],[PTR Number]]="n|a","",CONCATENATE("PTR No: ",Table13[[#This Row],[PTR Number]]," - ")),IF(Table13[[#This Row],[Origin]]="n|a","",CONCATENATE("Origin: ",Table13[[#This Row],[Origin]]))) -> - Supplier: - Subject: - Quarter: - Grade Level: - DR No: - CN: - PTR No: - Origin:
D4311: =CONCATENATE(TEXT(Table13[[#This Row],[Date of Acquisition]],"yyyy")," - ", VLOOKUP(Table13[[#This Row],[Article]],'Data Validation'!$A$2:$B$16,2,FALSE)," - ",TEXT(Table13[[#This Row],[Series Number]],"0000")," - ",TEXT(VLOOKUP(Table13[[#This Row],[Location]],'Data Validation'!$A$20:$B$47,2,FALSE),"00")) -> #N/A | Q4311: =Table13[[#This Row],[Unit Value]]*Table13[[#This Row],[Qty | PCount]] -> 0 | R4311: =IF(Table13[[#This Row],[Unit Value]]<=4999,"Low-Value Asset","High-Value Asset") -> Low-Value Asset | AB4311: =CONCATENATE(Table13[[#This Row],[Title]]," - ",IF(Table13[[#This Row],[Supplier]]="n|a","",CONCATENATE("Supplier: ",Table13[[#This Row],[Supplier]]," - ")),IF(Table13[[#This Row],[Subject]]="n|a","",CONCATENATE("Subject: ",Table13[[#This Row],[Subject]]," - ")),IF(Table13[[#This Row],[Quarter]]="n|a","",CONCATENATE("Quarter: ",Table13[[#This Row],[Quarter]]," - ")),IF(Table13[[#This Row],[Grade Level]]="n|a","",CONCATENATE("Grade Level: ",Table13[[#This Row],[Grade Level]]," - ")),IF(Table13[[#This Row],[Delivery Receipt Number]]="n|a","",CONCATENATE("DR No: ",Table13[[#This Row],[Delivery Receipt Number]]," - ")),IF(Table13[[#This Row],[Contract Number]]="n|a","",CONCATENATE("CN: ",Table13[[#This Row],[Contract Number]]," - ")),IF(Table13[[#This Row],[PTR Number]]="n|a","",CONCATENATE("PTR No: ",Table13[[#This Row],[PTR Number]]," - ")),IF(Table13[[#This Row],[Origin]]="n|a","",CONCATENATE("Origin: ",Table13[[#This Row],[Origin]]))) -> - Supplier: - Subject: - Quarter: - Grade Level: - DR No: - CN: - PTR No: - Origin:
D4312: =CONCATENATE(TEXT(Table13[[#This Row],[Date of Acquisition]],"yyyy")," - ", VLOOKUP(Table13[[#This Row],[Article]],'Data Validation'!$A$2:$B$16,2,FALSE)," - ",TEXT(Table13[[#This Row],[Series Number]],"0000")," - ",TEXT(VLOOKUP(Table13[[#This Row],[Location]],'Data Validation'!$A$20:$B$47,2,FALSE),"00")) -> #N/A | Q4312: =Table13[[#This Row],[Unit Value]]*Table13[[#This Row],[Qty | PCount]] -> 0 | R4312: =IF(Table13[[#This Row],[Unit Value]]<=4999,"Low-Value Asset","High-Value Asset") -> Low-Value Asset | AB4312: =CONCATENATE(Table13[[#This Row],[Title]]," - ",IF(Table13[[#This Row],[Supplier]]="n|a","",CONCATENATE("Supplier: ",Table13[[#This Row],[Supplier]]," - ")),IF(Table13[[#This Row],[Subject]]="n|a","",CONCATENATE("Subject: ",Table13[[#This Row],[Subject]]," - ")),IF(Table13[[#This Row],[Quarter]]="n|a","",CONCATENATE("Quarter: ",Table13[[#This Row],[Quarter]]," - ")),IF(Table13[[#This Row],[Grade Level]]="n|a","",CONCATENATE("Grade Level: ",Table13[[#This Row],[Grade Level]]," - ")),IF(Table13[[#This Row],[Delivery Receipt Number]]="n|a","",CONCATENATE("DR No: ",Table13[[#This Row],[Delivery Receipt Number]]," - ")),IF(Table13[[#This Row],[Contract Number]]="n|a","",CONCATENATE("CN: ",Table13[[#This Row],[Contract Number]]," - ")),IF(Table13[[#This Row],[PTR Number]]="n|a","",CONCATENATE("PTR No: ",Table13[[#This Row],[PTR Number]]," - ")),IF(Table13[[#This Row],[Origin]]="n|a","",CONCATENATE("Origin: ",Table13[[#This Row],[Origin]]))) -> - Supplier: - Subject: - Quarter: - Grade Level: - DR No: - CN: - PTR No: - Origin:
D4313: =CONCATENATE(TEXT(Table13[[#This Row],[Date of Acquisition]],"yyyy")," - ", VLOOKUP(Table13[[#This Row],[Article]],'Data Validation'!$A$2:$B$16,2,FALSE)," - ",TEXT(Table13[[#This Row],[Series Number]],"0000")," - ",TEXT(VLOOKUP(Table13[[#This Row],[Location]],'Data Validation'!$A$20:$B$47,2,FALSE),"00")) -> #N/A | Q4313: =Table13[[#This Row],[Unit Value]]*Table13[[#This Row],[Qty | PCount]] -> 0 | R4313: =IF(Table13[[#This Row],[Unit Value]]<=4999,"Low-Value Asset","High-Value Asset") -> Low-Value Asset | AB4313: =CONCATENATE(Table13[[#This Row],[Title]]," - ",IF(Table13[[#This Row],[Supplier]]="n|a","",CONCATENATE("Supplier: ",Table13[[#This Row],[Supplier]]," - ")),IF(Table13[[#This Row],[Subject]]="n|a","",CONCATENATE("Subject: ",Table13[[#This Row],[Subject]]," - ")),IF(Table13[[#This Row],[Quarter]]="n|a","",CONCATENATE("Quarter: ",Table13[[#This Row],[Quarter]]," - ")),IF(Table13[[#This Row],[Grade Level]]="n|a","",CONCATENATE("Grade Level: ",Table13[[#This Row],[Grade Level]]," - ")),IF(Table13[[#This Row],[Delivery Receipt Number]]="n|a","",CONCATENATE("DR No: ",Table13[[#This Row],[Delivery Receipt Number]]," - ")),IF(Table13[[#This Row],[Contract Number]]="n|a","",CONCATENATE("CN: ",Table13[[#This Row],[Contract Number]]," - ")),IF(Table13[[#This Row],[PTR Number]]="n|a","",CONCATENATE("PTR No: ",Table13[[#This Row],[PTR Number]]," - ")),IF(Table13[[#This Row],[Origin]]="n|a","",CONCATENATE("Origin: ",Table13[[#This Row],[Origin]]))) -> - Supplier: - Subject: - Quarter: - Grade Level: - DR No: - CN: - PTR No: - Origin:
D4314: 2021 - 07 - 00 - 0000 - 12 | Q4314: 220.2 | R4314: Low-Value Asset | AB4314: MODULE 6: Sequence and Working Backward - Supplier: Rex Book Store Inc. - Subject: Mathematics - Quarter: 3 - Grade Level: Grade 5 - DR No: - - CN: 2021-BLR2(009-018)-BIV-CB003-C013 - PTR No: PTR-REX-21-11-0061 - Origin: Central Office
D4315: 2021 - 07 - 00 - 0000 - 12 | Q4315: 220.2 | R4315: Low-Value Asset | AB4315: MODULE 6: Sequence and Working Backward - Supplier: Rex Book Store Inc. - Subject: Mathematics - Quarter: 3 - Grade Level: Grade 5 - DR No: - - CN: 2021-BLR2(009-018)-BIV-CB003-C013 - PTR No: PTR-REX-21-11-0061 - Origin: Central Office
