Workbook

Sheet Sheet2
H1: {=_xlfn.XLOOKUP(D5,Table1[Property Number],CONCATENATE("Fund Source: ",Table1[Source of Fund]))} -> #N/A | Q1: {=_xlfn.XLOOKUP(M5,Table1[Property Number],CONCATENATE("Fund Source: ",Table1[Source of Fund]))} -> #N/A
B4: ICS NUMBER | C4: : | D4: =_xlfn.XLOOKUP(D5,Table1[Property Number],Table1[ICS Number]) -> #N/A | K4: ICS NUMBER | L4: : | M4: =_xlfn.XLOOKUP(M5,Table1[Property Number],Table1[ICS Number]) -> #N/A
B5: PROPERTY NUMBER | C5: : | D5: SPHV - 2024 - 05 - 03 - 0004 - 03A | K5: PROPERTY NUMBER | L5: : | M5: SPHV - 2024 - 05 - 03 - 0005 - 02A
B6: ASSET CLASSIFICATION | C6: : | D6: =_xlfn.XLOOKUP(D5,Table1[Property Number],Table1[Article]) -> #N/A | K6: ASSET CLASSIFICATION | L6: : | M6: =_xlfn.XLOOKUP(M5,Table1[Property Number],Table1[Article]) -> #N/A
B7: ITEM|BRAND|MODEL | C7: : | D7: {=_xlfn.XLOOKUP(D5,Table1[Property Number],CONCATENATE(IF(Table1[Brand]="n|a"," ",Table1[Brand])," | ",IF(Table1[Model]="n|a"," ",Table1[Model])))} -> #N/A | K7: ITEM|BRAND|MODEL | L7: : | M7: {=_xlfn.XLOOKUP(M5,Table1[Property Number],CONCATENATE(IF(Table1[Brand]="n|a"," ",Table1[Brand])," | ",IF(Table1[Model]="n|a"," ",Table1[Model])))} -> #N/A
B8: SERIAL NUMBER | C8: : | D8: =_xlfn.XLOOKUP(D5,Table1[Property Number],Table1[Serial Number]) -> #N/A | K8: SERIAL NUMBER | L8: : | M8: =_xlfn.XLOOKUP(M5,Table1[Property Number],Table1[Serial Number]) -> #N/A
B9: ACQUISITION COST | C9: : | D9: =_xlfn.XLOOKUP(D5,Table1[Property Number],Table1[Total Value]) -> #N/A | E9: ACQUISITION DATE | F9: : | G9: =TEXT(_xlfn.XLOOKUP(D5,Table1[Property Number],Table1[Date of Renewal]),"mm.dd.yyyy") -> #N/A | K9: ACQUISITION COST | L9: : | M9: =_xlfn.XLOOKUP(M5,Table1[Property Number],Table1[Total Value]) -> #N/A | N9: ACQUISITION DATE | O9: : | P9: =_xlfn.XLOOKUP(M5,Table1[Property Number],Table1[Date of Renewal]) -> #N/A
B10: PERSON ACCOUNTABLE | C10: : | D10: =_xlfn.XLOOKUP(D5,Table1[Property Number],Table1[Accountable Person]) -> #N/A | K10: PERSON ACCOUNTABLE | L10: : | M10: =_xlfn.XLOOKUP(M5,Table1[Property Number],Table1[Accountable Person]) -> #N/A
B11: VALIDATION | SIGNATURE | C11: : | K11: VALIDATION | SIGNATURE | L11: :
B12: "Removing or tampering of this sticker is punishable by law" | K12: "Removing or tampering of this sticker is punishable by law"
H16: {=_xlfn.XLOOKUP(D20,Table1[Property Number],CONCATENATE("Fund Source: ",Table1[Source of Fund]))} -> #N/A | Q16: {=_xlfn.XLOOKUP(M20,Table1[Property Number],CONCATENATE("Fund Source: ",Table1[Source of Fund]))} -> #N/A
B19: ICS NUMBER | C19: : | D19: =_xlfn.XLOOKUP(D20,Table1[Property Number],Table1[ICS Number]) -> #N/A | K19: ICS NUMBER | L19: : | M19: =_xlfn.XLOOKUP(M20,Table1[Property Number],Table1[ICS Number]) -> #N/A
B20: PROPERTY NUMBER | C20: : | D20: SPHV - 2024 - 05 - 03 - 0006 - 01A | K20: PROPERTY NUMBER | L20: : | M20: SPHV - 2023 - 05 - 03 - 0035 - 01A
B21: ASSET CLASSIFICATION | C21: : | D21: =_xlfn.XLOOKUP(D20,Table1[Property Number],Table1[Article]) -> #N/A | K21: ASSET CLASSIFICATION | L21: : | M21: =_xlfn.XLOOKUP(M20,Table1[Property Number],Table1[Article]) -> #N/A
B22: ITEM|BRAND|MODEL | C22: : | D22: {=_xlfn.XLOOKUP(D20,Table1[Property Number],CONCATENATE(IF(Table1[Brand]="n|a"," ",Table1[Brand])," | ",IF(Table1[Model]="n|a"," ",Table1[Model])))} -> #N/A | K22: ITEM|BRAND|MODEL | L22: : | M22: {=_xlfn.XLOOKUP(M20,Table1[Property Number],CONCATENATE(IF(Table1[Brand]="n|a"," ",Table1[Brand])," | ",IF(Table1[Model]="n|a"," ",Table1[Model])))} -> #N/A
B23: SERIAL NUMBER | C23: : | D23: =_xlfn.XLOOKUP(D20,Table1[Property Number],Table1[Serial Number]) -> #N/A | K23: SERIAL NUMBER | L23: : | M23: =_xlfn.XLOOKUP(M20,Table1[Property Number],Table1[Serial Number]) -> #N/A
B24: ACQUISITION COST | C24: : | D24: =_xlfn.XLOOKUP(D20,Table1[Property Number],Table1[Total Value]) -> #N/A | E24: ACQUISITION DATE | F24: : | G24: =_xlfn.XLOOKUP(D20,Table1[Property Number],Table1[Date of Renewal]) -> #N/A | K24: ACQUISITION COST | L24: : | M24: =_xlfn.XLOOKUP(M20,Table1[Property Number],Table1[Total Value]) -> #N/A | N24: ACQUISITION DATE | O24: : | P24: =_xlfn.XLOOKUP(M20,Table1[Property Number],Table1[Date of Acquisition]) -> #N/A
B25: PERSON ACCOUNTABLE | C25: : | D25: =_xlfn.XLOOKUP(D20,Table1[Property Number],Table1[Accountable Person]) -> #N/A | K25: PERSON ACCOUNTABLE | L25: : | M25: =_xlfn.XLOOKUP(M20,Table1[Property Number],Table1[Accountable Person]) -> #N/A
B26: VALIDATION | SIGNATURE | C26: : | K26: VALIDATION | SIGNATURE | L26: :
B27: "Removing or tampering of this sticker is punishable by law" | K27: "Removing or tampering of this sticker is punishable by law"

Sheet List
A1: ICS Number | B1: Series Number | C1: Article | D1: Property Number | E1: Type of Properties | F1: Brand | G1: Model | H1: Serial Number | I1: Processor | J1: RAM | K1: Storage | L1: Color | M1: Other Description | N1: Unit of Measure | O1: Unit Value | P1: Total Value | Q1: Value Category | R1: Qty | PCard | S1: Qty | PCount | T1: S|O Qty | U1: S|O Value | V1: Date of Acquisition | W1: Location | X1: Accountable Person | Y1: Position | Z1: Source of Fund | AA1: Full Specifications | AB1: Issued ICS | AC1: Date of Renewal
A2: ICS2026 - 01 - 0104 | B2: 46 | C2: ICT Equipment | D2: SPHV - 2022 - 05 - 03 - 0046 - 03B | E2: Laptop | F2: COBY | G2: NBPC 2168 | H2: RDPBMNBPC2168202201001528 | I2: AMD Ryzen 5 | J2: 8 GB DDR4 | K2: 1 TB SSD | L2: Blue | M2: Laptop with Bag | N2: set | O2: 42167.91 | P2: 42167.91 | Q2: High-Value Asset | R2: 1 | S2: 1 | T2: 0 | U2: 0 | V2: 44799 | W2: 003B - School Health and Nutrition Unit | X2: Chrisabelle C. Quebec | Y2: Technical Assistant I - SBFP / WINS | Z2: Central Office | AA2: Laptop with Bag - Brand: COBY - Model: NBPC 2168 - SN: RDPBMNBPC2168202201001528 - Processor: AMD Ryzen 5 - RAM: 8 GB DDR4 - Storage: 1 TB SSD - Color: Blue | AB2: Yes | AC2: 46058

Sheet Sheet1
A1: {=_xlfn.UNIQUE(Table1[ICS Number])} -> ICS2026 - 01 - 0104 | D1: {=_xlfn.UNIQUE(Table1[Property Number])} -> SPHV - 2022 - 05 - 03 - 0046 - 03B
A2: 0 | D2: 0
I9: Row Labels | J9: Sum of Total Value
I10: 004 - Ladislao Diwa Elementary School | J10: 25450
I11: 005 - Julian R. Felipe Elementary School | J11: 20850
I12: 006 - Manuel S. Rojas Elementary School | J12: 16250
I13: 007 - Sta. Cruz Elementary School | J13: 16250
I14: 008 - Ovidio Dela Rosa Elementary School | J14: 16250
I15: 009 - Dalahican Elementary School | J15: 16250
I16: 010 - San Lorenzo Ruiz Elementary School | J16: 16250
I17: 011 - Garita Elementary School | J17: 11650
I18: 012 - Sangley Elementary School | J18: 11650
I19: 013 - Porta Vaga Elementary School | J19: 11650
I20: 014 - Bagumbuhay Elementary School | J20: 11650
I21: 015 - Estansuela Elementary School | J21: 11650
I22: (blank)
I23: 016 - Cavite National High School - JHS | J23: 4600
I24: 017 - Sangley Point National High School - JHS | J24: 4600
I25: 019 - Sangley Point National High School - SHS | J25: 4600
I26: 018 - Cavite National High School - SHS | J26: 4600
I27: 020 - Cavite City National Science High School | J27: 4600
I28: 003B - School Health and Nutrition Unit | J28: 4600
I29: Grand Total | J29: 213400

Sheet Printer
B1: Appendix 59
B2: INVENTORY CUSTODIAN SLIP
B5: Entity Name: | D5: DepED | I5: ICS Number: | J5: ICS2026 - 01 - 0104
B6: Fund Cluster: | D6: 1101101 | N6: =CHOOSECOLS(FILTER(Table13,Table13[ICS Number]=J5),2)
A8: QTY | C8: UNIT | E8: AMOUNT | H8: DESCRIPTION | J8: INVENTORY ITEM NO. | K8: ESTIMATED USEFUL LIFE
E9: UNIT COST | F9: TOTAL COST
B10: =_xlfn.IFNA(_xlfn.XLOOKUP(J10,Table1[Property Number],Table1[Qty | PCount]),"-") -> 1 | C10: =_xlfn.IFNA(_xlfn.XLOOKUP(J10,Table1[Property Number],Table1[Unit of Measure]),"-") -> set | E10: =_xlfn.IFNA(_xlfn.XLOOKUP(J10,Table1[Property Number],Table1[Unit Value]),"-") -> 42167.91 | F10: =IFERROR(B10*E10,0) -> 42167.91 | I10: =_xlfn.IFNA(CONCATENATE(_xlfn.XLOOKUP(J10,Table1[Property Number], Table1[Full Specifications])," - Acquisition Date: ",TEXT(_xlfn.XLOOKUP(J10,Table1[Property Number], Table1[Date of Acquisition]),"mmmm dd, yyyy")),"-") -> Laptop with Bag - Brand: COBY - Model: NBPC 2168 - SN: RDPBMNBPC2168202201001528 - Processor: AMD Ryzen 5 - RAM: 8 GB DDR4 - Storage: 1 TB SSD - Color: Blue - Acquisition Date: August 26, 2022 | J10: =_xlfn.XLOOKUP(J5,Table1[ICS Number],Table1[Property Number]) -> SPHV - 2022 - 05 - 03 - 0046 - 03B | K10: =IF(N10="","-","2 Years") -> 2 Years | N10: {=_xlfn.CHOOSECOLS(_xlfn._xlws.FILTER(Table1[],Table1[ICS Number]=Printer!J5),4)} -> SPHV - 2022 - 05 - 03 - 0046 - 03B
I11: x ---------- N O T H I N G F O L L O W S ---------- x
B12: =_xlfn.IFNA(_xlfn.XLOOKUP(J12,Table1[Property Number],Table1[Qty | PCount]),"-") -> - | C12: =_xlfn.IFNA(_xlfn.XLOOKUP(J12,Table1[Property Number],Table1[Unit of Measure]),"-") -> - | E12: =_xlfn.IFNA(_xlfn.XLOOKUP(J12,Table1[Property Number],Table1[Unit Value]),"-") -> - | F12: =IFERROR(B12*E12,0) -> 0 | I12: =_xlfn.IFNA(CONCATENATE(_xlfn.XLOOKUP(J12,Table1[Property Number], Table1[Full Specifications])," - Acquisition Date: ",TEXT(_xlfn.XLOOKUP(J12,Table1[Property Number], Table1[Date of Acquisition]),"mmmm dd, yyyy")),"-") -> - | J12: =N12 -> 0 | K12: =IF(N12="","-","2 Years") -> -
B13: =_xlfn.IFNA(_xlfn.XLOOKUP(J13,Table1[Property Number],Table1[Qty | PCount]),"-") -> - | C13: =_xlfn.IFNA(_xlfn.XLOOKUP(J13,Table1[Property Number],Table1[Unit of Measure]),"-") -> - | E13: =_xlfn.IFNA(_xlfn.XLOOKUP(J13,Table1[Property Number],Table1[Unit Value]),"-") -> - | F13: =IFERROR(B13*E13,0) -> 0 | I13: =_xlfn.IFNA(CONCATENATE(_xlfn.XLOOKUP(J13,Table1[Property Number], Table1[Full Specifications])," - Acquisition Date: ",TEXT(_xlfn.XLOOKUP(J13,Table1[Property Number], Table1[Date of Acquisition]),"mmmm dd, yyyy")),"-") -> - | J13: =N13 -> 0 | K13: =IF(N13="","-","2 Years") -> -
B14: =_xlfn.IFNA(_xlfn.XLOOKUP(J14,Table1[Property Number],Table1[Qty | PCount]),"-") -> - | C14: =_xlfn.IFNA(_xlfn.XLOOKUP(J14,Table1[Property Number],Table1[Unit of Measure]),"-") -> - | E14: =_xlfn.IFNA(_xlfn.XLOOKUP(J14,Table1[Property Number],Table1[Unit Value]),"-") -> - | F14: =IFERROR(B14*E14,0) -> 0 | I14: =_xlfn.IFNA(CONCATENATE(_xlfn.XLOOKUP(J14,Table1[Property Number], Table1[Full Specifications])," - Acquisition Date: ",TEXT(_xlfn.XLOOKUP(J14,Table1[Property Number], Table1[Date of Acquisition]),"mmmm dd, yyyy")),"-") -> - | J14: =N14 -> 0 | K14: =IF(N14="","-","2 Years") -> -
B15: =_xlfn.IFNA(_xlfn.XLOOKUP(J15,Table1[Property Number],Table1[Qty | PCount]),"-") -> - | C15: =_xlfn.IFNA(_xlfn.XLOOKUP(J15,Table1[Property Number],Table1[Unit of Measure]),"-") -> - | E15: =_xlfn.IFNA(_xlfn.XLOOKUP(J15,Table1[Property Number],Table1[Unit Value]),"-") -> - | F15: =IFERROR(B15*E15,0) -> 0 | I15: =_xlfn.IFNA(CONCATENATE(_xlfn.XLOOKUP(J15,Table1[Property Number], Table1[Full Specifications])," - Acquisition Date: ",TEXT(_xlfn.XLOOKUP(J15,Table1[Property Number], Table1[Date of Acquisition]),"mmmm dd, yyyy")),"-") -> - | J15: =N15 -> 0 | K15: =IF(N15="","-","2 Years") -> -
B16: =_xlfn.IFNA(_xlfn.XLOOKUP(J16,Table1[Property Number],Table1[Qty | PCount]),"-") -> - | C16: =_xlfn.IFNA(_xlfn.XLOOKUP(J16,Table1[Property Number],Table1[Unit of Measure]),"-") -> - | E16: =_xlfn.IFNA(_xlfn.XLOOKUP(J16,Table1[Property Number],Table1[Unit Value]),"-") -> - | F16: =IFERROR(B16*E16,0) -> 0 | I16: =_xlfn.IFNA(CONCATENATE(_xlfn.XLOOKUP(J16,Table1[Property Number], Table1[Full Specifications])," - Acquisition Date: ",TEXT(_xlfn.XLOOKUP(J16,Table1[Property Number], Table1[Date of Acquisition]),"mmmm dd, yyyy")),"-") -> - | J16: =N16 -> 0 | K16: =IF(N16="","-","2 Years") -> -
B17: =_xlfn.IFNA(_xlfn.XLOOKUP(J17,Table1[Property Number],Table1[Qty | PCount]),"-") -> - | C17: =_xlfn.IFNA(_xlfn.XLOOKUP(J17,Table1[Property Number],Table1[Unit of Measure]),"-") -> - | E17: =_xlfn.IFNA(_xlfn.XLOOKUP(J17,Table1[Property Number],Table1[Unit Value]),"-") -> - | F17: =IFERROR(B17*E17,0) -> 0 | I17: =_xlfn.IFNA(CONCATENATE(_xlfn.XLOOKUP(J17,Table1[Property Number], Table1[Full Specifications])," - Acquisition Date: ",TEXT(_xlfn.XLOOKUP(J17,Table1[Property Number], Table1[Date of Acquisition]),"mmmm dd, yyyy")),"-") -> - | J17: =N17 -> 0 | K17: =IF(N17="","-","2 Years") -> -
B18: =_xlfn.IFNA(_xlfn.XLOOKUP(J18,Table1[Property Number],Table1[Qty | PCount]),"-") -> - | C18: =_xlfn.IFNA(_xlfn.XLOOKUP(J18,Table1[Property Number],Table1[Unit of Measure]),"-") -> - | E18: =_xlfn.IFNA(_xlfn.XLOOKUP(J18,Table1[Property Number],Table1[Unit Value]),"-") -> - | F18: =IFERROR(B18*E18,0) -> 0 | I18: =_xlfn.IFNA(CONCATENATE(_xlfn.XLOOKUP(J18,Table1[Property Number], Table1[Full Specifications])," - Acquisition Date: ",TEXT(_xlfn.XLOOKUP(J18,Table1[Property Number], Table1[Date of Acquisition]),"mmmm dd, yyyy")),"-") -> - | J18: =N18 -> 0 | K18: =IF(N18="","-","2 Years") -> -
B19: =_xlfn.IFNA(_xlfn.XLOOKUP(J19,Table1[Property Number],Table1[Qty | PCount]),"-") -> - | C19: =_xlfn.IFNA(_xlfn.XLOOKUP(J19,Table1[Property Number],Table1[Unit of Measure]),"-") -> - | E19: =_xlfn.IFNA(_xlfn.XLOOKUP(J19,Table1[Property Number],Table1[Unit Value]),"-") -> - | F19: =IFERROR(B19*E19,0) -> 0 | I19: =_xlfn.IFNA(CONCATENATE(_xlfn.XLOOKUP(J19,Table1[Property Number], Table1[Full Specifications])," - Acquisition Date: ",TEXT(_xlfn.XLOOKUP(J19,Table1[Property Number], Table1[Date of Acquisition]),"mmmm dd, yyyy")),"-") -> - | J19: =N19 -> 0 | K19: =IF(N19="","-","2 Years") -> -
B20: =_xlfn.IFNA(_xlfn.XLOOKUP(J20,Table1[Property Number],Table1[Qty | PCount]),"-") -> - | C20: =_xlfn.IFNA(_xlfn.XLOOKUP(J20,Table1[Property Number],Table1[Unit of Measure]),"-") -> - | E20: =_xlfn.IFNA(_xlfn.XLOOKUP(J20,Table1[Property Number],Table1[Unit Value]),"-") -> - | F20: =IFERROR(B20*E20,0) -> 0 | I20: =_xlfn.IFNA(CONCATENATE(_xlfn.XLOOKUP(J20,Table1[Property Number], Table1[Full Specifications])," - Acquisition Date: ",TEXT(_xlfn.XLOOKUP(J20,Table1[Property Number], Table1[Date of Acquisition]),"mmmm dd, yyyy")),"-") -> - | J20: =N20 -> 0 | K20: =IF(N20="","-","2 Years") -> -
B21: =_xlfn.IFNA(_xlfn.XLOOKUP(J21,Table1[Property Number],Table1[Qty | PCount]),"-") -> - | C21: =_xlfn.IFNA(_xlfn.XLOOKUP(J21,Table1[Property Number],Table1[Unit of Measure]),"-") -> - | E21: =_xlfn.IFNA(_xlfn.XLOOKUP(J21,Table1[Property Number],Table1[Unit Value]),"-") -> - | F21: =IFERROR(B21*E21,0) -> 0 | I21: =_xlfn.IFNA(CONCATENATE(_xlfn.XLOOKUP(J21,Table1[Property Number], Table1[Full Specifications])," - Acquisition Date: ",TEXT(_xlfn.XLOOKUP(J21,Table1[Property Number], Table1[Date of Acquisition]),"mmmm dd, yyyy")),"-") -> - | J21: =N21 -> 0 | K21: =IF(N21="","-","2 Years") -> -
E96: Total | F96: =IFERROR(SUM(F10:F95),"-") -> 42167.91
B108: Received from: | I108: Received by:
B110: KARL MANUEL O. CORDORA | I110: =UPPER(P110) -> CHRISABELLE C. QUEBEC | P110: =_xlfn.XLOOKUP(J5,Table1[ICS Number],Table1[Accountable Person]) -> Chrisabelle C. Quebec
B111: Signature Over Printed Name | I111: Signature Over Printed Name
B112: Administrative Officer IV | I112: =_xlfn.XLOOKUP(J5,Table1[ICS Number],Table1[Position]) -> Technical Assistant I - SBFP / WINS
B113: Position | Designation | I113: Position | Designation
B114: =TODAY() -> 46058 | I114: =B114 -> 46058
B115: Date | I115: Date
I116: =_xlfn.XLOOKUP($J$5,Table1[ICS Number],Table1[Location]) -> 003B - School Health and Nutrition Unit

Sheet Sticker
B3: ICS No. | C3: Property No. | D3: Asset Classification | E3: Item | Brand | Model | F3: Serial No. | G3: Acquisition Cost | H3: Acquisition Date | I3: Issuance Date | J3: Location | K3: Accountable Person | L3: Fund Source
B4: =List!A2 -> ICS2026 - 01 - 0104 | C4: =List!D2 -> SPHV - 2022 - 05 - 03 - 0046 - 03B | D4: =List!C2 -> ICT Equipment | E4: =CONCATENATE(List!E2," - ",List!F2," - ",List!G2) -> Laptop - COBY - NBPC 2168 | F4: =List!H2 -> RDPBMNBPC2168202201001528 | G4: =List!O2 -> 42167.91 | H4: =List!V2 -> 44799 | I4: =TODAY() -> 46058 | J4: =List!W2 -> 003B - School Health and Nutrition Unit | K4: =List!X2 -> Chrisabelle C. Quebec | L4: =List!Z2 -> Central Office
B5: =List!A3 -> 0 | C5: =List!D3 -> 0 | D5: =List!C3 -> 0 | E5: =CONCATENATE(List!E3," - ",List!F3," - ",List!G3) -> - - | F5: =List!H3 -> 0 | G5: =List!O3 -> 0 | H5: =List!V3 -> 0 | I5: =TODAY() -> 46058 | J5: =List!W3 -> 0 | K5: =List!X3 -> 0 | L5: =List!Z3 -> 0
B6: =List!A4 -> 0 | C6: =List!D4 -> 0 | D6: =List!C4 -> 0 | E6: =CONCATENATE(List!E4," - ",List!F4," - ",List!G4) -> - - | F6: =List!H4 -> 0 | G6: =List!O4 -> 0 | H6: =List!V4 -> 0 | I6: =TODAY() -> 46058 | J6: =List!W4 -> 0 | K6: =List!X4 -> 0 | L6: =List!Z4 -> 0
B7: =List!A5 -> 0 | C7: =List!D5 -> 0 | D7: =List!C5 -> 0 | E7: =CONCATENATE(List!E5," - ",List!F5," - ",List!G5) -> - - | F7: =List!H5 -> 0 | G7: =List!O5 -> 0 | H7: =List!V5 -> 0 | I7: =TODAY() -> 46058 | J7: =List!W5 -> 0 | K7: =List!X5 -> 0 | L7: =List!Z5 -> 0
B8: =List!A6 -> 0 | C8: =List!D6 -> 0 | D8: =List!C6 -> 0 | E8: =CONCATENATE(List!E6," - ",List!F6," - ",List!G6) -> - - | F8: =List!H6 -> 0 | G8: =List!O6 -> 0 | H8: =List!V6 -> 0 | I8: =TODAY() -> 46058 | J8: =List!W6 -> 0 | K8: =List!X6 -> 0 | L8: =List!Z6 -> 0
B9: =List!A7 -> 0 | C9: =List!D7 -> 0 | D9: =List!C7 -> 0 | E9: =CONCATENATE(List!E7," - ",List!F7," - ",List!G7) -> - - | F9: =List!H7 -> 0 | G9: =List!O7 -> 0 | H9: =List!V7 -> 0 | I9: =TODAY() -> 46058 | J9: =List!W7 -> 0 | K9: =List!X7 -> 0 | L9: =List!Z7 -> 0
B10: =List!A8 -> 0 | C10: =List!D8 -> 0 | D10: =List!C8 -> 0 | E10: =CONCATENATE(List!E8," - ",List!F8," - ",List!G8) -> - - | F10: =List!H8 -> 0 | G10: =List!O8 -> 0 | H10: =List!V8 -> 0 | I10: =TODAY() -> 46058 | J10: =List!W8 -> 0 | K10: =List!X8 -> 0 | L10: =List!Z8 -> 0
B11: =List!A9 -> 0 | C11: =List!D9 -> 0 | D11: =List!C9 -> 0 | E11: =CONCATENATE(List!E9," - ",List!F9," - ",List!G9) -> - - | F11: =List!H9 -> 0 | G11: =List!O9 -> 0 | H11: =List!V9 -> 0 | I11: =TODAY() -> 46058 | J11: =List!W9 -> 0 | K11: =List!X9 -> 0 | L11: =List!Z9 -> 0
B12: =List!A10 -> 0 | C12: =List!D10 -> 0 | D12: =List!C10 -> 0 | E12: =CONCATENATE(List!E10," - ",List!F10," - ",List!G10) -> - - | F12: =List!H10 -> 0 | G12: =List!O10 -> 0 | H12: =List!V10 -> 0 | I12: =TODAY() -> 46058 | J12: =List!W10 -> 0 | K12: =List!X10 -> 0 | L12: =List!Z10 -> 0
B13: =List!A11 -> 0 | C13: =List!D11 -> 0 | D13: =List!C11 -> 0 | E13: =CONCATENATE(List!E11," - ",List!F11," - ",List!G11) -> - - | F13: =List!H11 -> 0 | G13: =List!O11 -> 0 | H13: =List!V11 -> 0 | I13: =TODAY() -> 46058 | J13: =List!W11 -> 0 | K13: =List!X11 -> 0 | L13: =List!Z11 -> 0
B14: =List!A12 -> 0 | C14: =List!D12 -> 0 | D14: =List!C12 -> 0 | E14: =CONCATENATE(List!E12," - ",List!F12," - ",List!G12) -> - - | F14: =List!H12 -> 0 | G14: =List!O12 -> 0 | H14: =List!V12 -> 0 | I14: =TODAY() -> 46058 | J14: =List!W12 -> 0 | K14: =List!X12 -> 0 | L14: =List!Z12 -> 0
B15: =List!A13 -> 0 | C15: =List!D13 -> 0 | D15: =List!C13 -> 0 | E15: =CONCATENATE(List!E13," - ",List!F13," - ",List!G13) -> - - | F15: =List!H13 -> 0 | G15: =List!O13 -> 0 | H15: =List!V13 -> 0 | I15: =TODAY() -> 46058 | J15: =List!W13 -> 0 | K15: =List!X13 -> 0 | L15: =List!Z13 -> 0
... B24: =List!A22 -> 0 | C24: =List!D22 -> 0 | D24: =List!C22 -> 0 | E24: =CONCATENATE(List!E22," - ",List!F22," - ",List!G22) -> - - | F24: =List!H22 -> 0 | G24: =List!O22 -> 0 | H24: =List!V22 -> 0 | I24: =TODAY() -> 46058 | J24: =List!W22 -> 0 | K24: =List!X22 -> 0 | L24: =List!Z22 -> 0

Sheet Q1
B2: Republic of the Philippines
B3: Department of Education
B4: Region IV - A CALABARZON
B5: SCHOOLS DIVISION OFFICE OF CAVITE CITY
B6: City of Cavite
I7: 44648
I8: Date
B9: Business Name: | C9: PANDAYAN BOOKSHOP, INC.
B11: Dear Sir/Madam:
C13: Please quote your price for the purchase of
B14: listed hereunder to be used
B15: The supplies/materials will be delivered at the
B16: in accordance with the Advice of
A18: QUANTITY | C18: UNIT | E18: MATERIALS | PARTICULARS | I18: UNIT PRICE | J18: TOTAL
A19: =#REF! -> #REF! | C19: =#REF! -> #REF! | E19: =#REF! -> #REF! | I19: =#REF! -> #REF! | J19: =I19*A19 -> #REF!
A20: =#REF! -> #REF! | C20: =#REF! -> #REF! | E20: =#REF! -> #REF! | I20: =#REF! -> #REF! | J20: =I20*A20 -> #REF!
J21: =I21*A21 -> 0
J22: =I22*A22 -> 0
J23: =I23*A23 -> 0
J24: =I24*A24 -> 0
J25: =I25*A25 -> 0
J26: =I26*A26 -> 0
J27: =I27*A27 -> 0
J28: =I28*A28 -> 0
J29: =I29*A29 -> 0
J30: =I30*A30 -> 0
J31: =I31*A31 -> 0
J32: =I32*A32 -> 0
... J34: =I34*A34 -> 0
A57: Total: | J57: =SUM(J19:K56) -> #REF!
B60: JOSHUA AIRIS DE LEON | H60: KARL MANUEL O. CORDORA
B61: Signature over Printed Name | H61: Administrative Assistant III
H62: Designated Supply Officer

Sheet Q2
B2: Republic of the Philippines
B3: Department of Education
B4: Region IV - A CALABARZON
B5: SCHOOLS DIVISION OFFICE OF CAVITE CITY
B6: City of Cavite
I7: ='Q1'!I7 -> 44648
I8: Date
B9: Business Name: | C9: NETH'S EAT
B11: Dear Sir/Madam:
C13: Please quote your price for the purchase of | G13: ='Q1'!G13 -> 0
B14: listed hereunder to be used | D14: ='Q1'!D14 -> 0
B15: The supplies/materials will be delivered at the | F15: Schools Division Office of Cavite City
B16: in accordance with the Advice of
A18: QUANTITY | C18: UNIT | E18: MATERIALS | PARTICULARS | I18: UNIT PRICE | J18: TOTAL
A19: =#REF! -> #REF! | J19: =I19*A19 -> #REF!
J20: =I20*A20 -> 0
J21: =I21*A21 -> 0
J22: =I22*A22 -> 0
J23: =I23*A23 -> 0
J24: =I24*A24 -> 0
J25: =I25*A25 -> 0
J26: =I26*A26 -> 0
J27: =I27*A27 -> 0
J31: =I31*A31 -> 0
J32: =I32*A32 -> 0
J33: =I33*A33 -> 0
J34: =I34*A34 -> 0
A57: Total: | J57: =SUM(J19:K55) -> #REF!
B60: MARINEL S. DOMINGO | H60: KARL MANUEL O. CORDORA
B61: Signature over Printed Name | H61: Administrative Assistant III
H62: Designated Supply Officer

Sheet Q3
B2: Republic of the Philippines
B3: Department of Education
B4: Region IV - A CALABARZON
B5: SCHOOLS DIVISION OFFICE OF CAVITE CITY
B6: City of Cavite
I7: ='Q1'!I7 -> 44648
I8: Date
B9: Business Name: | C9: MACKY'S CATERING SERVICES
B11: Dear Sir/Madam:
C13: Please quote your price for the purchase of | G13: ='Q1'!G13 -> 0
B14: listed hereunder to be used | D14: ='Q1'!D14 -> 0
B15: The supplies/materials will be delivered at the | F15: Schools Division Office of Cavite City
B16: in accordance with the Advice of
A18: QUANTITY | C18: UNIT | E18: MATERIALS | PARTICULARS | I18: UNIT PRICE | J18: TOTAL
A19: =#REF! -> #REF! | J19: =I19*A19 -> #REF!
J20: =I20*A20 -> 0
J21: =I21*A21 -> 0
J22: =I22*A22 -> 0
J23: =I23*A23 -> 0
J24: =I24*A24 -> 0
J25: =I25*A25 -> 0
J26: =I26*A26 -> 0
J27: =I27*A27 -> 0
J28: =I28*A28 -> 0
J29: =I29*A29 -> 0
J30: =I30*A30 -> 0
J31: =I31*A31 -> 0
... J34: =I34*A34 -> 0
A57: Total: | J57: =SUM(J19:K55) -> #REF!
B60: MACKY SALIENDRA | H60: KARL MANUEL O. CORDORA
B61: Signature over Printed Name | H61: Administrative Assistant III
H62: Designated Supply Officer

Sheet PO
B2: PURCHASE ORDER
B3: DEPED CAVITE CITY
B4: Entity Name
B6: Supplier: | D6: COPYLANDIA OFFICE SYSTEMS CORPORATION | I6: PO No.: | J6: =#REF! -> #REF!
B7: Address: | D7: G/F SQH 1 Bldg., E. Aguinaldo Highway, Anabu 2F, Imus City | I7: Date: | J7: ='Q1'!I7 -> 44648
B8: TIN: | C8: 008-387-425-000 | I8: Mode of Procurement:
B10: Gentlemen: | F10: Please furnish this Office the following articles subject to the terms and conditions contained herein:
B14: Place of Delivery: | F14: Schools Division Office of Cavite City | I14: Delivery Term:
B15: Date of Delivery: | I15: Payment Term:
A17: Stock | Property No. | E17: Unit | G17: Description | I17: Qty | K17: Unit Cost | M17: Amount
E18: ='Q1'!C19 -> #REF! | G18: ='Q1'!E19 -> #REF! | I18: ='Q1'!A19 -> #REF! | K18: ='Q1'!I19 -> #REF! | M18: =I18*K18 -> #REF!
E19: ='Q1'!C20 -> #REF! | G19: ='Q1'!E20 -> #REF! | I19: ='Q1'!A20 -> #REF! | K19: ='Q1'!I20 -> #REF! | M19: =I19*K19 -> #REF!
K20: ='Q1'!I21 -> 0 | M20: =I20*K20 -> 0
K21: ='Q1'!I22 -> 0 | M21: =I21*K21 -> 0
K22: ='Q1'!I23 -> 0 | M22: =I22*K22 -> 0
K23: ='Q1'!I24 -> 0 | M23: =I23*K23 -> 0
K24: ='Q1'!I25 -> 0 | M24: =I24*K24 -> 0
K25: ='Q1'!I26 -> 0 | M25: =I25*K25 -> 0
K26: ='Q1'!I27 -> 0 | M26: =I26*K26 -> 0
K27: ='Q1'!I28 -> 0 | M27: =I27*K27 -> 0
K28: ='Q1'!I29 -> 0 | M28: =I28*K28 -> 0
K29: ='Q1'!I30 -> 0 | M29: =I29*K29 -> 0
K30: ='Q1'!I31 -> 0 | M30: =I30*K30 -> 0
K31: ='Q1'!I32 -> 0 | M31: =I31*K31 -> 0
... K33: ='Q1'!I34 -> 0 | M33: =I33*K33 -> 0
A44: Total: | M44: =SUM(M18:N43) -> #REF!
B45: (Total Amount in Words) | H45: Six Thousand Pesos
B47: In case of failure to make the full delivery within the time specified above, a penalty of one-tenth (1/10) of one percent for every day of delay shall be imposed on the undelivered item/s.
B50: Conforme: | I50: Very truly yours,
B52: JOSHUA AIRIS DE LEON | I52: EDGARDO B. MILITANTE
B53: Signature over Printed Name of Supplier | Representative | I53: Signature over Printed Name of Authorized Official
B54: ________________________________________ | I54: OIC, Schools Division Superintendent
B55: Date | I55: Designation
B57: Fund Cluster: | I57: ORS | BURS No.:
B58: Funds Available: | I58: Date of ORS | BURS:
I60: Amount: | K60: =M44 -> #REF!
A61: MICHELLE L. MATA
A62: Signature over Printed Name of Chief
A63: Accountant/Head of Accounting Division/Unit
